Workbook
Name PMIS_Building_Helper: [1]_PMIS_Helper!$A$1:$N$31
Name PMIS_Building_List: 'PMIS_Data (2)'!$A$3:$A$32
Name PMIS_Building_List: [8]PMIS_Data!$A$3:$A$32
Name PMIS_Building_List: PMIS_Data!$A$3:$A$32
Name PMIS_Config_Navigation: _PMIS_Config!$A$18:$C$24
Name PMIS_Config_Theme: _PMIS_Config!$A$4:$D$10
Name PMIS_Config_Thresholds: _PMIS_Config!$A$12:$D$16
Name PMIS_Open_Questions: 'PMIS_Data (2)'!$I$3:$I$32
Name PMIS_Open_Questions: PMIS_Data!$I$3:$I$32
Name PMIS_Open_Risks: 'PMIS_Data (2)'!$H$3:$H$32
Name PMIS_Open_Risks: PMIS_Data!$H$3:$H$32
Name PMIS_Readiness: 'PMIS_Data (2)'!$D$3:$D$32
Name PMIS_Readiness: PMIS_Data!$D$3:$D$32
Name PMIS_Shutdowns: 'PMIS_Data (2)'!$Q$3:$Q$32
Name PMIS_Shutdowns: PMIS_Data!$Q$3:$Q$32
Name V4_Action_Queue: _V4_ActionQueue!$A$3:$O$200
Name V4_Active_Building: V4_Mission_Control!$C$3
Name V4_BuildingHelper: [2]_V4_Helper!$A$3:$N$34
Name V4_Config_Source: [3]_V4_Config!$A$1:$G$23
Name V4_ConfigTokens: [3]_V4_Config!$A$4:$G$23
Name V4_PriorityQueue: V4_Mission_Control!$A$10:$L$34

Sheet PMIS_Config
A1: BEDFORD VA EHRM PMIS — CONFIG / BUILDING MAP | J1: Selector IDs
A2: Purpose | B2: Central building list used for selectors, validation, QA, and future dashboard mapping. Edit only if buildings/sheet names change. | J2: =PMIS_Data!A3 -> 01 | K2: =PMIS_Data!B3 -> B01_Assessment
J3: =PMIS_Data!A4 -> 02 | K3: =PMIS_Data!B4 -> B02_Assessment
A4: Display Building | B4: Assessment Sheet | C4: PMIS_Data Row | D4: Open Assessment Link | E4: Has Sheet? | F4: Has PMIS Row? | G4: Has Trade Notes? | H4: Notes | J4: =PMIS_Data!A5 -> 03 | K4: =PMIS_Data!B5 -> B03_Assessment
A5: B01 | B5: B01_Assessment | C5: 3 | D5: =HYPERLINK("#'B01_Assessment'!A1","Open") -> Open | E5: =IF(ISREF(INDIRECT("'"&B5&"'!A1")),"Yes","No") -> Yes | F5: =IF(COUNTIF(PMIS_Data!$B:$B,B5)>0,"Yes","Check") -> Yes | G5: =IF(COUNTIF(PMIS_Trade_Notes!$C:$C,B5)>0,"Yes","Check") -> Yes | J5: =PMIS_Data!A6 -> 04 | K5: =PMIS_Data!B6 -> B04_Assessment
A6: B02 | B6: B02_Assessment | C6: 4 | D6: =HYPERLINK("#'B02_Assessment'!A1","Open") -> Open | E6: =IF(ISREF(INDIRECT("'"&B6&"'!A1")),"Yes","No") -> Yes | F6: =IF(COUNTIF(PMIS_Data!$B:$B,B6)>0,"Yes","Check") -> Yes | G6: =IF(COUNTIF(PMIS_Trade_Notes!$C:$C,B6)>0,"Yes","Check") -> Yes | J6: =PMIS_Data!A7 -> 05 | K6: =PMIS_Data!B7 -> B05_Assessment
A7: B03 | B7: B03_Assessment | C7: 5 | D7: =HYPERLINK("#'B03_Assessment'!A1","Open") -> Open | E7: =IF(ISREF(INDIRECT("'"&B7&"'!A1")),"Yes","No") -> Yes | F7: =IF(COUNTIF(PMIS_Data!$B:$B,B7)>0,"Yes","Check") -> Yes | G7: =IF(COUNTIF(PMIS_Trade_Notes!$C:$C,B7)>0,"Yes","Check") -> Yes | J7: =PMIS_Data!A8 -> 06 | K7: =PMIS_Data!B8 -> B06_Assessment
A8: B04 | B8: B04_Assessment | C8: 6 | D8: =HYPERLINK("#'B04_Assessment'!A1","Open") -> Open | E8: =IF(ISREF(INDIRECT("'"&B8&"'!A1")),"Yes","No") -> Yes | F8: =IF(COUNTIF(PMIS_Data!$B:$B,B8)>0,"Yes","Check") -> Yes | G8: =IF(COUNTIF(PMIS_Trade_Notes!$C:$C,B8)>0,"Yes","Check") -> Yes | J8: =PMIS_Data!A9 -> 07 | K8: =PMIS_Data!B9 -> B07_Assessment
A9: B05 | B9: B05_Assessment | C9: 7 | D9: =HYPERLINK("#'B05_Assessment'!A1","Open") -> Open | E9: =IF(ISREF(INDIRECT("'"&B9&"'!A1")),"Yes","No") -> Yes | F9: =IF(COUNTIF(PMIS_Data!$B:$B,B9)>0,"Yes","Check") -> Yes | G9: =IF(COUNTIF(PMIS_Trade_Notes!$C:$C,B9)>0,"Yes","Check") -> Yes | J9: =PMIS_Data!A10 -> 08 | K9: =PMIS_Data!B10 -> B08_Assessment
A10: B06 | B10: B06_Assessment | C10: 8 | D10: =HYPERLINK("#'B06_Assessment'!A1","Open") -> Open | E10: =IF(ISREF(INDIRECT("'"&B10&"'!A1")),"Yes","No") -> Yes | F10: =IF(COUNTIF(PMIS_Data!$B:$B,B10)>0,"Yes","Check") -> Yes | G10: =IF(COUNTIF(PMIS_Trade_Notes!$C:$C,B10)>0,"Yes","Check") -> Yes | J10: =PMIS_Data!A11 -> 09 | K10: =PMIS_Data!B11 -> B09_Assessment
A11: B07 | B11: B07_Assessment | C11: 9 | D11: =HYPERLINK("#'B07_Assessment'!A1","Open") -> Open | E11: =IF(ISREF(INDIRECT("'"&B11&"'!A1")),"Yes","No") -> Yes | F11: =IF(COUNTIF(PMIS_Data!$B:$B,B11)>0,"Yes","Check") -> Yes | G11: =IF(COUNTIF(PMIS_Trade_Notes!$C:$C,B11)>0,"Yes","Check") -> Yes | J11: =PMIS_Data!A12 -> 10 | K11: =PMIS_Data!B12 -> B10_Assessment
A12: B08 | B12: B08_Assessment | C12: 10 | D12: =HYPERLINK("#'B08_Assessment'!A1","Open") -> Open | E12: =IF(ISREF(INDIRECT("'"&B12&"'!A1")),"Yes","No") -> Yes | F12: =IF(COUNTIF(PMIS_Data!$B:$B,B12)>0,"Yes","Check") -> Yes | G12: =IF(COUNTIF(PMIS_Trade_Notes!$C:$C,B12)>0,"Yes","Check") -> Yes | J12: =PMIS_Data!A13 -> 12 | K12: =PMIS_Data!B13 -> B12_Assessment
A13: B09 | B13: B09_Assessment | C13: 11 | D13: =HYPERLINK("#'B09_Assessment'!A1","Open") -> Open | E13: =IF(ISREF(INDIRECT("'"&B13&"'!A1")),"Yes","No") -> Yes | F13: =IF(COUNTIF(PMIS_Data!$B:$B,B13)>0,"Yes","Check") -> Yes | G13: =IF(COUNTIF(PMIS_Trade_Notes!$C:$C,B13)>0,"Yes","Check") -> Yes | J13: =PMIS_Data!A14 -> 13 | K13: =PMIS_Data!B14 -> B13_Assessment
A14: B10 | B14: B10_Assessment | C14: 12 | D14: =HYPERLINK("#'B10_Assessment'!A1","Open") -> Open | E14: =IF(ISREF(INDIRECT("'"&B14&"'!A1")),"Yes","No") -> Yes | F14: =IF(COUNTIF(PMIS_Data!$B:$B,B14)>0,"Yes","Check") -> Yes | G14: =IF(COUNTIF(PMIS_Trade_Notes!$C:$C,B14)>0,"Yes","Check") -> Yes | J14: =PMIS_Data!A15 -> 14 | K14: =PMIS_Data!B15 -> B14_Assessment
A15: B12 | B15: B12_Assessment | C15: 13 | D15: =HYPERLINK("#'B12_Assessment'!A1","Open") -> Open | E15: =IF(ISREF(INDIRECT("'"&B15&"'!A1")),"Yes","No") -> Yes | F15: =IF(COUNTIF(PMIS_Data!$B:$B,B15)>0,"Yes","Check") -> Yes | G15: =IF(COUNTIF(PMIS_Trade_Notes!$C:$C,B15)>0,"Yes","Check") -> Yes | J15: =PMIS_Data!A16 -> 15 | K15: =PMIS_Data!B16 -> B15_Assessment
A16: B13 | B16: B13_Assessment | C16: 14 | D16: =HYPERLINK("#'B13_Assessment'!A1","Open") -> Open | E16: =IF(ISREF(INDIRECT("'"&B16&"'!A1")),"Yes","No") -> Yes | F16: =IF(COUNTIF(PMIS_Data!$B:$B,B16)>0,"Yes","Check") -> Yes | G16: =IF(COUNTIF(PMIS_Trade_Notes!$C:$C,B16)>0,"Yes","Check") -> Yes | J16: =PMIS_Data!A17 -> 16 | K16: =PMIS_Data!B17 -> B16_Assessment
A17: B14 | B17: B14_Assessment | C17: 15 | D17: =HYPERLINK("#'B14_Assessment'!A1","Open") -> Open | E17: =IF(ISREF(INDIRECT("'"&B17&"'!A1")),"Yes","No") -> Yes | F17: =IF(COUNTIF(PMIS_Data!$B:$B,B17)>0,"Yes","Check") -> Yes | G17: =IF(COUNTIF(PMIS_Trade_Notes!$C:$C,B17)>0,"Yes","Check") -> Yes | J17: =PMIS_Data!A18 -> 17 | K17: =PMIS_Data!B18 -> B17_Assessment
A18: B15 | B18: B15_Assessment | C18: 16 | D18: =HYPERLINK("#'B15_Assessment'!A1","Open") -> Open | E18: =IF(ISREF(INDIRECT("'"&B18&"'!A1")),"Yes","No") -> Yes | F18: =IF(COUNTIF(PMIS_Data!$B:$B,B18)>0,"Yes","Check") -> Yes | G18: =IF(COUNTIF(PMIS_Trade_Notes!$C:$C,B18)>0,"Yes","Check") -> Yes | J18: =PMIS_Data!A19 -> 18 | K18: =PMIS_Data!B19 -> B18_Assessment
A19: B16 | B19: B16_Assessment | C19: 17 | D19: =HYPERLINK("#'B16_Assessment'!A1","Open") -> Open | E19: =IF(ISREF(INDIRECT("'"&B19&"'!A1")),"Yes","No") -> Yes | F19: =IF(COUNTIF(PMIS_Data!$B:$B,B19)>0,"Yes","Check") -> Yes | G19: =IF(COUNTIF(PMIS_Trade_Notes!$C:$C,B19)>0,"Yes","Check") -> Yes | J19: =PMIS_Data!A20 -> 20 | K19: =PMIS_Data!B20 -> B20_Assessment
A20: B17 | B20: B17_Assessment | C20: 18 | D20: =HYPERLINK("#'B17_Assessment'!A1","Open") -> Open | E20: =IF(ISREF(INDIRECT("'"&B20&"'!A1")),"Yes","No") -> Yes | F20: =IF(COUNTIF(PMIS_Data!$B:$B,B20)>0,"Yes","Check") -> Yes | G20: =IF(COUNTIF(PMIS_Trade_Notes!$C:$C,B20)>0,"Yes","Check") -> Yes | J20: =PMIS_Data!A21 -> 21 | K20: =PMIS_Data!B21 -> B21_Assessment
A21: B18 | B21: B18_Assessment | C21: 19 | D21: =HYPERLINK("#'B18_Assessment'!A1","Open") -> Open | E21: =IF(ISREF(INDIRECT("'"&B21&"'!A1")),"Yes","No") -> Yes | F21: =IF(COUNTIF(PMIS_Data!$B:$B,B21)>0,"Yes","Check") -> Yes | G21: =IF(COUNTIF(PMIS_Trade_Notes!$C:$C,B21)>0,"Yes","Check") -> Yes | J21: =PMIS_Data!A22 -> 22 | K21: =PMIS_Data!B22 -> B22_Assessment
A22: B20 | B22: B20_Assessment | C22: 20 | D22: =HYPERLINK("#'B20_Assessment'!A1","Open") -> Open | E22: =IF(ISREF(INDIRECT("'"&B22&"'!A1")),"Yes","No") -> Yes | F22: =IF(COUNTIF(PMIS_Data!$B:$B,B22)>0,"Yes","Check") -> Yes | G22: =IF(COUNTIF(PMIS_Trade_Notes!$C:$C,B22)>0,"Yes","Check") -> Yes | J22: =PMIS_Data!A23 -> 33 | K22: =PMIS_Data!B23 -> B33_Assessment
A23: B21 | B23: B21_Assessment | C23: 21 | D23: =HYPERLINK("#'B21_Assessment'!A1","Open") -> Open | E23: =IF(ISREF(INDIRECT("'"&B23&"'!A1")),"Yes","No") -> Yes | F23: =IF(COUNTIF(PMIS_Data!$B:$B,B23)>0,"Yes","Check") -> Yes | G23: =IF(COUNTIF(PMIS_Trade_Notes!$C:$C,B23)>0,"Yes","Check") -> Yes | J23: =PMIS_Data!A24 -> 61 | K23: =PMIS_Data!B24 -> B61_Assessment
A24: B22 | B24: B22_Assessment | C24: 22 | D24: =HYPERLINK("#'B22_Assessment'!A1","Open") -> Open | E24: =IF(ISREF(INDIRECT("'"&B24&"'!A1")),"Yes","No") -> Yes | F24: =IF(COUNTIF(PMIS_Data!$B:$B,B24)>0,"Yes","Check") -> Yes | G24: =IF(COUNTIF(PMIS_Trade_Notes!$C:$C,B24)>0,"Yes","Check") -> Yes | J24: =PMIS_Data!A25 -> 62 | K24: =PMIS_Data!B25 -> B62_TR_Assessment
A25: B33 | B25: B33_Assessment | C25: 23 | D25: =HYPERLINK("#'B33_Assessment'!A1","Open") -> Open | E25: =IF(ISREF(INDIRECT("'"&B25&"'!A1")),"Yes","No") -> Yes | F25: =IF(COUNTIF(PMIS_Data!$B:$B,B25)>0,"Yes","Check") -> Yes | G25: =IF(COUNTIF(PMIS_Trade_Notes!$C:$C,B25)>0,"Yes","Check") -> Yes | J25: =PMIS_Data!A26 -> 70 | K25: =PMIS_Data!B26 -> B70_TR_Assessment
A26: B61 | B26: B61_Assessment | C26: 24 | D26: =HYPERLINK("#'B61_Assessment'!A1","Open") -> Open | E26: =IF(ISREF(INDIRECT("'"&B26&"'!A1")),"Yes","No") -> Yes | F26: =IF(COUNTIF(PMIS_Data!$B:$B,B26)>0,"Yes","Check") -> Yes | G26: =IF(COUNTIF(PMIS_Trade_Notes!$C:$C,B26)>0,"Yes","Check") -> Yes | J26: =PMIS_Data!A27 -> 78 | K26: =PMIS_Data!B27 -> B78_Assessment
A27: B62 | B27: B62_TR_Assessment | C27: 25 | D27: =HYPERLINK("#'B62_TR_Assessment'!A1","Open") -> Open | E27: =IF(ISREF(INDIRECT("'"&B27&"'!A1")),"Yes","No") -> Yes | F27: =IF(COUNTIF(PMIS_Data!$B:$B,B27)>0,"Yes","Check") -> Yes | G27: =IF(COUNTIF(PMIS_Trade_Notes!$C:$C,B27)>0,"Yes","Check") -> Yes | J27: =PMIS_Data!A28 -> 80 | K27: =PMIS_Data!B28 -> B80_Assessment
A28: B70 | B28: B70_TR_Assessment | C28: 26 | D28: =HYPERLINK("#'B70_TR_Assessment'!A1","Open") -> Open | E28: =IF(ISREF(INDIRECT("'"&B28&"'!A1")),"Yes","No") -> Yes | F28: =IF(COUNTIF(PMIS_Data!$B:$B,B28)>0,"Yes","Check") -> Yes | G28: =IF(COUNTIF(PMIS_Trade_Notes!$C:$C,B28)>0,"Yes","Check") -> Yes | J28: =PMIS_Data!A29 -> 82 | K28: =PMIS_Data!B29 -> B82_Assessment
A29: B78 | B29: B78_Assessment | C29: 27 | D29: =HYPERLINK("#'B78_Assessment'!A1","Open") -> Open | E29: =IF(ISREF(INDIRECT("'"&B29&"'!A1")),"Yes","No") -> Yes | F29: =IF(COUNTIF(PMIS_Data!$B:$B,B29)>0,"Yes","Check") -> Yes | G29: =IF(COUNTIF(PMIS_Trade_Notes!$C:$C,B29)>0,"Yes","Check") -> Yes | J29: =PMIS_Data!A30 -> BCH | K29: =PMIS_Data!B30 -> BCH_Assessment
A30: B80 | B30: B80_Assessment | C30: 28 | D30: =HYPERLINK("#'B80_Assessment'!A1","Open") -> Open | E30: =IF(ISREF(INDIRECT("'"&B30&"'!A1")),"Yes","No") -> Yes | F30: =IF(COUNTIF(PMIS_Data!$B:$B,B30)>0,"Yes","Check") -> Yes | G30: =IF(COUNTIF(PMIS_Trade_Notes!$C:$C,B30)>0,"Yes","Check") -> Yes | J30: =PMIS_Data!A31 -> MCR | K30: =PMIS_Data!B31 -> MCR_Assessment
A31: 82B | B31: B82_Assessment | C31: 29 | D31: =HYPERLINK("#'B82_Assessment'!A1","Open") -> Open | E31: =IF(ISREF(INDIRECT("'"&B31&"'!A1")),"Yes","No") -> Yes | F31: =IF(COUNTIF(PMIS_Data!$B:$B,B31)>0,"Yes","Check") -> Yes | G31: =IF(COUNTIF(PMIS_Trade_Notes!$C:$C,B31)>0,"Yes","Check") -> Yes | J31: =PMIS_Data!A32 -> SITE | K31: =PMIS_Data!B32 -> SITE_Assesment
A32: CH | B32: BCH_Assessment | C32: 30 | D32: =HYPERLINK("#'BCH_Assessment'!A1","Open") -> Open | E32: =IF(ISREF(INDIRECT("'"&B32&"'!A1")),"Yes","No") -> Yes | F32: =IF(COUNTIF(PMIS_Data!$B:$B,B32)>0,"Yes","Check") -> Yes | G32: =IF(COUNTIF(PMIS_Trade_Notes!$C:$C,B32)>0,"Yes","Check") -> Yes
A33: MCR | B33: MCR_Assessment | C33: 31 | D33: =HYPERLINK("#'MCR_Assessment'!A1","Open") -> Open | E33: =IF(ISREF(INDIRECT("'"&B33&"'!A1")),"Yes","No") -> Yes | F33: =IF(COUNTIF(PMIS_Data!$B:$B,B33)>0,"Yes","Check") -> Yes | G33: =IF(COUNTIF(PMIS_Trade_Notes!$C:$C,B33)>0,"Yes","Check") -> Yes
A34: SITE | B34: SITE_Assesment | C34: 32 | D34: =HYPERLINK("#'SITE_Assesment'!A1","Open") -> Open | E34: =IF(ISREF(INDIRECT("'"&B34&"'!A1")),"Yes","No") -> Yes | F34: =IF(COUNTIF(PMIS_Data!$B:$B,B34)>0,"Yes","Check") -> Yes | G34: =IF(COUNTIF(PMIS_Trade_Notes!$C:$C,B34)>0,"Yes","Check") -> Yes

Sheet Data_Health
A1: BEDFORD VA EHRM PMIS — DATA HEALTH / RELEASE QA
A2: Purpose | B2: Quick confidence panel for workbook architecture, missing mappings, and dashboard data flow. Formulas recalculate when opened in Excel.
A4: Check | B4: Current Value | C4: Expected | D4: Status | E4: Notes
A5: Assessment sheets mapped | B5: =COUNTA(PMIS_Config!B5:B34) -> 30 | C5: =30 -> 30 | D5: =IF(B5>=C5,"OK","CHECK") -> OK | E5: Mapped source assessment sheets from PMIS_Config.
A6: PMIS_Data building rows | B6: =COUNTA(PMIS_Data!A3:A44) -> 30 | C6: =30 -> 30 | D6: =IF(B6>=C6,"OK","CHECK") -> OK | E6: One row per building / area in PMIS_Data.
A7: PMIS_Trade_Notes rows | B7: =COUNTA(PMIS_Trade_Notes!A2:A100) -> 33 | C7: =30 -> 30 | D7: =IF(B7>=C7,"OK","CHECK") -> OK | E7: One row per building / area in PMIS_Trade_Notes.
A8: Command Center selected building | B8: =Command_Center!C17 -> 61 | C8: Not blank | D8: =IF(B8<>"","OK","CHECK") -> OK | E8: Building selector drives Command Center cards.
A9: Command Center PMIS match row | B9: =Command_Center!Z2 -> 22 | C9: >=1 | D9: =IF(ISNUMBER(B9),"OK","CHECK") -> OK | E9: Helper row used to retrieve PMIS_Data values.
A10: Open risks total | B10: =SUM(PMIS_Data!H3:H44) -> 0 | C10: >=0 | D10: =IF(B10>=0,"OK","CHECK") -> OK | E10: Campus-wide open risks.
A11: Open questions total | B11: =SUM(PMIS_Data!I3:I44) -> 0 | C11: >=0 | D11: =IF(B11>=0,"OK","CHECK") -> OK | E11: Campus-wide open questions.
A12: Open photos total | B12: =SUM(PMIS_Data!J3:J44) -> 0 | C12: >=0 | D12: =IF(B12>=0,"OK","CHECK") -> OK | E12: Campus-wide open photos.
A13: Active shutdown total | B13: =SUM(PMIS_Data!X3:X44) -> 0 | C13: >=0 | D13: =IF(B13>=0,"OK","CHECK") -> OK | E13: Campus-wide shutdown indicators.
A14: Missing trade notes | B14: =COUNTIF(PMIS_Config!G5:G34,"Check") -> 0 | C14: 0 | D14: =IF(B14=0,"OK","CHECK") -> OK | E14: PMIS_Trade_Notes mapping check.
A15: Missing assessment sheets | B15: =COUNTIF(PMIS_Config!E5:E34,"No") -> 0 | C15: 0 | D15: =IF(B15=0,"OK","CHECK") -> OK | E15: Assessment sheet existence check.
A16: Today's Focus rows | B16: =COUNTA('Today''s_Focus'!A15:A44) -> 30 | C16: >=1 | D16: =IF(B16>=1,"OK","CHECK") -> OK | E16: Formula-fed worklist built from PMIS_Data.
A17: Top focus item | B17: ='Today''s_Focus'!B5 -> SITE | C17: Not blank | D17: =IF(B17<>"","OK","CHECK") -> OK | E17: Highest priority work item calculated from shutdowns, risks, questions, and readiness.
A18: Command Center quick link | B18: =Command_Center!S13 -> Today's Focus | C18: Visible | D18: =IFERROR(IF(B18<>"","OK","CHECK"),"OK") -> OK | E18: Command Center includes shortcut to Today's Focus.

Sheet README_ARCHITECTURE
A1: BEDFORD VA EHRM PMIS — ARCHITECTURE / USER GUIDE
A3: What this is | B3: A lightweight Project Management Information System for multidisciplinary facility assessments. The workbook is designed so building assessment sheets remain the source of truth while dashboards display the current operational picture.
A5: Core workflow | B5: 1. Update the building assessment sheet. 2. PMIS_Data rolls up metrics. 3. PMIS_Trade_Notes rolls up narrative/trade notes. 4. Command_Center displays the selected building. 5. V4_Mission_Control summarizes campus-wide health.
A7: Non-negotiable rules | B7: • Edit project data on Building Assessment sheets only. • Do not manually overwrite formulas in PMIS_Data. • Do not manually overwrite formulas in PMIS_Trade_Notes. • Use PMIS_Config when building names or sheet names change. • Use Data_Health to verify workbook readiness before reports or meetings.
A9: Primary user paths | B9: • COR / PM: start at V4_Mission_Control. • Field / QC / Engineer: start at Command_Center. • Data audit: start at Data_Health. • Mapping maintenance: start at PMIS_Config.
A11: Current architecture | B11: Building Assessment Sheets → PMIS_Data + PMIS_Trade_Notes → Command_Center / V4_Mission_Control / Reports.
A14: Today's Focus | B14: Formula-fed priority worklist ranking buildings by shutdowns, open risks, open questions, and readiness gaps. Use it as the morning planning screen. | C14: =HYPERLINK("#'Command_Center'!A1","Command Center") -> Command Center | D14: =HYPERLINK("#'PMIS_Data'!A1","PMIS_Data") -> PMIS_Data | E14: =HYPERLINK("#'PMIS_Trade_Notes'!A1","PMIS_Trade_Notes") -> PMIS_Trade_Notes | F14: =HYPERLINK("#'Data_Health'!A1","Data Health") -> Data Health | G14: =HYPERLINK("#'PMIS_Config'!A1","Config") -> Config

Sheet V4_Mission_Control
B1: BEDFORD VA EHRM PMIS MISSION CONTROL V5 | S1: Last refresh | T1: =NOW() -> 46220.364 | Z1: SelectedIndex | AA1: SelectedSheet | AB1: SelectedBuilding
B2: Mission Control rebuilt from live PMIS_Data + Building Assessment rollups. Select a building below; all cards update automatically. | Z2: =IFERROR(MATCH($C$7,PMIS_Data!$A$3:$A$32,0),1) -> 1 | AA2: =IFERROR(INDEX(PMIS_Data!$B$3:$B$32,$Z$2),"") -> B01_Assessment | AB2: =$C$7&"" -> 01
B3: OVERALL PROGRESS | D3: BUILDINGS ASSESSED | F3: OPEN RISKS | H3: OPEN QUESTIONS | J3: OPEN PHOTOS | L3: ACTIVE SHUTDOWNS | N3: NOT READY | P3: NEXT ACTION
B4: =IFERROR(AVERAGE(PMIS_Data!$E$3:$E$32),0) -> 0.50666667 | D4: =COUNTA(PMIS_Data!$A$3:$A$32) -> 30 | F4: =SUM(PMIS_Data!$H$3:$H$32) -> 0 | H4: =SUM(PMIS_Data!$I$3:$I$32) -> 0 | J4: =SUM(PMIS_Data!$J$3:$J$32) -> 0 | L4: =SUM(PMIS_Data!$X$3:$X$32) -> 0 | N4: =COUNTIF(PMIS_Data!$F$3:$F$32,"No") -> 29 | P4: =IFERROR(INDEX(_V4_ActionQueue!$F$4:$F$33,MATCH(1,_V4_ActionQueue!$A$4:$A$33,0)),"Monitor") -> READY BUILDING
B6: SELECT BUILDING | F6: MISSION STATUS | J6: PROGRESS OVERVIEW | N6: NEXT REQUIRED ACTION
B7: Building | C7: 01
F8: Selected Building Readiness | J8: Rooms | K8: =IFERROR(INDEX(PMIS_Data!$G$3:$G$94,$Z$2),0) -> 29 | L8: Fire Protection | M8: =IFERROR(INDEX(PMIS_Data!$N$3:$N$94,$Z$2),"") -> Not Started | N8: Action | P8: =IFERROR(INDEX(_V4_ActionQueue!$F$4:$F$33,MATCH($C$7,_V4_ActionQueue!$B$4:$B$33,0)),"Monitor") -> READY BUILDING
F9: =IFERROR(INDEX(PMIS_Data!$E$3:$E$94,$Z$2),0) -> 0.5
B10: Assessment Sheet | C10: =IFERROR(INDEX(PMIS_Data!$B$3:$B$94,$Z$2),"") -> B01_Assessment | J10: HVAC | K10: =IFERROR(INDEX(PMIS_Data!$K$3:$K$94,$Z$2),"") -> Not Started | L10: IT/Telecom | M10: =IFERROR(INDEX(PMIS_Data!$P$3:$P$94,$Z$2),"") -> Not Started
N11: Why | P11: =IFERROR(INDEX(_V4_ActionQueue!$G$4:$G$33,MATCH($C$7,_V4_ActionQueue!$B$4:$B$33,0)),"No exception detected") -> No major exception detected.
B12: Overall Status | C12: =IFERROR(INDEX(PMIS_Data!$C$3:$C$94,$Z$2),"") -> Yellow | F12: Decision | J12: Electrical | K12: =IFERROR(INDEX(PMIS_Data!$L$3:$L$94,$Z$2),"") -> Not Started
F13: =IFERROR(IF(INDEX(PMIS_Data!$F$3:$F$94,$Z$2)="Yes","Ready to proceed",IF(INDEX(PMIS_Data!$X$3:$X$94,$Z$2)>0,"Shutdown coordination required",IF(INDEX(PMIS_Data!$H$3:$H$94,$Z$2)>0,"Risk closure required",IF(INDEX(PMIS_Data!$I$3:$I$94,$Z$2)>0,"Open questions require answers","Continue assessment / monitoring")))),"Review needed") -> Continue assessment / monitoring
B14: Construction Ready | C14: =IFERROR(INDEX(PMIS_Data!$F$3:$F$94,$Z$2),"") -> No | J14: Telecom | K14: =IFERROR(INDEX(PMIS_Data!$M$3:$M$94,$Z$2),"") -> Not Started
N15: Next Step | P15: =IFERROR(INDEX(_V4_ActionQueue!$H$4:$H$33,MATCH($C$7,_V4_ActionQueue!$B$4:$B$33,0)),"Maintain monitoring") -> Maintain monitoring.
B16: =HYPERLINK("#'"&$AA$2&"'!A1","Open selected Building Assessment") -> Open selected Building Assessment | J16: Fire Alarm | K16: =IFERROR(INDEX(PMIS_Data!$O$3:$O$94,$Z$2),"") -> Not Started
B20: RISK SUMMARY | F20: OPEN QUESTIONS | J20: DOCUMENTS / PHOTOS | N20: SHUTDOWNS
B22: Open Risks | D22: =IFERROR(INDEX(PMIS_Data!$H$3:$H$94,$Z$2),0) -> 0 | F22: Selected Open | H22: =IFERROR(INDEX(PMIS_Data!$I$3:$I$94,$Z$2),0) -> 0 | J22: Open Photos | L22: =IFERROR(INDEX(PMIS_Data!$J$3:$J$94,$Z$2),0) -> 0 | N22: Selected Active | P22: =IFERROR(INDEX(PMIS_Data!$X$3:$X$94,$Z$2),0) -> 0
B24: Campus Open | D24: =SUM(PMIS_Data!$H$3:$H$32) -> 0 | F24: Campus Open | H24: =SUM(PMIS_Data!$I$3:$I$32) -> 0 | J24: Campus Docs | L24: =COUNTA(Doc_Register!$A$5:$A$300) -> 40 | N24: Campus Active | P24: =SUM(PMIS_Data!$X$3:$X$32) -> 0
B26: Selected Rank | D26: =IFERROR(INDEX(_V4_ActionQueue!$A$4:$A$33,MATCH($C$7,_V4_ActionQueue!$B$4:$B$33,0)),"") -> 1 | F26: High Priority | H26: =COUNTIFS(#REF!,"High",#REF!,"Open") -> #REF! | J26: Campus Photos | L26: =COUNTA(#REF!) -> 1 | N26: Not Ready | P26: =COUNTIF(PMIS_Data!$F$3:$F$32,"No") -> 29
B30: SELECTED BUILDING DETAIL — LIVE FROM PMIS_Data
B32: Building | C32: Sheet | D32: Status | E32: Readiness | F32: Ready | G32: Rooms | H32: Risks | I32: Questions | J32: Photos | K32: Shutdowns
B33: =$C$7&"" -> 01 | C33: =IFERROR(INDEX(PMIS_Data!$B$3:$B$94,$Z$2),"") -> B01_Assessment | D33: =IFERROR(INDEX(PMIS_Data!$C$3:$C$94,$Z$2),"") -> Yellow | E33: =IFERROR(INDEX(PMIS_Data!$E$3:$E$94,$Z$2),0) -> 0.5 | F33: =IFERROR(INDEX(PMIS_Data!$F$3:$F$94,$Z$2),"") -> No | G33: =IFERROR(INDEX(PMIS_Data!$G$3:$G$94,$Z$2),0) -> 29 | H33: =IFERROR(INDEX(PMIS_Data!$H$3:$H$94,$Z$2),0) -> 0 | I33: =IFERROR(INDEX(PMIS_Data!$I$3:$I$94,$Z$2),0) -> 0 | J33: =IFERROR(INDEX(PMIS_Data!$J$3:$J$94,$Z$2),0) -> 0 | K33: =IFERROR(INDEX(PMIS_Data!$X$3:$X$94,$Z$2),0) -> 0

Sheet Dashboard
A1: BEDFORD VA EHRM PROGRAM DASHBOARD | M1: =HYPERLINK("#'V4_Mission_Control'!A1","Mission") -> Mission | N1: =HYPERLINK("#'Command_Center'!A1","Command") -> Command | O1: =HYPERLINK("#'Building_View'!A1","Building") -> Building | P1: =HYPERLINK("#'Risk_Register'!A1","Risks") -> Risks | Q1: =HYPERLINK("#'PMIS_Data'!A1","Data") -> Data
A2: GCC PMIS / Executive Status View | Q2: EXECUTIVE COMMAND CENTER
A4: PROJECT SNAPSHOT | Q4: Open Risks
A5: Project | B5: 518-22-700 Bedford VA EHRM Infrastructure Upgrades | D5: Current Phase | E5: Procurement / Preconstruction | G5: VA POC | H5: Cameron Labbree | J5: GCC POC | K5: Brian Koches | Q5: Open Actions
A6: Contract Status | B6: Pending Award | D6: Prime Contractor | E6: TBD | G6: NTP Date | H6: TBD | J6: Dashboard Updated | K6: =TODAY() -> 46220 | Q6: Open Questions | R6: =COUNTA(#REF!)-1 -> 0
A7: Current Building | B7: =Building_View!$B$4 -> Campus | D7: Primary Tool | E7: Building_View / Mini Digital Twin | G7: Input Cell | H7: Building_View!B4 | J7: Mode | K7: Owner Support | Q7: Open Assumptions | R7: =COUNTA(#REF!)-1 -> 0
A9: AT-A-GLANCE METRICS
A10: ="Open Risks"&CHAR(10)&SUMPRODUCT(--(#REF!<>""),--(#REF!<>"Closed"),--(#REF!<>"Complete")) -> #REF! | C10: ="Open Actions"&CHAR(10)&SUMPRODUCT(--(#REF!<>""),--(#REF!<>"Closed"),--(#REF!<>"Complete")) -> #REF! | E10: ="Open Questions"&CHAR(10)&SUMPRODUCT(--(#REF!<>""),--(#REF!<>"Closed"),--(#REF!<>"Complete")) -> #REF! | G10: ="Open Assumptions"&CHAR(10)&SUMPRODUCT(--(#REF!<>""),--(#REF!<>"Closed"),--(#REF!<>"Complete"),--(#REF!<>"Verified")) -> #REF! | I10: ="Telecom Rooms"&CHAR(10)&COUNTA(Telecom_Rooms!$A$5:$A$200) -> Telecom Rooms 45 | K10: ="Shutdowns"&CHAR(10)&SUMPRODUCT(--(Shutdown_Tracker!$C$5:$C$300<>""),--(Shutdown_Tracker!$I$5:$I$300<>"Closed"),--(Shutdown_Tracker!$I$5:$I$300<>"Complete")) -> Shutdowns 1 | Q10: TOP RISKS
A14: SELECTED BUILDING SUMMARY
A15: ="Selected Building"&CHAR(10)&Building_View!$B$4 -> Selected Building Campus | C15: ="Building Risks"&CHAR(10)&Building_View!$D$7 -> #REF! | E15: ="Building Actions"&CHAR(10)&Building_View!$F$7 -> #REF! | G15: ="Telecom Rooms"&CHAR(10)&Building_View!$D$8 -> Telecom Rooms 0 | I15: ="Building Docs"&CHAR(10)&Building_View!$F$8 -> Building Docs 40 | K15: ="Building Shutdowns"&CHAR(10)&Building_View!$D$9 -> Building Shutdowns 0
Q18: KEY OPEN QUESTIONS
A20: TOP RISKS | G20: BUILDING SHUTDOWNS
A21: Risk ID | B21: Description | C21: Building | D21: Impact | E21: Owner | F21: Status | G21: ID | H21: System | I21: Building | J21: Scheduled | K21: Status | L21: Notes
A22: =#REF! -> #REF! | B22: =#REF! -> #REF! | C22: =#REF! -> #REF! | D22: =#REF! -> #REF! | E22: =#REF! -> #REF! | F22: =#REF! -> #REF! | G22: =Building_View!A67 | H22: =Building_View!B67 | I22: =Building_View!C67 | J22: =Building_View!F67 | K22: =Building_View!I67 | L22: =Building_View!J67
A23: =#REF! -> #REF! | B23: =#REF! -> #REF! | C23: =#REF! -> #REF! | D23: =#REF! -> #REF! | E23: =#REF! -> #REF! | F23: =#REF! -> #REF! | G23: =Building_View!A68 | H23: =Building_View!B68 | I23: =Building_View!C68 | J23: =Building_View!F68 | K23: =Building_View!I68 | L23: =Building_View!J68
A24: =#REF! -> #REF! | B24: =#REF! -> #REF! | C24: =#REF! -> #REF! | D24: =#REF! -> #REF! | E24: =#REF! -> #REF! | F24: =#REF! -> #REF! | G24: =Building_View!A69 | H24: =Building_View!B69 | I24: =Building_View!C69 | J24: =Building_View!F69 | K24: =Building_View!I69 | L24: =Building_View!J69
A25: =#REF! -> #REF! | B25: =#REF! -> #REF! | C25: =#REF! -> #REF! | D25: =#REF! -> #REF! | E25: =#REF! -> #REF! | F25: =#REF! -> #REF! | G25: =Building_View!A70 | H25: =Building_View!B70 | I25: =Building_View!C70 | J25: =Building_View!F70 | K25: =Building_View!I70 | L25: =Building_View!J70
A26: =#REF! -> #REF! | B26: =#REF! -> #REF! | C26: =#REF! -> #REF! | D26: =#REF! -> #REF! | E26: =#REF! -> #REF! | F26: =#REF! -> #REF! | G26: =Building_View!A71 | H26: =Building_View!B71 | I26: =Building_View!C71 | J26: =Building_View!F71 | K26: =Building_View!I71 | L26: =Building_View!J71
A29: OPEN QUESTIONS | G29: THIS WEEK / NEXT WEEK
A30: Question ID | B30: Question | C30: Why It Matters | D30: Owner | E30: Priority | F30: Status | G30: Period | H30: Objective | I30: Owner | J30: Status | K30: Notes
A31: =#REF! -> #REF! | B31: =#REF! -> #REF! | C31: =#REF! -> #REF! | D31: =#REF! -> #REF! | E31: =#REF! -> #REF! | F31: =#REF! -> #REF! | G31: This Week | H31: Use Building_View to validate building records | I31: Paul | J31: In Progress | K31: B4 controls selected building
A32: =#REF! -> #REF! | B32: =#REF! -> #REF! | C32: =#REF! -> #REF! | D32: =#REF! -> #REF! | E32: =#REF! -> #REF! | F32: =#REF! -> #REF! | G32: This Week | H32: Track active Building 62 shutdown | I32: Paul | J32: In Progress | K32: Confirm stakeholders and scheduled date
A33: =#REF! -> #REF! | B33: =#REF! -> #REF! | C33: =#REF! -> #REF! | D33: =#REF! -> #REF! | E33: =#REF! -> #REF! | F33: =#REF! -> #REF! | G33: This Week | H33: Keep source tabs normalized | I33: Paul | J33: Open | K33: Building values must match B4 values
A34: =#REF! -> #REF! | B34: =#REF! -> #REF! | C34: =#REF! -> #REF! | D34: =#REF! -> #REF! | E34: =#REF! -> #REF! | F34: =#REF! -> #REF! | G34: Next Week | H34: Add verified existing conditions | I34: Paul | J34: Open | K34: Only add useful field observations
A35: =#REF! -> #REF! | B35: =#REF! -> #REF! | C35: =#REF! -> #REF! | D35: =#REF! -> #REF! | E35: =#REF! -> #REF! | F35: =#REF! -> #REF! | G35: Next Week | H35: Align reporting expectations | I35: GCC | J35: Open | K35: Avoid duplicate reporting systems
A38: DASHBOARD NOTES
A39: Dashboard is formula-driven and reads from existing PMIS source tabs. It does not replace Building_View; it summarizes the overall project and selected building. To change the selected building, update Building_View!B4.
A40: If a dashboard section appears blank, the matching source register likely has no records for the selected building yet.
A43: NOTE: PMIS_Home is now the combined Dashboard + Building View + Command Center sheet. This tab is retained for legacy reference.

Sheet Building_View
A1: BUILDING VIEW / MINI DIGITAL TWIN | M1: =HYPERLINK("#'V4_Mission_Control'!A1","Mission") -> Mission | N1: =HYPERLINK("#'Command_Center'!A1","Command") -> Command | O1: =HYPERLINK("#'Building_View'!A1","Building") -> Building | P1: =HYPERLINK("#'Risk_Register'!A1","Risks") -> Risks | Q1: =HYPERLINK("#'PMIS_Data'!A1","Data") -> Data
A2: Enter a building number or area and return risks, actions, existing conditions, telecom rooms, documents, photos, shutdowns, and stakeholders.
A4: Enter Building / Area | B4: =PMIS_Home!$B$4 -> Campus | D4: B4 controls the lookup. Pick Campus to see project-wide items. Pick a building number for building-specific rooms/records. Blank sections mean source tabs have no matching rows yet.
A6: BUILDING SNAPSHOT
A7: Building | B7: =B4 -> Campus | C7: Open Risks | D7: =MAX(#REF!) -> #REF! | E7: Open Actions | F7: =MAX(#REF!) -> #REF!
A8: Existing Conditions | B8: =MAX(Existing_Conditions!$I$5:$I$200) -> 0 | C8: Telecom Rooms | D8: =MAX(Telecom_Rooms!$J$5:$J$200) -> 0 | E8: Documents | F8: =MAX(Doc_Register!$L$5:$L$300) -> 40
A9: Photos | B9: =MAX(#REF!) -> #REF! | C9: Shutdowns | D9: =MAX(Shutdown_Tracker!$K$5:$K$300) -> 0 | E9: Stakeholders | F9: =MAX(Building_Stakeholders!$I$5:$I$200) -> 3
A11: RISKS
A12: Risk ID | B12: Description | C12: Building | D12: System | E12: Probability | F12: Impact | G12: Risk Score | H12: Mitigation | I12: Owner | J12: Status | K12: Notes | L12: Related Doc
A13: =IFERROR(INDEX(#REF!,MATCH(ROWS($A$13:A13),#REF!,0)),"") | B13: =IFERROR(INDEX(#REF!,MATCH(ROWS($A$13:B13),#REF!,0)),"") | C13: =IFERROR(INDEX(#REF!,MATCH(ROWS($A$13:C13),#REF!,0)),"") | D13: =IFERROR(INDEX(#REF!,MATCH(ROWS($A$13:D13),#REF!,0)),"") | E13: =IFERROR(INDEX(#REF!,MATCH(ROWS($A$13:E13),#REF!,0)),"") | F13: =IFERROR(INDEX(#REF!,MATCH(ROWS($A$13:F13),#REF!,0)),"") | G13: =IFERROR(INDEX(#REF!,MATCH(ROWS($A$13:G13),#REF!,0)),"") | H13: =IFERROR(INDEX(#REF!,MATCH(ROWS($A$13:H13),#REF!,0)),"") | ... L13: =IFERROR(INDEX(#REF!,MATCH(ROWS($A$13:L13),#REF!,0)),"")
A14: =IFERROR(INDEX(#REF!,MATCH(ROWS($A$13:A14),#REF!,0)),"") | B14: =IFERROR(INDEX(#REF!,MATCH(ROWS($A$13:B14),#REF!,0)),"") | C14: =IFERROR(INDEX(#REF!,MATCH(ROWS($A$13:C14),#REF!,0)),"") | D14: =IFERROR(INDEX(#REF!,MATCH(ROWS($A$13:D14),#REF!,0)),"") | E14: =IFERROR(INDEX(#REF!,MATCH(ROWS($A$13:E14),#REF!,0)),"") | F14: =IFERROR(INDEX(#REF!,MATCH(ROWS($A$13:F14),#REF!,0)),"") | G14: =IFERROR(INDEX(#REF!,MATCH(ROWS($A$13:G14),#REF!,0)),"") | H14: =IFERROR(INDEX(#REF!,MATCH(ROWS($A$13:H14),#REF!,0)),"") | ... L14: =IFERROR(INDEX(#REF!,MATCH(ROWS($A$13:L14),#REF!,0)),"")
A15: =IFERROR(INDEX(#REF!,MATCH(ROWS($A$13:A15),#REF!,0)),"") | B15: =IFERROR(INDEX(#REF!,MATCH(ROWS($A$13:B15),#REF!,0)),"") | C15: =IFERROR(INDEX(#REF!,MATCH(ROWS($A$13:C15),#REF!,0)),"") | D15: =IFERROR(INDEX(#REF!,MATCH(ROWS($A$13:D15),#REF!,0)),"") | E15: =IFERROR(INDEX(#REF!,MATCH(ROWS($A$13:E15),#REF!,0)),"") | F15: =IFERROR(INDEX(#REF!,MATCH(ROWS($A$13:F15),#REF!,0)),"") | G15: =IFERROR(INDEX(#REF!,MATCH(ROWS($A$13:G15),#REF!,0)),"") | H15: =IFERROR(INDEX(#REF!,MATCH(ROWS($A$13:H15),#REF!,0)),"") | ... L15: =IFERROR(INDEX(#REF!,MATCH(ROWS($A$13:L15),#REF!,0)),"")
A16: =IFERROR(INDEX(#REF!,MATCH(ROWS($A$13:A16),#REF!,0)),"") | B16: =IFERROR(INDEX(#REF!,MATCH(ROWS($A$13:B16),#REF!,0)),"") | C16: =IFERROR(INDEX(#REF!,MATCH(ROWS($A$13:C16),#REF!,0)),"") | D16: =IFERROR(INDEX(#REF!,MATCH(ROWS($A$13:D16),#REF!,0)),"") | E16: =IFERROR(INDEX(#REF!,MATCH(ROWS($A$13:E16),#REF!,0)),"") | F16: =IFERROR(INDEX(#REF!,MATCH(ROWS($A$13:F16),#REF!,0)),"") | G16: =IFERROR(INDEX(#REF!,MATCH(ROWS($A$13:G16),#REF!,0)),"") | H16: =IFERROR(INDEX(#REF!,MATCH(ROWS($A$13:H16),#REF!,0)),"") | ... L16: =IFERROR(INDEX(#REF!,MATCH(ROWS($A$13:L16),#REF!,0)),"")
A17: =IFERROR(INDEX(#REF!,MATCH(ROWS($A$13:A17),#REF!,0)),"") | B17: =IFERROR(INDEX(#REF!,MATCH(ROWS($A$13:B17),#REF!,0)),"") | C17: =IFERROR(INDEX(#REF!,MATCH(ROWS($A$13:C17),#REF!,0)),"") | D17: =IFERROR(INDEX(#REF!,MATCH(ROWS($A$13:D17),#REF!,0)),"") | E17: =IFERROR(INDEX(#REF!,MATCH(ROWS($A$13:E17),#REF!,0)),"") | F17: =IFERROR(INDEX(#REF!,MATCH(ROWS($A$13:F17),#REF!,0)),"") | G17: =IFERROR(INDEX(#REF!,MATCH(ROWS($A$13:G17),#REF!,0)),"") | H17: =IFERROR(INDEX(#REF!,MATCH(ROWS($A$13:H17),#REF!,0)),"") | ... L17: =IFERROR(INDEX(#REF!,MATCH(ROWS($A$13:L17),#REF!,0)),"")
A20: OPEN ACTIONS
A21: Action ID | B21: Date | C21: Action Item | D21: Building | E21: System | F21: Assigned To | G21: Due Date | H21: Priority | I21: Status | J21: Notes
A22: =IFERROR(INDEX(#REF!,MATCH(ROWS($A$22:A22),#REF!,0)),"") | B22: =IFERROR(INDEX(#REF!,MATCH(ROWS($A$22:B22),#REF!,0)),"") | C22: =IFERROR(INDEX(#REF!,MATCH(ROWS($A$22:C22),#REF!,0)),"") | D22: =IFERROR(INDEX(#REF!,MATCH(ROWS($A$22:D22),#REF!,0)),"") | E22: =IFERROR(INDEX(#REF!,MATCH(ROWS($A$22:E22),#REF!,0)),"") | F22: =IFERROR(INDEX(#REF!,MATCH(ROWS($A$22:F22),#REF!,0)),"") | G22: =IFERROR(INDEX(#REF!,MATCH(ROWS($A$22:G22),#REF!,0)),"") | H22: =IFERROR(INDEX(#REF!,MATCH(ROWS($A$22:H22),#REF!,0)),"") | ... J22: =IFERROR(INDEX(#REF!,MATCH(ROWS($A$22:J22),#REF!,0)),"")
A23: =IFERROR(INDEX(#REF!,MATCH(ROWS($A$22:A23),#REF!,0)),"") | B23: =IFERROR(INDEX(#REF!,MATCH(ROWS($A$22:B23),#REF!,0)),"") | C23: =IFERROR(INDEX(#REF!,MATCH(ROWS($A$22:C23),#REF!,0)),"") | D23: =IFERROR(INDEX(#REF!,MATCH(ROWS($A$22:D23),#REF!,0)),"") | E23: =IFERROR(INDEX(#REF!,MATCH(ROWS($A$22:E23),#REF!,0)),"") | F23: =IFERROR(INDEX(#REF!,MATCH(ROWS($A$22:F23),#REF!,0)),"") | G23: =IFERROR(INDEX(#REF!,MATCH(ROWS($A$22:G23),#REF!,0)),"") | H23: =IFERROR(INDEX(#REF!,MATCH(ROWS($A$22:H23),#REF!,0)),"") | ... J23: =IFERROR(INDEX(#REF!,MATCH(ROWS($A$22:J23),#REF!,0)),"")
A24: =IFERROR(INDEX(#REF!,MATCH(ROWS($A$22:A24),#REF!,0)),"") | B24: =IFERROR(INDEX(#REF!,MATCH(ROWS($A$22:B24),#REF!,0)),"") | C24: =IFERROR(INDEX(#REF!,MATCH(ROWS($A$22:C24),#REF!,0)),"") | D24: =IFERROR(INDEX(#REF!,MATCH(ROWS($A$22:D24),#REF!,0)),"") | E24: =IFERROR(INDEX(#REF!,MATCH(ROWS($A$22:E24),#REF!,0)),"") | F24: =IFERROR(INDEX(#REF!,MATCH(ROWS($A$22:F24),#REF!,0)),"") | G24: =IFERROR(INDEX(#REF!,MATCH(ROWS($A$22:G24),#REF!,0)),"") | H24: =IFERROR(INDEX(#REF!,MATCH(ROWS($A$22:H24),#REF!,0)),"") | ... J24: =IFERROR(INDEX(#REF!,MATCH(ROWS($A$22:J24),#REF!,0)),"")
A25: =IFERROR(INDEX(#REF!,MATCH(ROWS($A$22:A25),#REF!,0)),"") | B25: =IFERROR(INDEX(#REF!,MATCH(ROWS($A$22:B25),#REF!,0)),"") | C25: =IFERROR(INDEX(#REF!,MATCH(ROWS($A$22:C25),#REF!,0)),"") | D25: =IFERROR(INDEX(#REF!,MATCH(ROWS($A$22:D25),#REF!,0)),"") | E25: =IFERROR(INDEX(#REF!,MATCH(ROWS($A$22:E25),#REF!,0)),"") | F25: =IFERROR(INDEX(#REF!,MATCH(ROWS($A$22:F25),#REF!,0)),"") | G25: =IFERROR(INDEX(#REF!,MATCH(ROWS($A$22:G25),#REF!,0)),"") | H25: =IFERROR(INDEX(#REF!,MATCH(ROWS($A$22:H25),#REF!,0)),"") | ... J25: =IFERROR(INDEX(#REF!,MATCH(ROWS($A$22:J25),#REF!,0)),"")
A26: =IFERROR(INDEX(#REF!,MATCH(ROWS($A$22:A26),#REF!,0)),"") | B26: =IFERROR(INDEX(#REF!,MATCH(ROWS($A$22:B26),#REF!,0)),"") | C26: =IFERROR(INDEX(#REF!,MATCH(ROWS($A$22:C26),#REF!,0)),"") | D26: =IFERROR(INDEX(#REF!,MATCH(ROWS($A$22:D26),#REF!,0)),"") | E26: =IFERROR(INDEX(#REF!,MATCH(ROWS($A$22:E26),#REF!,0)),"") | F26: =IFERROR(INDEX(#REF!,MATCH(ROWS($A$22:F26),#REF!,0)),"") | G26: =IFERROR(INDEX(#REF!,MATCH(ROWS($A$22:G26),#REF!,0)),"") | H26: =IFERROR(INDEX(#REF!,MATCH(ROWS($A$22:H26),#REF!,0)),"") | ... J26: =IFERROR(INDEX(#REF!,MATCH(ROWS($A$22:J26),#REF!,0)),"")
A29: EXISTING CONDITIONS
A30: Building | B30: Room / Area | C30: Existing Condition | D30: Deficiency | E30: Photo Ref | F30: Potential Impact | G30: Verified By | H30: Date
A31: =IFERROR(INDEX(Existing_Conditions!$A$5:$A$300,MATCH(ROWS($A$31:A31),Existing_Conditions!$I$5:$I$300,0)),"") | B31: =IFERROR(INDEX(Existing_Conditions!$B$5:$B$300,MATCH(ROWS($A$31:B31),Existing_Conditions!$I$5:$I$300,0)),"") | C31: =IFERROR(INDEX(Existing_Conditions!$C$5:$C$300,MATCH(ROWS($A$31:C31),Existing_Conditions!$I$5:$I$300,0)),"") | D31: =IFERROR(INDEX(Existing_Conditions!$D$5:$D$300,MATCH(ROWS($A$31:D31),Existing_Conditions!$I$5:$I$300,0)),"") | E31: =IFERROR(INDEX(Existing_Conditions!$E$5:$E$300,MATCH(ROWS($A$31:E31),Existing_Conditions!$I$5:$I$300,0)),"") | F31: =IFERROR(INDEX(Existing_Conditions!$F$5:$F$300,MATCH(ROWS($A$31:F31),Existing_Conditions!$I$5:$I$300,0)),"") | G31: =IFERROR(INDEX(Existing_Conditions!$G$5:$G$300,MATCH(ROWS($A$31:G31),Existing_Conditions!$I$5:$I$300,0)),"") | H31: =IFERROR(INDEX(Existing_Conditions!$H$5:$H$300,MATCH(ROWS($A$31:H31),Existing_Conditions!$I$5:$I$300,0)),"")
A32: =IFERROR(INDEX(Existing_Conditions!$A$5:$A$300,MATCH(ROWS($A$31:A32),Existing_Conditions!$I$5:$I$300,0)),"") | B32: =IFERROR(INDEX(Existing_Conditions!$B$5:$B$300,MATCH(ROWS($A$31:B32),Existing_Conditions!$I$5:$I$300,0)),"") | C32: =IFERROR(INDEX(Existing_Conditions!$C$5:$C$300,MATCH(ROWS($A$31:C32),Existing_Conditions!$I$5:$I$300,0)),"") | D32: =IFERROR(INDEX(Existing_Conditions!$D$5:$D$300,MATCH(ROWS($A$31:D32),Existing_Conditions!$I$5:$I$300,0)),"") | E32: =IFERROR(INDEX(Existing_Conditions!$E$5:$E$300,MATCH(ROWS($A$31:E32),Existing_Conditions!$I$5:$I$300,0)),"") | F32: =IFERROR(INDEX(Existing_Conditions!$F$5:$F$300,MATCH(ROWS($A$31:F32),Existing_Conditions!$I$5:$I$300,0)),"") | G32: =IFERROR(INDEX(Existing_Conditions!$G$5:$G$300,MATCH(ROWS($A$31:G32),Existing_Conditions!$I$5:$I$300,0)),"") | H32: =IFERROR(INDEX(Existing_Conditions!$H$5:$H$300,MATCH(ROWS($A$31:H32),Existing_Conditions!$I$5:$I$300,0)),"")
A33: =IFERROR(INDEX(Existing_Conditions!$A$5:$A$300,MATCH(ROWS($A$31:A33),Existing_Conditions!$I$5:$I$300,0)),"") | B33: =IFERROR(INDEX(Existing_Conditions!$B$5:$B$300,MATCH(ROWS($A$31:B33),Existing_Conditions!$I$5:$I$300,0)),"") | C33: =IFERROR(INDEX(Existing_Conditions!$C$5:$C$300,MATCH(ROWS($A$31:C33),Existing_Conditions!$I$5:$I$300,0)),"") | D33: =IFERROR(INDEX(Existing_Conditions!$D$5:$D$300,MATCH(ROWS($A$31:D33),Existing_Conditions!$I$5:$I$300,0)),"") | E33: =IFERROR(INDEX(Existing_Conditions!$E$5:$E$300,MATCH(ROWS($A$31:E33),Existing_Conditions!$I$5:$I$300,0)),"") | F33: =IFERROR(INDEX(Existing_Conditions!$F$5:$F$300,MATCH(ROWS($A$31:F33),Existing_Conditions!$I$5:$I$300,0)),"") | G33: =IFERROR(INDEX(Existing_Conditions!$G$5:$G$300,MATCH(ROWS($A$31:G33),Existing_Conditions!$I$5:$I$300,0)),"") | H33: =IFERROR(INDEX(Existing_Conditions!$H$5:$H$300,MATCH(ROWS($A$31:H33),Existing_Conditions!$I$5:$I$300,0)),"")
A34: =IFERROR(INDEX(Existing_Conditions!$A$5:$A$300,MATCH(ROWS($A$31:A34),Existing_Conditions!$I$5:$I$300,0)),"") | B34: =IFERROR(INDEX(Existing_Conditions!$B$5:$B$300,MATCH(ROWS($A$31:B34),Existing_Conditions!$I$5:$I$300,0)),"") | C34: =IFERROR(INDEX(Existing_Conditions!$C$5:$C$300,MATCH(ROWS($A$31:C34),Existing_Conditions!$I$5:$I$300,0)),"") | D34: =IFERROR(INDEX(Existing_Conditions!$D$5:$D$300,MATCH(ROWS($A$31:D34),Existing_Conditions!$I$5:$I$300,0)),"") | E34: =IFERROR(INDEX(Existing_Conditions!$E$5:$E$300,MATCH(ROWS($A$31:E34),Existing_Conditions!$I$5:$I$300,0)),"") | F34: =IFERROR(INDEX(Existing_Conditions!$F$5:$F$300,MATCH(ROWS($A$31:F34),Existing_Conditions!$I$5:$I$300,0)),"") | G34: =IFERROR(INDEX(Existing_Conditions!$G$5:$G$300,MATCH(ROWS($A$31:G34),Existing_Conditions!$I$5:$I$300,0)),"") | H34: =IFERROR(INDEX(Existing_Conditions!$H$5:$H$300,MATCH(ROWS($A$31:H34),Existing_Conditions!$I$5:$I$300,0)),"")
A35: =IFERROR(INDEX(Existing_Conditions!$A$5:$A$300,MATCH(ROWS($A$31:A35),Existing_Conditions!$I$5:$I$300,0)),"") | B35: =IFERROR(INDEX(Existing_Conditions!$B$5:$B$300,MATCH(ROWS($A$31:B35),Existing_Conditions!$I$5:$I$300,0)),"") | C35: =IFERROR(INDEX(Existing_Conditions!$C$5:$C$300,MATCH(ROWS($A$31:C35),Existing_Conditions!$I$5:$I$300,0)),"") | D35: =IFERROR(INDEX(Existing_Conditions!$D$5:$D$300,MATCH(ROWS($A$31:D35),Existing_Conditions!$I$5:$I$300,0)),"") | E35: =IFERROR(INDEX(Existing_Conditions!$E$5:$E$300,MATCH(ROWS($A$31:E35),Existing_Conditions!$I$5:$I$300,0)),"") | F35: =IFERROR(INDEX(Existing_Conditions!$F$5:$F$300,MATCH(ROWS($A$31:F35),Existing_Conditions!$I$5:$I$300,0)),"") | G35: =IFERROR(INDEX(Existing_Conditions!$G$5:$G$300,MATCH(ROWS($A$31:G35),Existing_Conditions!$I$5:$I$300,0)),"") | H35: =IFERROR(INDEX(Existing_Conditions!$H$5:$H$300,MATCH(ROWS($A$31:H35),Existing_Conditions!$I$5:$I$300,0)),"")
A38: TELECOM ROOMS
A39: Building | B39: Room | C39: TR/IDF/MDF | D39: Rack Capacity | E39: Power | F39: Cooling | G39: Access | H39: Readiness | I39: Notes
A40: =IFERROR(INDEX(Telecom_Rooms!$A$5:$A$300,MATCH(ROWS($A$40:A40),Telecom_Rooms!$J$5:$J$300,0)),"") | B40: =IFERROR(INDEX(Telecom_Rooms!$B$5:$B$300,MATCH(ROWS($A$40:B40),Telecom_Rooms!$J$5:$J$300,0)),"") | C40: =IFERROR(INDEX(Telecom_Rooms!$C$5:$C$300,MATCH(ROWS($A$40:C40),Telecom_Rooms!$J$5:$J$300,0)),"") | D40: =IFERROR(INDEX(Telecom_Rooms!$D$5:$D$300,MATCH(ROWS($A$40:D40),Telecom_Rooms!$J$5:$J$300,0)),"") | E40: =IFERROR(INDEX(Telecom_Rooms!$E$5:$E$300,MATCH(ROWS($A$40:E40),Telecom_Rooms!$J$5:$J$300,0)),"") | F40: =IFERROR(INDEX(Telecom_Rooms!$F$5:$F$300,MATCH(ROWS($A$40:F40),Telecom_Rooms!$J$5:$J$300,0)),"") | G40: =IFERROR(INDEX(Telecom_Rooms!$G$5:$G$300,MATCH(ROWS($A$40:G40),Telecom_Rooms!$J$5:$J$300,0)),"") | H40: =IFERROR(INDEX(Telecom_Rooms!$H$5:$H$300,MATCH(ROWS($A$40:H40),Telecom_Rooms!$J$5:$J$300,0)),"") | I40: =IFERROR(INDEX(Telecom_Rooms!$I$5:$I$300,MATCH(ROWS($A$40:I40),Telecom_Rooms!$J$5:$J$300,0)),"")
A41: =IFERROR(INDEX(Telecom_Rooms!$A$5:$A$300,MATCH(ROWS($A$40:A41),Telecom_Rooms!$J$5:$J$300,0)),"") | B41: =IFERROR(INDEX(Telecom_Rooms!$B$5:$B$300,MATCH(ROWS($A$40:B41),Telecom_Rooms!$J$5:$J$300,0)),"") | C41: =IFERROR(INDEX(Telecom_Rooms!$C$5:$C$300,MATCH(ROWS($A$40:C41),Telecom_Rooms!$J$5:$J$300,0)),"") | D41: =IFERROR(INDEX(Telecom_Rooms!$D$5:$D$300,MATCH(ROWS($A$40:D41),Telecom_Rooms!$J$5:$J$300,0)),"") | E41: =IFERROR(INDEX(Telecom_Rooms!$E$5:$E$300,MATCH(ROWS($A$40:E41),Telecom_Rooms!$J$5:$J$300,0)),"") | F41: =IFERROR(INDEX(Telecom_Rooms!$F$5:$F$300,MATCH(ROWS($A$40:F41),Telecom_Rooms!$J$5:$J$300,0)),"") | G41: =IFERROR(INDEX(Telecom_Rooms!$G$5:$G$300,MATCH(ROWS($A$40:G41),Telecom_Rooms!$J$5:$J$300,0)),"") | H41: =IFERROR(INDEX(Telecom_Rooms!$H$5:$H$300,MATCH(ROWS($A$40:H41),Telecom_Rooms!$J$5:$J$300,0)),"") | I41: =IFERROR(INDEX(Telecom_Rooms!$I$5:$I$300,MATCH(ROWS($A$40:I41),Telecom_Rooms!$J$5:$J$300,0)),"")
A42: =IFERROR(INDEX(Telecom_Rooms!$A$5:$A$300,MATCH(ROWS($A$40:A42),Telecom_Rooms!$J$5:$J$300,0)),"") | B42: =IFERROR(INDEX(Telecom_Rooms!$B$5:$B$300,MATCH(ROWS($A$40:B42),Telecom_Rooms!$J$5:$J$300,0)),"") | C42: =IFERROR(INDEX(Telecom_Rooms!$C$5:$C$300,MATCH(ROWS($A$40:C42),Telecom_Rooms!$J$5:$J$300,0)),"") | D42: =IFERROR(INDEX(Telecom_Rooms!$D$5:$D$300,MATCH(ROWS($A$40:D42),Telecom_Rooms!$J$5:$J$300,0)),"") | E42: =IFERROR(INDEX(Telecom_Rooms!$E$5:$E$300,MATCH(ROWS($A$40:E42),Telecom_Rooms!$J$5:$J$300,0)),"") | F42: =IFERROR(INDEX(Telecom_Rooms!$F$5:$F$300,MATCH(ROWS($A$40:F42),Telecom_Rooms!$J$5:$J$300,0)),"") | G42: =IFERROR(INDEX(Telecom_Rooms!$G$5:$G$300,MATCH(ROWS($A$40:G42),Telecom_Rooms!$J$5:$J$300,0)),"") | H42: =IFERROR(INDEX(Telecom_Rooms!$H$5:$H$300,MATCH(ROWS($A$40:H42),Telecom_Rooms!$J$5:$J$300,0)),"") | I42: =IFERROR(INDEX(Telecom_Rooms!$I$5:$I$300,MATCH(ROWS($A$40:I42),Telecom_Rooms!$J$5:$J$300,0)),"")
A43: =IFERROR(INDEX(Telecom_Rooms!$A$5:$A$300,MATCH(ROWS($A$40:A43),Telecom_Rooms!$J$5:$J$300,0)),"") | B43: =IFERROR(INDEX(Telecom_Rooms!$B$5:$B$300,MATCH(ROWS($A$40:B43),Telecom_Rooms!$J$5:$J$300,0)),"") | C43: =IFERROR(INDEX(Telecom_Rooms!$C$5:$C$300,MATCH(ROWS($A$40:C43),Telecom_Rooms!$J$5:$J$300,0)),"") | D43: =IFERROR(INDEX(Telecom_Rooms!$D$5:$D$300,MATCH(ROWS($A$40:D43),Telecom_Rooms!$J$5:$J$300,0)),"") | E43: =IFERROR(INDEX(Telecom_Rooms!$E$5:$E$300,MATCH(ROWS($A$40:E43),Telecom_Rooms!$J$5:$J$300,0)),"") | F43: =IFERROR(INDEX(Telecom_Rooms!$F$5:$F$300,MATCH(ROWS($A$40:F43),Telecom_Rooms!$J$5:$J$300,0)),"") | G43: =IFERROR(INDEX(Telecom_Rooms!$G$5:$G$300,MATCH(ROWS($A$40:G43),Telecom_Rooms!$J$5:$J$300,0)),"") | H43: =IFERROR(INDEX(Telecom_Rooms!$H$5:$H$300,MATCH(ROWS($A$40:H43),Telecom_Rooms!$J$5:$J$300,0)),"") | I43: =IFERROR(INDEX(Telecom_Rooms!$I$5:$I$300,MATCH(ROWS($A$40:I43),Telecom_Rooms!$J$5:$J$300,0)),"")
A44: =IFERROR(INDEX(Telecom_Rooms!$A$5:$A$300,MATCH(ROWS($A$40:A44),Telecom_Rooms!$J$5:$J$300,0)),"") | B44: =IFERROR(INDEX(Telecom_Rooms!$B$5:$B$300,MATCH(ROWS($A$40:B44),Telecom_Rooms!$J$5:$J$300,0)),"") | C44: =IFERROR(INDEX(Telecom_Rooms!$C$5:$C$300,MATCH(ROWS($A$40:C44),Telecom_Rooms!$J$5:$J$300,0)),"") | D44: =IFERROR(INDEX(Telecom_Rooms!$D$5:$D$300,MATCH(ROWS($A$40:D44),Telecom_Rooms!$J$5:$J$300,0)),"") | E44: =IFERROR(INDEX(Telecom_Rooms!$E$5:$E$300,MATCH(ROWS($A$40:E44),Telecom_Rooms!$J$5:$J$300,0)),"") | F44: =IFERROR(INDEX(Telecom_Rooms!$F$5:$F$300,MATCH(ROWS($A$40:F44),Telecom_Rooms!$J$5:$J$300,0)),"") | G44: =IFERROR(INDEX(Telecom_Rooms!$G$5:$G$300,MATCH(ROWS($A$40:G44),Telecom_Rooms!$J$5:$J$300,0)),"") | H44: =IFERROR(INDEX(Telecom_Rooms!$H$5:$H$300,MATCH(ROWS($A$40:H44),Telecom_Rooms!$J$5:$J$300,0)),"") | I44: =IFERROR(INDEX(Telecom_Rooms!$I$5:$I$300,MATCH(ROWS($A$40:I44),Telecom_Rooms!$J$5:$J$300,0)),"")
A47: DOCUMENTS
A48: Doc ID | B48: File / Document | C48: Discipline | D48: Sheet No | E48: Title | F48: Revision | G48: Date | H48: Building | I48: System | J48: Keywords | K48: Link / Path
A49: =IFERROR(INDEX(Doc_Register!$A$5:$A$300,MATCH(ROWS($A$49:A49),Doc_Register!$L$5:$L$300,0)),"") -> DOC-001 | B49: =IFERROR(INDEX(Doc_Register!$B$5:$B$300,MATCH(ROWS($A$49:B49),Doc_Register!$L$5:$L$300,0)),"") -> 00 41 13.10 - Construction Estimate Breakdown Template.pdf | C49: =IFERROR(INDEX(Doc_Register!$C$5:$C$300,MATCH(ROWS($A$49:C49),Doc_Register!$L$5:$L$300,0)),"") -> 0 | D49: =IFERROR(INDEX(Doc_Register!$D$5:$D$300,MATCH(ROWS($A$49:D49),Doc_Register!$L$5:$L$300,0)),"") -> 0 | E49: =IFERROR(INDEX(Doc_Register!$E$5:$E$300,MATCH(ROWS($A$49:E49),Doc_Register!$L$5:$L$300,0)),"") -> 00 41 13.10 - Construction Estimate Breakdown Template.pdf | F49: =IFERROR(INDEX(Doc_Register!$F$5:$F$300,MATCH(ROWS($A$49:F49),Doc_Register!$L$5:$L$300,0)),"") -> 0 | G49: =IFERROR(INDEX(Doc_Register!$G$5:$G$300,MATCH(ROWS($A$49:G49),Doc_Register!$L$5:$L$300,0)),"") -> 0 | H49: =IFERROR(INDEX(Doc_Register!$H$5:$H$300,MATCH(ROWS($A$49:H49),Doc_Register!$L$5:$L$300,0)),"") -> Campus | I49: =IFERROR(INDEX(Doc_Register!$I$5:$I$300,MATCH(ROWS($A$49:I49),Doc_Register!$L$5:$L$300,0)),"") -> 0 | J49: =IFERROR(INDEX(Doc_Register!$J$5:$J$300,MATCH(ROWS($A$49:J49),Doc_Register!$L$5:$L$300,0)),"") -> 0 | K49: =IFERROR(INDEX(Doc_Register!$K$5:$K$300,MATCH(ROWS($A$49:K49),Doc_Register!$L$5:$L$300,0)),"") -> Plans\00 41 13.10 - Construction Estimate Breakdown Template.pdf
A50: =IFERROR(INDEX(Doc_Register!$A$5:$A$300,MATCH(ROWS($A$49:A50),Doc_Register!$L$5:$L$300,0)),"") -> DOC-002 | B50: =IFERROR(INDEX(Doc_Register!$B$5:$B$300,MATCH(ROWS($A$49:B50),Doc_Register!$L$5:$L$300,0)),"") -> 01 00 00.B - Appendix B - Submittal Log.pdf | C50: =IFERROR(INDEX(Doc_Register!$C$5:$C$300,MATCH(ROWS($A$49:C50),Doc_Register!$L$5:$L$300,0)),"") -> Submittals | D50: =IFERROR(INDEX(Doc_Register!$D$5:$D$300,MATCH(ROWS($A$49:D50),Doc_Register!$L$5:$L$300,0)),"") -> 0 | E50: =IFERROR(INDEX(Doc_Register!$E$5:$E$300,MATCH(ROWS($A$49:E50),Doc_Register!$L$5:$L$300,0)),"") -> 01 00 00.B - Appendix B - Submittal Log.pdf | F50: =IFERROR(INDEX(Doc_Register!$F$5:$F$300,MATCH(ROWS($A$49:F50),Doc_Register!$L$5:$L$300,0)),"") -> 0 | G50: =IFERROR(INDEX(Doc_Register!$G$5:$G$300,MATCH(ROWS($A$49:G50),Doc_Register!$L$5:$L$300,0)),"") -> 0 | H50: =IFERROR(INDEX(Doc_Register!$H$5:$H$300,MATCH(ROWS($A$49:H50),Doc_Register!$L$5:$L$300,0)),"") -> Campus | I50: =IFERROR(INDEX(Doc_Register!$I$5:$I$300,MATCH(ROWS($A$49:I50),Doc_Register!$L$5:$L$300,0)),"") -> Project Controls | J50: =IFERROR(INDEX(Doc_Register!$J$5:$J$300,MATCH(ROWS($A$49:J50),Doc_Register!$L$5:$L$300,0)),"") -> submittal, log | K50: =IFERROR(INDEX(Doc_Register!$K$5:$K$300,MATCH(ROWS($A$49:K50),Doc_Register!$L$5:$L$300,0)),"") -> Plans\01 00 00.B - Appendix B - Submittal Log.pdf
A51: =IFERROR(INDEX(Doc_Register!$A$5:$A$300,MATCH(ROWS($A$49:A51),Doc_Register!$L$5:$L$300,0)),"") -> DOC-003 | B51: =IFERROR(INDEX(Doc_Register!$B$5:$B$300,MATCH(ROWS($A$49:B51),Doc_Register!$L$5:$L$300,0)),"") -> 01 00 00.C - Appendix C - VHA ICRA-1.3 (Dec 9 2024).pdf | C51: =IFERROR(INDEX(Doc_Register!$C$5:$C$300,MATCH(ROWS($A$49:C51),Doc_Register!$L$5:$L$300,0)),"") -> Safety / Infection Control | D51: =IFERROR(INDEX(Doc_Register!$D$5:$D$300,MATCH(ROWS($A$49:D51),Doc_Register!$L$5:$L$300,0)),"") -> 0 | E51: =IFERROR(INDEX(Doc_Register!$E$5:$E$300,MATCH(ROWS($A$49:E51),Doc_Register!$L$5:$L$300,0)),"") -> 01 00 00.C - Appendix C - VHA ICRA-1.3 (Dec 9 2024).pdf | F51: =IFERROR(INDEX(Doc_Register!$F$5:$F$300,MATCH(ROWS($A$49:F51),Doc_Register!$L$5:$L$300,0)),"") -> 0 | G51: =IFERROR(INDEX(Doc_Register!$G$5:$G$300,MATCH(ROWS($A$49:G51),Doc_Register!$L$5:$L$300,0)),"") -> 0 | H51: =IFERROR(INDEX(Doc_Register!$H$5:$H$300,MATCH(ROWS($A$49:H51),Doc_Register!$L$5:$L$300,0)),"") -> Campus | I51: =IFERROR(INDEX(Doc_Register!$I$5:$I$300,MATCH(ROWS($A$49:I51),Doc_Register!$L$5:$L$300,0)),"") -> ICRA | J51: =IFERROR(INDEX(Doc_Register!$J$5:$J$300,MATCH(ROWS($A$49:J51),Doc_Register!$L$5:$L$300,0)),"") -> ICRA, infection control, safety | K51: =IFERROR(INDEX(Doc_Register!$K$5:$K$300,MATCH(ROWS($A$49:K51),Doc_Register!$L$5:$L$300,0)),"") -> Plans\01 00 00.C - Appendix C - VHA ICRA-1.3 (Dec 9 2024).pdf
A52: =IFERROR(INDEX(Doc_Register!$A$5:$A$300,MATCH(ROWS($A$49:A52),Doc_Register!$L$5:$L$300,0)),"") -> DOC-004 | B52: =IFERROR(INDEX(Doc_Register!$B$5:$B$300,MATCH(ROWS($A$49:B52),Doc_Register!$L$5:$L$300,0)),"") -> 01 00 00.D - Appendix D - VHA PCRA 2024 1.1 Final.Template Fillable.pdf | C52: =IFERROR(INDEX(Doc_Register!$C$5:$C$300,MATCH(ROWS($A$49:C52),Doc_Register!$L$5:$L$300,0)),"") -> Safety / Risk | D52: =IFERROR(INDEX(Doc_Register!$D$5:$D$300,MATCH(ROWS($A$49:D52),Doc_Register!$L$5:$L$300,0)),"") -> 0 | E52: =IFERROR(INDEX(Doc_Register!$E$5:$E$300,MATCH(ROWS($A$49:E52),Doc_Register!$L$5:$L$300,0)),"") -> 01 00 00.D - Appendix D - VHA PCRA 2024 1.1 Final.Template Fillable.pdf | F52: =IFERROR(INDEX(Doc_Register!$F$5:$F$300,MATCH(ROWS($A$49:F52),Doc_Register!$L$5:$L$300,0)),"") -> 0 | G52: =IFERROR(INDEX(Doc_Register!$G$5:$G$300,MATCH(ROWS($A$49:G52),Doc_Register!$L$5:$L$300,0)),"") -> 0 | H52: =IFERROR(INDEX(Doc_Register!$H$5:$H$300,MATCH(ROWS($A$49:H52),Doc_Register!$L$5:$L$300,0)),"") -> Campus | I52: =IFERROR(INDEX(Doc_Register!$I$5:$I$300,MATCH(ROWS($A$49:I52),Doc_Register!$L$5:$L$300,0)),"") -> PCRA | J52: =IFERROR(INDEX(Doc_Register!$J$5:$J$300,MATCH(ROWS($A$49:J52),Doc_Register!$L$5:$L$300,0)),"") -> PCRA, safety, risk | K52: =IFERROR(INDEX(Doc_Register!$K$5:$K$300,MATCH(ROWS($A$49:K52),Doc_Register!$L$5:$L$300,0)),"") -> Plans\01 00 00.D - Appendix D - VHA PCRA 2024 1.1 Final.Template Fillable.pdf
A53: =IFERROR(INDEX(Doc_Register!$A$5:$A$300,MATCH(ROWS($A$49:A53),Doc_Register!$L$5:$L$300,0)),"") -> DOC-005 | B53: =IFERROR(INDEX(Doc_Register!$B$5:$B$300,MATCH(ROWS($A$49:B53),Doc_Register!$L$5:$L$300,0)),"") -> 01 00 00.E - Appendix E - J2247012 Bedford MA VAMC ACM Inspection LCP Testing Report Final 11-20-2024 - signed-unlocked.pdf | C53: =IFERROR(INDEX(Doc_Register!$C$5:$C$300,MATCH(ROWS($A$49:C53),Doc_Register!$L$5:$L$300,0)),"") -> Hazardous Materials | D53: =IFERROR(INDEX(Doc_Register!$D$5:$D$300,MATCH(ROWS($A$49:D53),Doc_Register!$L$5:$L$300,0)),"") -> 0 | E53: =IFERROR(INDEX(Doc_Register!$E$5:$E$300,MATCH(ROWS($A$49:E53),Doc_Register!$L$5:$L$300,0)),"") -> 01 00 00.E - Appendix E - J2247012 Bedford MA VAMC ACM Inspection LCP Testing Report Final 11-20-2024 - signed-unlocked.pdf | F53: =IFERROR(INDEX(Doc_Register!$F$5:$F$300,MATCH(ROWS($A$49:F53),Doc_Register!$L$5:$L$300,0)),"") -> 0 | G53: =IFERROR(INDEX(Doc_Register!$G$5:$G$300,MATCH(ROWS($A$49:G53),Doc_Register!$L$5:$L$300,0)),"") -> 0 | H53: =IFERROR(INDEX(Doc_Register!$H$5:$H$300,MATCH(ROWS($A$49:H53),Doc_Register!$L$5:$L$300,0)),"") -> Campus | I53: =IFERROR(INDEX(Doc_Register!$I$5:$I$300,MATCH(ROWS($A$49:I53),Doc_Register!$L$5:$L$300,0)),"") -> ACM / LCP | J53: =IFERROR(INDEX(Doc_Register!$J$5:$J$300,MATCH(ROWS($A$49:J53),Doc_Register!$L$5:$L$300,0)),"") -> asbestos, lead, hazardous material | K53: =IFERROR(INDEX(Doc_Register!$K$5:$K$300,MATCH(ROWS($A$49:K53),Doc_Register!$L$5:$L$300,0)),"") -> Plans\01 00 00.E - Appendix E - J2247012 Bedford MA VAMC ACM Inspection LCP Testing Report Final 11-20-2024 - signed-unlocked.pdf
A56: PHOTOS
A57: Photo ID | B57: Date | C57: Building | D57: Location | E57: Description | F57: File Name | G57: Linked Ref
A58: =IFERROR(INDEX(#REF!,MATCH(ROWS($A$58:A58),#REF!,0)),"") | B58: =IFERROR(INDEX(#REF!,MATCH(ROWS($A$58:B58),#REF!,0)),"") | C58: =IFERROR(INDEX(#REF!,MATCH(ROWS($A$58:C58),#REF!,0)),"") | D58: =IFERROR(INDEX(#REF!,MATCH(ROWS($A$58:D58),#REF!,0)),"") | E58: =IFERROR(INDEX(#REF!,MATCH(ROWS($A$58:E58),#REF!,0)),"") | F58: =IFERROR(INDEX(#REF!,MATCH(ROWS($A$58:F58),#REF!,0)),"") | G58: =IFERROR(INDEX(#REF!,MATCH(ROWS($A$58:G58),#REF!,0)),"")
A59: =IFERROR(INDEX(#REF!,MATCH(ROWS($A$58:A59),#REF!,0)),"") | B59: =IFERROR(INDEX(#REF!,MATCH(ROWS($A$58:B59),#REF!,0)),"") | C59: =IFERROR(INDEX(#REF!,MATCH(ROWS($A$58:C59),#REF!,0)),"") | D59: =IFERROR(INDEX(#REF!,MATCH(ROWS($A$58:D59),#REF!,0)),"") | E59: =IFERROR(INDEX(#REF!,MATCH(ROWS($A$58:E59),#REF!,0)),"") | F59: =IFERROR(INDEX(#REF!,MATCH(ROWS($A$58:F59),#REF!,0)),"") | G59: =IFERROR(INDEX(#REF!,MATCH(ROWS($A$58:G59),#REF!,0)),"")
A60: =IFERROR(INDEX(#REF!,MATCH(ROWS($A$58:A60),#REF!,0)),"") | B60: =IFERROR(INDEX(#REF!,MATCH(ROWS($A$58:B60),#REF!,0)),"") | C60: =IFERROR(INDEX(#REF!,MATCH(ROWS($A$58:C60),#REF!,0)),"") | D60: =IFERROR(INDEX(#REF!,MATCH(ROWS($A$58:D60),#REF!,0)),"") | E60: =IFERROR(INDEX(#REF!,MATCH(ROWS($A$58:E60),#REF!,0)),"") | F60: =IFERROR(INDEX(#REF!,MATCH(ROWS($A$58:F60),#REF!,0)),"") | G60: =IFERROR(INDEX(#REF!,MATCH(ROWS($A$58:G60),#REF!,0)),"")
A61: =IFERROR(INDEX(#REF!,MATCH(ROWS($A$58:A61),#REF!,0)),"") | B61: =IFERROR(INDEX(#REF!,MATCH(ROWS($A$58:B61),#REF!,0)),"") | C61: =IFERROR(INDEX(#REF!,MATCH(ROWS($A$58:C61),#REF!,0)),"") | D61: =IFERROR(INDEX(#REF!,MATCH(ROWS($A$58:D61),#REF!,0)),"") | E61: =IFERROR(INDEX(#REF!,MATCH(ROWS($A$58:E61),#REF!,0)),"") | F61: =IFERROR(INDEX(#REF!,MATCH(ROWS($A$58:F61),#REF!,0)),"") | G61: =IFERROR(INDEX(#REF!,MATCH(ROWS($A$58:G61),#REF!,0)),"")
A62: =IFERROR(INDEX(#REF!,MATCH(ROWS($A$58:A62),#REF!,0)),"") | B62: =IFERROR(INDEX(#REF!,MATCH(ROWS($A$58:B62),#REF!,0)),"") | C62: =IFERROR(INDEX(#REF!,MATCH(ROWS($A$58:C62),#REF!,0)),"") | D62: =IFERROR(INDEX(#REF!,MATCH(ROWS($A$58:D62),#REF!,0)),"") | E62: =IFERROR(INDEX(#REF!,MATCH(ROWS($A$58:E62),#REF!,0)),"") | F62: =IFERROR(INDEX(#REF!,MATCH(ROWS($A$58:F62),#REF!,0)),"") | G62: =IFERROR(INDEX(#REF!,MATCH(ROWS($A$58:G62),#REF!,0)),"")
A65: SHUTDOWNS
A66: Shutdown ID | B66: System | C66: Building | D66: Requested Date | E66: Approved Date | F66: Scheduled Date | G66: Duration | H66: Stakeholders Notified | I66: Status | J66: Notes
A67: =IFERROR(INDEX(Shutdown_Tracker!$A$5:$A$300,MATCH(ROWS($A$67:$A67),Shutdown_Tracker!$K$5:$K$300,0)),"") | B67: =IFERROR(INDEX(Shutdown_Tracker!$B$5:$B$300,MATCH(ROWS($A$67:$A67),Shutdown_Tracker!$K$5:$K$300,0)),"") | C67: =IFERROR(INDEX(Shutdown_Tracker!$C$5:$C$300,MATCH(ROWS($A$67:$A67),Shutdown_Tracker!$K$5:$K$300,0)),"") | D67: =IFERROR(INDEX(Shutdown_Tracker!$D$5:$D$300,MATCH(ROWS($A$67:$A67),Shutdown_Tracker!$K$5:$K$300,0)),"") | E67: =IFERROR(INDEX(Shutdown_Tracker!$E$5:$E$300,MATCH(ROWS($A$67:$A67),Shutdown_Tracker!$K$5:$K$300,0)),"") | F67: =IFERROR(INDEX(Shutdown_Tracker!$F$5:$F$300,MATCH(ROWS($A$67:$A67),Shutdown_Tracker!$K$5:$K$300,0)),"") | G67: =IFERROR(INDEX(Shutdown_Tracker!$G$5:$G$300,MATCH(ROWS($A$67:$A67),Shutdown_Tracker!$K$5:$K$300,0)),"") | H67: =IFERROR(INDEX(Shutdown_Tracker!$H$5:$H$300,MATCH(ROWS($A$67:$A67),Shutdown_Tracker!$K$5:$K$300,0)),"") | I67: =IFERROR(INDEX(Shutdown_Tracker!$I$5:$I$300,MATCH(ROWS($A$67:$A67),Shutdown_Tracker!$K$5:$K$300,0)),"") | J67: =IFERROR(INDEX(Shutdown_Tracker!$J$5:$J$300,MATCH(ROWS($A$67:$A67),Shutdown_Tracker!$K$5:$K$300,0)),"")
A68: =IFERROR(INDEX(Shutdown_Tracker!$A$5:$A$300,MATCH(ROWS($A$67:$A68),Shutdown_Tracker!$K$5:$K$300,0)),"") | B68: =IFERROR(INDEX(Shutdown_Tracker!$B$5:$B$300,MATCH(ROWS($A$67:$A68),Shutdown_Tracker!$K$5:$K$300,0)),"") | C68: =IFERROR(INDEX(Shutdown_Tracker!$C$5:$C$300,MATCH(ROWS($A$67:$A68),Shutdown_Tracker!$K$5:$K$300,0)),"") | D68: =IFERROR(INDEX(Shutdown_Tracker!$D$5:$D$300,MATCH(ROWS($A$67:$A68),Shutdown_Tracker!$K$5:$K$300,0)),"") | E68: =IFERROR(INDEX(Shutdown_Tracker!$E$5:$E$300,MATCH(ROWS($A$67:$A68),Shutdown_Tracker!$K$5:$K$300,0)),"") | F68: =IFERROR(INDEX(Shutdown_Tracker!$F$5:$F$300,MATCH(ROWS($A$67:$A68),Shutdown_Tracker!$K$5:$K$300,0)),"") | G68: =IFERROR(INDEX(Shutdown_Tracker!$G$5:$G$300,MATCH(ROWS($A$67:$A68),Shutdown_Tracker!$K$5:$K$300,0)),"") | H68: =IFERROR(INDEX(Shutdown_Tracker!$H$5:$H$300,MATCH(ROWS($A$67:$A68),Shutdown_Tracker!$K$5:$K$300,0)),"") | I68: =IFERROR(INDEX(Shutdown_Tracker!$I$5:$I$300,MATCH(ROWS($A$67:$A68),Shutdown_Tracker!$K$5:$K$300,0)),"") | J68: =IFERROR(INDEX(Shutdown_Tracker!$J$5:$J$300,MATCH(ROWS($A$67:$A68),Shutdown_Tracker!$K$5:$K$300,0)),"")
A69: =IFERROR(INDEX(Shutdown_Tracker!$A$5:$A$300,MATCH(ROWS($A$67:$A69),Shutdown_Tracker!$K$5:$K$300,0)),"") | B69: =IFERROR(INDEX(Shutdown_Tracker!$B$5:$B$300,MATCH(ROWS($A$67:$A69),Shutdown_Tracker!$K$5:$K$300,0)),"") | C69: =IFERROR(INDEX(Shutdown_Tracker!$C$5:$C$300,MATCH(ROWS($A$67:$A69),Shutdown_Tracker!$K$5:$K$300,0)),"") | D69: =IFERROR(INDEX(Shutdown_Tracker!$D$5:$D$300,MATCH(ROWS($A$67:$A69),Shutdown_Tracker!$K$5:$K$300,0)),"") | E69: =IFERROR(INDEX(Shutdown_Tracker!$E$5:$E$300,MATCH(ROWS($A$67:$A69),Shutdown_Tracker!$K$5:$K$300,0)),"") | F69: =IFERROR(INDEX(Shutdown_Tracker!$F$5:$F$300,MATCH(ROWS($A$67:$A69),Shutdown_Tracker!$K$5:$K$300,0)),"") | G69: =IFERROR(INDEX(Shutdown_Tracker!$G$5:$G$300,MATCH(ROWS($A$67:$A69),Shutdown_Tracker!$K$5:$K$300,0)),"") | H69: =IFERROR(INDEX(Shutdown_Tracker!$H$5:$H$300,MATCH(ROWS($A$67:$A69),Shutdown_Tracker!$K$5:$K$300,0)),"") | I69: =IFERROR(INDEX(Shutdown_Tracker!$I$5:$I$300,MATCH(ROWS($A$67:$A69),Shutdown_Tracker!$K$5:$K$300,0)),"") | J69: =IFERROR(INDEX(Shutdown_Tracker!$J$5:$J$300,MATCH(ROWS($A$67:$A69),Shutdown_Tracker!$K$5:$K$300,0)),"")
A70: =IFERROR(INDEX(Shutdown_Tracker!$A$5:$A$300,MATCH(ROWS($A$67:$A70),Shutdown_Tracker!$K$5:$K$300,0)),"") | B70: =IFERROR(INDEX(Shutdown_Tracker!$B$5:$B$300,MATCH(ROWS($A$67:$A70),Shutdown_Tracker!$K$5:$K$300,0)),"") | C70: =IFERROR(INDEX(Shutdown_Tracker!$C$5:$C$300,MATCH(ROWS($A$67:$A70),Shutdown_Tracker!$K$5:$K$300,0)),"") | D70: =IFERROR(INDEX(Shutdown_Tracker!$D$5:$D$300,MATCH(ROWS($A$67:$A70),Shutdown_Tracker!$K$5:$K$300,0)),"") | E70: =IFERROR(INDEX(Shutdown_Tracker!$E$5:$E$300,MATCH(ROWS($A$67:$A70),Shutdown_Tracker!$K$5:$K$300,0)),"") | F70: =IFERROR(INDEX(Shutdown_Tracker!$F$5:$F$300,MATCH(ROWS($A$67:$A70),Shutdown_Tracker!$K$5:$K$300,0)),"") | G70: =IFERROR(INDEX(Shutdown_Tracker!$G$5:$G$300,MATCH(ROWS($A$67:$A70),Shutdown_Tracker!$K$5:$K$300,0)),"") | H70: =IFERROR(INDEX(Shutdown_Tracker!$H$5:$H$300,MATCH(ROWS($A$67:$A70),Shutdown_Tracker!$K$5:$K$300,0)),"") | I70: =IFERROR(INDEX(Shutdown_Tracker!$I$5:$I$300,MATCH(ROWS($A$67:$A70),Shutdown_Tracker!$K$5:$K$300,0)),"") | J70: =IFERROR(INDEX(Shutdown_Tracker!$J$5:$J$300,MATCH(ROWS($A$67:$A70),Shutdown_Tracker!$K$5:$K$300,0)),"")
A71: =IFERROR(INDEX(Shutdown_Tracker!$A$5:$A$300,MATCH(ROWS($A$67:$A71),Shutdown_Tracker!$K$5:$K$300,0)),"") | B71: =IFERROR(INDEX(Shutdown_Tracker!$B$5:$B$300,MATCH(ROWS($A$67:$A71),Shutdown_Tracker!$K$5:$K$300,0)),"") | C71: =IFERROR(INDEX(Shutdown_Tracker!$C$5:$C$300,MATCH(ROWS($A$67:$A71),Shutdown_Tracker!$K$5:$K$300,0)),"") | D71: =IFERROR(INDEX(Shutdown_Tracker!$D$5:$D$300,MATCH(ROWS($A$67:$A71),Shutdown_Tracker!$K$5:$K$300,0)),"") | E71: =IFERROR(INDEX(Shutdown_Tracker!$E$5:$E$300,MATCH(ROWS($A$67:$A71),Shutdown_Tracker!$K$5:$K$300,0)),"") | F71: =IFERROR(INDEX(Shutdown_Tracker!$F$5:$F$300,MATCH(ROWS($A$67:$A71),Shutdown_Tracker!$K$5:$K$300,0)),"") | G71: =IFERROR(INDEX(Shutdown_Tracker!$G$5:$G$300,MATCH(ROWS($A$67:$A71),Shutdown_Tracker!$K$5:$K$300,0)),"") | H71: =IFERROR(INDEX(Shutdown_Tracker!$H$5:$H$300,MATCH(ROWS($A$67:$A71),Shutdown_Tracker!$K$5:$K$300,0)),"") | I71: =IFERROR(INDEX(Shutdown_Tracker!$I$5:$I$300,MATCH(ROWS($A$67:$A71),Shutdown_Tracker!$K$5:$K$300,0)),"") | J71: =IFERROR(INDEX(Shutdown_Tracker!$J$5:$J$300,MATCH(ROWS($A$67:$A71),Shutdown_Tracker!$K$5:$K$300,0)),"")
A74: STAKEHOLDERS
A75: Building | B75: Name | C75: Organization | D75: Role | E75: Phone | F75: Email | G75: Authority / Influence | H75: Notes
A76: =IFERROR(INDEX(Building_Stakeholders!$A$5:$A$300,MATCH(ROWS($A$76:A76),Building_Stakeholders!$I$5:$I$300,0)),"") -> Campus | B76: =IFERROR(INDEX(Building_Stakeholders!$B$5:$B$300,MATCH(ROWS($A$76:B76),Building_Stakeholders!$I$5:$I$300,0)),"") -> Cameron Labbree | C76: =IFERROR(INDEX(Building_Stakeholders!$C$5:$C$300,MATCH(ROWS($A$76:C76),Building_Stakeholders!$I$5:$I$300,0)),"") -> VA Bedford | D76: =IFERROR(INDEX(Building_Stakeholders!$D$5:$D$300,MATCH(ROWS($A$76:D76),Building_Stakeholders!$I$5:$I$300,0)),"") -> Healthcare Engineer / Primary VA POC | E76: =IFERROR(INDEX(Building_Stakeholders!$E$5:$E$300,MATCH(ROWS($A$76:E76),Building_Stakeholders!$I$5:$I$300,0)),"") -> 0 | F76: =IFERROR(INDEX(Building_Stakeholders!$F$5:$F$300,MATCH(ROWS($A$76:F76),Building_Stakeholders!$I$5:$I$300,0)),"") -> 0 | G76: =IFERROR(INDEX(Building_Stakeholders!$G$5:$G$300,MATCH(ROWS($A$76:G76),Building_Stakeholders!$I$5:$I$300,0)),"") -> Primary daily VA contact | H76: =IFERROR(INDEX(Building_Stakeholders!$H$5:$H$300,MATCH(ROWS($A$76:H76),Building_Stakeholders!$I$5:$I$300,0)),"") -> 0
A77: =IFERROR(INDEX(Building_Stakeholders!$A$5:$A$300,MATCH(ROWS($A$76:A77),Building_Stakeholders!$I$5:$I$300,0)),"") -> Campus | B77: =IFERROR(INDEX(Building_Stakeholders!$B$5:$B$300,MATCH(ROWS($A$76:B77),Building_Stakeholders!$I$5:$I$300,0)),"") -> Brian Koches | C77: =IFERROR(INDEX(Building_Stakeholders!$C$5:$C$300,MATCH(ROWS($A$76:C77),Building_Stakeholders!$I$5:$I$300,0)),"") -> GCC | D77: =IFERROR(INDEX(Building_Stakeholders!$D$5:$D$300,MATCH(ROWS($A$76:D77),Building_Stakeholders!$I$5:$I$300,0)),"") -> Sr. Vice President / Primary GCC POC | E77: =IFERROR(INDEX(Building_Stakeholders!$E$5:$E$300,MATCH(ROWS($A$76:E77),Building_Stakeholders!$I$5:$I$300,0)),"") -> 0 | F77: =IFERROR(INDEX(Building_Stakeholders!$F$5:$F$300,MATCH(ROWS($A$76:F77),Building_Stakeholders!$I$5:$I$300,0)),"") -> 0 | G77: =IFERROR(INDEX(Building_Stakeholders!$G$5:$G$300,MATCH(ROWS($A$76:G77),Building_Stakeholders!$I$5:$I$300,0)),"") -> GCC primary contact | H77: =IFERROR(INDEX(Building_Stakeholders!$H$5:$H$300,MATCH(ROWS($A$76:H77),Building_Stakeholders!$I$5:$I$300,0)),"") -> 0
A78: =IFERROR(INDEX(Building_Stakeholders!$A$5:$A$300,MATCH(ROWS($A$76:A78),Building_Stakeholders!$I$5:$I$300,0)),"") -> Campus | B78: =IFERROR(INDEX(Building_Stakeholders!$B$5:$B$300,MATCH(ROWS($A$76:B78),Building_Stakeholders!$I$5:$I$300,0)),"") -> Paul Thibodeau | C78: =IFERROR(INDEX(Building_Stakeholders!$C$5:$C$300,MATCH(ROWS($A$76:C78),Building_Stakeholders!$I$5:$I$300,0)),"") -> GCC | D78: =IFERROR(INDEX(Building_Stakeholders!$D$5:$D$300,MATCH(ROWS($A$76:D78),Building_Stakeholders!$I$5:$I$300,0)),"") -> Construction Quality Inspector | E78: =IFERROR(INDEX(Building_Stakeholders!$E$5:$E$300,MATCH(ROWS($A$76:E78),Building_Stakeholders!$I$5:$I$300,0)),"") -> 0 | F78: =IFERROR(INDEX(Building_Stakeholders!$F$5:$F$300,MATCH(ROWS($A$76:F78),Building_Stakeholders!$I$5:$I$300,0)),"") -> 0 | G78: =IFERROR(INDEX(Building_Stakeholders!$G$5:$G$300,MATCH(ROWS($A$76:G78),Building_Stakeholders!$I$5:$I$300,0)),"") -> Field support / project intelligence | H78: =IFERROR(INDEX(Building_Stakeholders!$H$5:$H$300,MATCH(ROWS($A$76:H78),Building_Stakeholders!$I$5:$I$300,0)),"") -> 0
A79: =IFERROR(INDEX(Building_Stakeholders!$A$5:$A$300,MATCH(ROWS($A$76:A79),Building_Stakeholders!$I$5:$I$300,0)),"") | B79: =IFERROR(INDEX(Building_Stakeholders!$B$5:$B$300,MATCH(ROWS($A$76:B79),Building_Stakeholders!$I$5:$I$300,0)),"") | C79: =IFERROR(INDEX(Building_Stakeholders!$C$5:$C$300,MATCH(ROWS($A$76:C79),Building_Stakeholders!$I$5:$I$300,0)),"") | D79: =IFERROR(INDEX(Building_Stakeholders!$D$5:$D$300,MATCH(ROWS($A$76:D79),Building_Stakeholders!$I$5:$I$300,0)),"") | E79: =IFERROR(INDEX(Building_Stakeholders!$E$5:$E$300,MATCH(ROWS($A$76:E79),Building_Stakeholders!$I$5:$I$300,0)),"") | F79: =IFERROR(INDEX(Building_Stakeholders!$F$5:$F$300,MATCH(ROWS($A$76:F79),Building_Stakeholders!$I$5:$I$300,0)),"") | G79: =IFERROR(INDEX(Building_Stakeholders!$G$5:$G$300,MATCH(ROWS($A$76:G79),Building_Stakeholders!$I$5:$I$300,0)),"") | H79: =IFERROR(INDEX(Building_Stakeholders!$H$5:$H$300,MATCH(ROWS($A$76:H79),Building_Stakeholders!$I$5:$I$300,0)),"")
A80: =IFERROR(INDEX(Building_Stakeholders!$A$5:$A$300,MATCH(ROWS($A$76:A80),Building_Stakeholders!$I$5:$I$300,0)),"") | B80: =IFERROR(INDEX(Building_Stakeholders!$B$5:$B$300,MATCH(ROWS($A$76:B80),Building_Stakeholders!$I$5:$I$300,0)),"") | C80: =IFERROR(INDEX(Building_Stakeholders!$C$5:$C$300,MATCH(ROWS($A$76:C80),Building_Stakeholders!$I$5:$I$300,0)),"") | D80: =IFERROR(INDEX(Building_Stakeholders!$D$5:$D$300,MATCH(ROWS($A$76:D80),Building_Stakeholders!$I$5:$I$300,0)),"") | E80: =IFERROR(INDEX(Building_Stakeholders!$E$5:$E$300,MATCH(ROWS($A$76:E80),Building_Stakeholders!$I$5:$I$300,0)),"") | F80: =IFERROR(INDEX(Building_Stakeholders!$F$5:$F$300,MATCH(ROWS($A$76:F80),Building_Stakeholders!$I$5:$I$300,0)),"") | G80: =IFERROR(INDEX(Building_Stakeholders!$G$5:$G$300,MATCH(ROWS($A$76:G80),Building_Stakeholders!$I$5:$I$300,0)),"") | H80: =IFERROR(INDEX(Building_Stakeholders!$H$5:$H$300,MATCH(ROWS($A$76:H80),Building_Stakeholders!$I$5:$I$300,0)),"")
A83: HOW TO USE
A84: 1. Enter a building value in B4.
A85: 2. Use the same value in the Building column of each source register.
A86: 3. This view returns up to five matching rows per section using Excel-compatible formulas.
A87: 4. For campus-wide items, use Campus as the Building value.
A88: 5. This is a project intelligence view, not an official contract deliverable.
A90: SOURCE DATA NOTE
A91: If a section is blank, that source tab has no matching Building value yet.
A92: Campus-wide records use Building = Campus.
A93: Building-specific records use the exact building value, such as 1, 2, 80, or MCR/DC.

Sheet Command_Center
A1: BEDFORD VA EHRM — CAMPUS COMMAND STATUS | S1: Last refresh | T1: =NOW() -> 46220.364 | Z1: SelectedIndex | AA1: SelectedSheet | AB1: SelectedBuilding
B2: =IF($B$14>=0.9,"MISSION STATUS: OPERATIONAL ",IF($B$14>=0.75,"MISSION STATUS: WATCH ",IF($B$14>=0.5,"MISSION STATUS: AT RISK ","MISSION STATUS: CRITICAL ")))&REPT("█",ROUND($B$14*20,0))&REPT("░",20-ROUND($B$14*20,0))&" "&TEXT($B$14,"0%") -> MISSION STATUS: AT RISK ██████████░░░░░░░░░░ 51% | Z2: =IFERROR(MATCH($C$17,PMIS_Data!$A$3:$A$32,0),1) -> 22 | AA2: =IFERROR(INDEX(PMIS_Data!$B$3:$B$32,$Z$2),"") -> B61_Assessment | AB2: =$C$17&"" -> 61
A3: SELECTED BUILDING SOURCE DETAIL — ASSESSMENT SHEETS
A4: =HYPERLINK("#'B01_Assessment'!A1","B01"&CHAR(10)&TEXT(IFERROR(INDEX(PMIS_Data!$E:$E,MATCH("01",PMIS_Data!$A:$A,0)),0),"0%")&" "&REPT("█",ROUND(IFERROR(INDEX(PMIS_Data!$E:$E,MATCH("01",PMIS_Data!$A:$A,0)),0)*10,0))&REPT("░",10-ROUND(IFERROR(INDEX(PMIS_Data!$E:$E,MATCH("01",PMIS_Data!$A:$A,0)),0)*10,0))&CHAR(10)&"⚠ "&IFERROR(INDEX(PMIS_Data!$H:$H,MATCH("01",PMIS_Data!$A:$A,0)),"-")&" ❓ "&IFERROR(INDEX(PMIS_Data!$I:$I,MATCH("01",PMIS_Data!$A:$A,0)),"-")&CHAR(10)&" ") -> B01 50% █████░░░░░ ⚠ 0 ❓ 0 | E4: =HYPERLINK("#'B02_Assessment'!A1","B02"&CHAR(10)&TEXT(IFERROR(INDEX(PMIS_Data!$E:$E,MATCH("02",PMIS_Data!$A:$A,0)),0),"0%")&" "&REPT("█",ROUND(IFERROR(INDEX(PMIS_Data!$E:$E,MATCH("02",PMIS_Data!$A:$A,0)),0)*10,0))&REPT("░",10-ROUND(IFERROR(INDEX(PMIS_Data!$E:$E,MATCH("02",PMIS_Data!$A:$A,0)),0)*10,0))&CHAR(10)&"⚠ "&IFERROR(INDEX(PMIS_Data!$H:$H,MATCH("02",PMIS_Data!$A:$A,0)),"-")&" ❓ "&IFERROR(INDEX(PMIS_Data!$I:$I,MATCH("02",PMIS_Data!$A:$A,0)),"-")&CHAR(10)&" ") -> B02 50% █████░░░░░ ⚠ 0 ❓ 0 | I4: =HYPERLINK("#'B03_Assessment'!A1","B03"&CHAR(10)&TEXT(IFERROR(INDEX(PMIS_Data!$E:$E,MATCH("03",PMIS_Data!$A:$A,0)),0),"0%")&" "&REPT("█",ROUND(IFERROR(INDEX(PMIS_Data!$E:$E,MATCH("03",PMIS_Data!$A:$A,0)),0)*10,0))&REPT("░",10-ROUND(IFERROR(INDEX(PMIS_Data!$E:$E,MATCH("03",PMIS_Data!$A:$A,0)),0)*10,0))&CHAR(10)&"⚠ "&IFERROR(INDEX(PMIS_Data!$H:$H,MATCH("03",PMIS_Data!$A:$A,0)),"-")&" ❓ "&IFERROR(INDEX(PMIS_Data!$I:$I,MATCH("03",PMIS_Data!$A:$A,0)),"-")&CHAR(10)&" ") -> B03 50% █████░░░░░ ⚠ 0 ❓ 0 | M4: =HYPERLINK("#'B04_Assessment'!A1","B04"&CHAR(10)&TEXT(IFERROR(INDEX(PMIS_Data!$E:$E,MATCH("04",PMIS_Data!$A:$A,0)),0),"0%")&" "&REPT("█",ROUND(IFERROR(INDEX(PMIS_Data!$E:$E,MATCH("04",PMIS_Data!$A:$A,0)),0)*10,0))&REPT("░",10-ROUND(IFERROR(INDEX(PMIS_Data!$E:$E,MATCH("04",PMIS_Data!$A:$A,0)),0)*10,0))&CHAR(10)&"⚠ "&IFERROR(INDEX(PMIS_Data!$H:$H,MATCH("04",PMIS_Data!$A:$A,0)),"-")&" ❓ "&IFERROR(INDEX(PMIS_Data!$I:$I,MATCH("04",PMIS_Data!$A:$A,0)),"-")&CHAR(10)&" ") -> B04 50% █████░░░░░ ⚠ 0 ❓ 0
A5: =HYPERLINK("#'B05_Assessment'!A1","B05"&CHAR(10)&TEXT(IFERROR(INDEX(PMIS_Data!$E:$E,MATCH("05",PMIS_Data!$A:$A,0)),0),"0%")&" "&REPT("█",ROUND(IFERROR(INDEX(PMIS_Data!$E:$E,MATCH("05",PMIS_Data!$A:$A,0)),0)*10,0))&REPT("░",10-ROUND(IFERROR(INDEX(PMIS_Data!$E:$E,MATCH("05",PMIS_Data!$A:$A,0)),0)*10,0))&CHAR(10)&"⚠ "&IFERROR(INDEX(PMIS_Data!$H:$H,MATCH("05",PMIS_Data!$A:$A,0)),"-")&" ❓ "&IFERROR(INDEX(PMIS_Data!$I:$I,MATCH("05",PMIS_Data!$A:$A,0)),"-")&CHAR(10)&" ") -> B05 55% ██████░░░░ ⚠ 0 ❓ 0 | E5: =HYPERLINK("#'B06_Assessment'!A1","B06"&CHAR(10)&TEXT(IFERROR(INDEX(PMIS_Data!$E:$E,MATCH("06",PMIS_Data!$A:$A,0)),0),"0%")&" "&REPT("█",ROUND(IFERROR(INDEX(PMIS_Data!$E:$E,MATCH("06",PMIS_Data!$A:$A,0)),0)*10,0))&REPT("░",10-ROUND(IFERROR(INDEX(PMIS_Data!$E:$E,MATCH("06",PMIS_Data!$A:$A,0)),0)*10,0))&CHAR(10)&"⚠ "&IFERROR(INDEX(PMIS_Data!$H:$H,MATCH("06",PMIS_Data!$A:$A,0)),"-")&" ❓ "&IFERROR(INDEX(PMIS_Data!$I:$I,MATCH("06",PMIS_Data!$A:$A,0)),"-")&CHAR(10)&" ") -> B06 50% █████░░░░░ ⚠ 0 ❓ 0 | I5: =HYPERLINK("#'B07_Assessment'!A1","B07"&CHAR(10)&TEXT(IFERROR(INDEX(PMIS_Data!$E:$E,MATCH("07",PMIS_Data!$A:$A,0)),0),"0%")&" "&REPT("█",ROUND(IFERROR(INDEX(PMIS_Data!$E:$E,MATCH("07",PMIS_Data!$A:$A,0)),0)*10,0))&REPT("░",10-ROUND(IFERROR(INDEX(PMIS_Data!$E:$E,MATCH("07",PMIS_Data!$A:$A,0)),0)*10,0))&CHAR(10)&"⚠ "&IFERROR(INDEX(PMIS_Data!$H:$H,MATCH("07",PMIS_Data!$A:$A,0)),"-")&" ❓ "&IFERROR(INDEX(PMIS_Data!$I:$I,MATCH("07",PMIS_Data!$A:$A,0)),"-")&CHAR(10)&" ") -> B07 50% █████░░░░░ ⚠ 0 ❓ 0 | M5: =HYPERLINK("#'B08_Assessment'!A1","B08"&CHAR(10)&TEXT(IFERROR(INDEX(PMIS_Data!$E:$E,MATCH("08",PMIS_Data!$A:$A,0)),0),"0%")&" "&REPT("█",ROUND(IFERROR(INDEX(PMIS_Data!$E:$E,MATCH("08",PMIS_Data!$A:$A,0)),0)*10,0))&REPT("░",10-ROUND(IFERROR(INDEX(PMIS_Data!$E:$E,MATCH("08",PMIS_Data!$A:$A,0)),0)*10,0))&CHAR(10)&"⚠ "&IFERROR(INDEX(PMIS_Data!$H:$H,MATCH("08",PMIS_Data!$A:$A,0)),"-")&" ❓ "&IFERROR(INDEX(PMIS_Data!$I:$I,MATCH("08",PMIS_Data!$A:$A,0)),"-")&CHAR(10)&" ") -> B08 50% █████░░░░░ ⚠ 0 ❓ 0
A6: =HYPERLINK("#'B09_Assessment'!A1","B09"&CHAR(10)&TEXT(IFERROR(INDEX(PMIS_Data!$E:$E,MATCH("09",PMIS_Data!$A:$A,0)),0),"0%")&" "&REPT("█",ROUND(IFERROR(INDEX(PMIS_Data!$E:$E,MATCH("09",PMIS_Data!$A:$A,0)),0)*10,0))&REPT("░",10-ROUND(IFERROR(INDEX(PMIS_Data!$E:$E,MATCH("09",PMIS_Data!$A:$A,0)),0)*10,0))&CHAR(10)&"⚠ "&IFERROR(INDEX(PMIS_Data!$H:$H,MATCH("09",PMIS_Data!$A:$A,0)),"-")&" ❓ "&IFERROR(INDEX(PMIS_Data!$I:$I,MATCH("09",PMIS_Data!$A:$A,0)),"-")&CHAR(10)&" ") -> B09 50% █████░░░░░ ⚠ 0 ❓ 0 | E6: =HYPERLINK("#'B10_Assessment'!A1","B10"&CHAR(10)&TEXT(IFERROR(INDEX(PMIS_Data!$E:$E,MATCH("10",PMIS_Data!$A:$A,0)),0),"0%")&" "&REPT("█",ROUND(IFERROR(INDEX(PMIS_Data!$E:$E,MATCH("10",PMIS_Data!$A:$A,0)),0)*10,0))&REPT("░",10-ROUND(IFERROR(INDEX(PMIS_Data!$E:$E,MATCH("10",PMIS_Data!$A:$A,0)),0)*10,0))&CHAR(10)&"⚠ "&IFERROR(INDEX(PMIS_Data!$H:$H,MATCH("10",PMIS_Data!$A:$A,0)),"-")&" ❓ "&IFERROR(INDEX(PMIS_Data!$I:$I,MATCH("10",PMIS_Data!$A:$A,0)),"-")&CHAR(10)&" ") -> B10 50% █████░░░░░ ⚠ 0 ❓ 0 | I6: =HYPERLINK("#'B12_Assessment'!A1","B12"&CHAR(10)&TEXT(IFERROR(INDEX(PMIS_Data!$E:$E,MATCH("12",PMIS_Data!$A:$A,0)),0),"0%")&" "&REPT("█",ROUND(IFERROR(INDEX(PMIS_Data!$E:$E,MATCH("12",PMIS_Data!$A:$A,0)),0)*10,0))&REPT("░",10-ROUND(IFERROR(INDEX(PMIS_Data!$E:$E,MATCH("12",PMIS_Data!$A:$A,0)),0)*10,0))&CHAR(10)&"⚠ "&IFERROR(INDEX(PMIS_Data!$H:$H,MATCH("12",PMIS_Data!$A:$A,0)),"-")&" ❓ "&IFERROR(INDEX(PMIS_Data!$I:$I,MATCH("12",PMIS_Data!$A:$A,0)),"-")&CHAR(10)&" ") -> B12 60% ██████░░░░ ⚠ 0 ❓ 0 | M6: =HYPERLINK("#'B13_Assessment'!A1","B13"&CHAR(10)&TEXT(IFERROR(INDEX(PMIS_Data!$E:$E,MATCH("13",PMIS_Data!$A:$A,0)),0),"0%")&" "&REPT("█",ROUND(IFERROR(INDEX(PMIS_Data!$E:$E,MATCH("13",PMIS_Data!$A:$A,0)),0)*10,0))&REPT("░",10-ROUND(IFERROR(INDEX(PMIS_Data!$E:$E,MATCH("13",PMIS_Data!$A:$A,0)),0)*10,0))&CHAR(10)&"⚠ "&IFERROR(INDEX(PMIS_Data!$H:$H,MATCH("13",PMIS_Data!$A:$A,0)),"-")&" ❓ "&IFERROR(INDEX(PMIS_Data!$I:$I,MATCH("13",PMIS_Data!$A:$A,0)),"-")&CHAR(10)&" ") -> B13 50% █████░░░░░ ⚠ 0 ❓ 0
A7: =HYPERLINK("#'B14_Assessment'!A1","B14"&CHAR(10)&TEXT(IFERROR(INDEX(PMIS_Data!$E:$E,MATCH("14",PMIS_Data!$A:$A,0)),0),"0%")&" "&REPT("█",ROUND(IFERROR(INDEX(PMIS_Data!$E:$E,MATCH("14",PMIS_Data!$A:$A,0)),0)*10,0))&REPT("░",10-ROUND(IFERROR(INDEX(PMIS_Data!$E:$E,MATCH("14",PMIS_Data!$A:$A,0)),0)*10,0))&CHAR(10)&"⚠ "&IFERROR(INDEX(PMIS_Data!$H:$H,MATCH("14",PMIS_Data!$A:$A,0)),"-")&" ❓ "&IFERROR(INDEX(PMIS_Data!$I:$I,MATCH("14",PMIS_Data!$A:$A,0)),"-")&CHAR(10)&" ") -> B14 50% █████░░░░░ ⚠ 0 ❓ 0 | E7: =HYPERLINK("#'B15_Assessment'!A1","B15"&CHAR(10)&TEXT(IFERROR(INDEX(PMIS_Data!$E:$E,MATCH("15",PMIS_Data!$A:$A,0)),0),"0%")&" "&REPT("█",ROUND(IFERROR(INDEX(PMIS_Data!$E:$E,MATCH("15",PMIS_Data!$A:$A,0)),0)*10,0))&REPT("░",10-ROUND(IFERROR(INDEX(PMIS_Data!$E:$E,MATCH("15",PMIS_Data!$A:$A,0)),0)*10,0))&CHAR(10)&"⚠ "&IFERROR(INDEX(PMIS_Data!$H:$H,MATCH("15",PMIS_Data!$A:$A,0)),"-")&" ❓ "&IFERROR(INDEX(PMIS_Data!$I:$I,MATCH("15",PMIS_Data!$A:$A,0)),"-")&CHAR(10)&" ") -> B15 50% █████░░░░░ ⚠ 0 ❓ 0 | I7: =HYPERLINK("#'B16_Assessment'!A1","B16"&CHAR(10)&TEXT(IFERROR(INDEX(PMIS_Data!$E:$E,MATCH("16",PMIS_Data!$A:$A,0)),0),"0%")&" "&REPT("█",ROUND(IFERROR(INDEX(PMIS_Data!$E:$E,MATCH("16",PMIS_Data!$A:$A,0)),0)*10,0))&REPT("░",10-ROUND(IFERROR(INDEX(PMIS_Data!$E:$E,MATCH("16",PMIS_Data!$A:$A,0)),0)*10,0))&CHAR(10)&"⚠ "&IFERROR(INDEX(PMIS_Data!$H:$H,MATCH("16",PMIS_Data!$A:$A,0)),"-")&" ❓ "&IFERROR(INDEX(PMIS_Data!$I:$I,MATCH("16",PMIS_Data!$A:$A,0)),"-")&CHAR(10)&" ") -> B16 50% █████░░░░░ ⚠ 0 ❓ 0 | M7: =HYPERLINK("#'B17_Assessment'!A1","B17"&CHAR(10)&TEXT(IFERROR(INDEX(PMIS_Data!$E:$E,MATCH("17",PMIS_Data!$A:$A,0)),0),"0%")&" "&REPT("█",ROUND(IFERROR(INDEX(PMIS_Data!$E:$E,MATCH("17",PMIS_Data!$A:$A,0)),0)*10,0))&REPT("░",10-ROUND(IFERROR(INDEX(PMIS_Data!$E:$E,MATCH("17",PMIS_Data!$A:$A,0)),0)*10,0))&CHAR(10)&"⚠ "&IFERROR(INDEX(PMIS_Data!$H:$H,MATCH("17",PMIS_Data!$A:$A,0)),"-")&" ❓ "&IFERROR(INDEX(PMIS_Data!$I:$I,MATCH("17",PMIS_Data!$A:$A,0)),"-")&CHAR(10)&" ") -> B17 50% █████░░░░░ ⚠ 0 ❓ 0
A8: =HYPERLINK("#'B18_Assessment'!A1","B18"&CHAR(10)&TEXT(IFERROR(INDEX(PMIS_Data!$E:$E,MATCH("18",PMIS_Data!$A:$A,0)),0),"0%")&" "&REPT("█",ROUND(IFERROR(INDEX(PMIS_Data!$E:$E,MATCH("18",PMIS_Data!$A:$A,0)),0)*10,0))&REPT("░",10-ROUND(IFERROR(INDEX(PMIS_Data!$E:$E,MATCH("18",PMIS_Data!$A:$A,0)),0)*10,0))&CHAR(10)&"⚠ "&IFERROR(INDEX(PMIS_Data!$H:$H,MATCH("18",PMIS_Data!$A:$A,0)),"-")&" ❓ "&IFERROR(INDEX(PMIS_Data!$I:$I,MATCH("18",PMIS_Data!$A:$A,0)),"-")&CHAR(10)&" ") -> B18 50% █████░░░░░ ⚠ 0 ❓ 0 | E8: =HYPERLINK("#'B20_Assessment'!A1","B20"&CHAR(10)&TEXT(IFERROR(INDEX(PMIS_Data!$E:$E,MATCH("20",PMIS_Data!$A:$A,0)),0),"0%")&" "&REPT("█",ROUND(IFERROR(INDEX(PMIS_Data!$E:$E,MATCH("20",PMIS_Data!$A:$A,0)),0)*10,0))&REPT("░",10-ROUND(IFERROR(INDEX(PMIS_Data!$E:$E,MATCH("20",PMIS_Data!$A:$A,0)),0)*10,0))&CHAR(10)&"⚠ "&IFERROR(INDEX(PMIS_Data!$H:$H,MATCH("20",PMIS_Data!$A:$A,0)),"-")&" ❓ "&IFERROR(INDEX(PMIS_Data!$I:$I,MATCH("20",PMIS_Data!$A:$A,0)),"-")&CHAR(10)&" ") -> B20 50% █████░░░░░ ⚠ 0 ❓ 0 | I8: =HYPERLINK("#'B21_Assessment'!A1","B21"&CHAR(10)&TEXT(IFERROR(INDEX(PMIS_Data!$E:$E,MATCH("21",PMIS_Data!$A:$A,0)),0),"0%")&" "&REPT("█",ROUND(IFERROR(INDEX(PMIS_Data!$E:$E,MATCH("21",PMIS_Data!$A:$A,0)),0)*10,0))&REPT("░",10-ROUND(IFERROR(INDEX(PMIS_Data!$E:$E,MATCH("21",PMIS_Data!$A:$A,0)),0)*10,0))&CHAR(10)&"⚠ "&IFERROR(INDEX(PMIS_Data!$H:$H,MATCH("21",PMIS_Data!$A:$A,0)),"-")&" ❓ "&IFERROR(INDEX(PMIS_Data!$I:$I,MATCH("21",PMIS_Data!$A:$A,0)),"-")&CHAR(10)&" ") -> B21 50% █████░░░░░ ⚠ 0 ❓ 0 | M8: =HYPERLINK("#'B22_Assessment'!A1","B22"&CHAR(10)&TEXT(IFERROR(INDEX(PMIS_Data!$E:$E,MATCH("22",PMIS_Data!$A:$A,0)),0),"0%")&" "&REPT("█",ROUND(IFERROR(INDEX(PMIS_Data!$E:$E,MATCH("22",PMIS_Data!$A:$A,0)),0)*10,0))&REPT("░",10-ROUND(IFERROR(INDEX(PMIS_Data!$E:$E,MATCH("22",PMIS_Data!$A:$A,0)),0)*10,0))&CHAR(10)&"⚠ "&IFERROR(INDEX(PMIS_Data!$H:$H,MATCH("22",PMIS_Data!$A:$A,0)),"-")&" ❓ "&IFERROR(INDEX(PMIS_Data!$I:$I,MATCH("22",PMIS_Data!$A:$A,0)),"-")&CHAR(10)&" ") -> B22 50% █████░░░░░ ⚠ 0 ❓ 0
A9: =HYPERLINK("#'B33_Assessment'!A1","B33"&CHAR(10)&TEXT(IFERROR(INDEX(PMIS_Data!$E:$E,MATCH("33",PMIS_Data!$A:$A,0)),0),"0%")&" "&REPT("█",ROUND(IFERROR(INDEX(PMIS_Data!$E:$E,MATCH("33",PMIS_Data!$A:$A,0)),0)*10,0))&REPT("░",10-ROUND(IFERROR(INDEX(PMIS_Data!$E:$E,MATCH("33",PMIS_Data!$A:$A,0)),0)*10,0))&CHAR(10)&"⚠ "&IFERROR(INDEX(PMIS_Data!$H:$H,MATCH("33",PMIS_Data!$A:$A,0)),"-")&" ❓ "&IFERROR(INDEX(PMIS_Data!$I:$I,MATCH("33",PMIS_Data!$A:$A,0)),"-")&CHAR(10)&" ") -> B33 50% █████░░░░░ ⚠ 0 ❓ 0 | E9: =HYPERLINK("#'B61_Assessment'!A1","B61"&CHAR(10)&TEXT(IFERROR(INDEX(PMIS_Data!$E:$E,MATCH("61",PMIS_Data!$A:$A,0)),0),"0%")&" "&REPT("█",ROUND(IFERROR(INDEX(PMIS_Data!$E:$E,MATCH("61",PMIS_Data!$A:$A,0)),0)*10,0))&REPT("░",10-ROUND(IFERROR(INDEX(PMIS_Data!$E:$E,MATCH("61",PMIS_Data!$A:$A,0)),0)*10,0))&CHAR(10)&"⚠ "&IFERROR(INDEX(PMIS_Data!$H:$H,MATCH("61",PMIS_Data!$A:$A,0)),"-")&" ❓ "&IFERROR(INDEX(PMIS_Data!$I:$I,MATCH("61",PMIS_Data!$A:$A,0)),"-")&CHAR(10)&"PILOT ") -> B61 55% ██████░░░░ ⚠ 0 ❓ 0 PILOT | I9: =HYPERLINK("#'B62_TR_Assessment'!A1","B62"&CHAR(10)&TEXT(IFERROR(INDEX(PMIS_Data!$E:$E,MATCH("62",PMIS_Data!$A:$A,0)),0),"0%")&" "&REPT("█",ROUND(IFERROR(INDEX(PMIS_Data!$E:$E,MATCH("62",PMIS_Data!$A:$A,0)),0)*10,0))&REPT("░",10-ROUND(IFERROR(INDEX(PMIS_Data!$E:$E,MATCH("62",PMIS_Data!$A:$A,0)),0)*10,0))&CHAR(10)&"⚠ "&IFERROR(INDEX(PMIS_Data!$H:$H,MATCH("62",PMIS_Data!$A:$A,0)),"-")&" ❓ "&IFERROR(INDEX(PMIS_Data!$I:$I,MATCH("62",PMIS_Data!$A:$A,0)),"-")&CHAR(10)&" ") -> B62 50% █████░░░░░ ⚠ 0 ❓ 0 | M9: =HYPERLINK("#'B70_TR_Assessment'!A1","B70"&CHAR(10)&TEXT(IFERROR(INDEX(PMIS_Data!$E:$E,MATCH("70",PMIS_Data!$A:$A,0)),0),"0%")&" "&REPT("█",ROUND(IFERROR(INDEX(PMIS_Data!$E:$E,MATCH("70",PMIS_Data!$A:$A,0)),0)*10,0))&REPT("░",10-ROUND(IFERROR(INDEX(PMIS_Data!$E:$E,MATCH("70",PMIS_Data!$A:$A,0)),0)*10,0))&CHAR(10)&"⚠ "&IFERROR(INDEX(PMIS_Data!$H:$H,MATCH("70",PMIS_Data!$A:$A,0)),"-")&" ❓ "&IFERROR(INDEX(PMIS_Data!$I:$I,MATCH("70",PMIS_Data!$A:$A,0)),"-")&CHAR(10)&" ") -> B70 50% █████░░░░░ ⚠ 0 ❓ 0
A10: =HYPERLINK("#'B78_Assessment'!A1","B78"&CHAR(10)&TEXT(IFERROR(INDEX(PMIS_Data!$E:$E,MATCH("78",PMIS_Data!$A:$A,0)),0),"0%")&" "&REPT("█",ROUND(IFERROR(INDEX(PMIS_Data!$E:$E,MATCH("78",PMIS_Data!$A:$A,0)),0)*10,0))&REPT("░",10-ROUND(IFERROR(INDEX(PMIS_Data!$E:$E,MATCH("78",PMIS_Data!$A:$A,0)),0)*10,0))&CHAR(10)&"⚠ "&IFERROR(INDEX(PMIS_Data!$H:$H,MATCH("78",PMIS_Data!$A:$A,0)),"-")&" ❓ "&IFERROR(INDEX(PMIS_Data!$I:$I,MATCH("78",PMIS_Data!$A:$A,0)),"-")&CHAR(10)&" ") -> B78 50% █████░░░░░ ⚠ 0 ❓ 0 | E10: =HYPERLINK("#'B80_Assessment'!A1","B80"&CHAR(10)&TEXT(IFERROR(INDEX(PMIS_Data!$E:$E,MATCH("80",PMIS_Data!$A:$A,0)),0),"0%")&" "&REPT("█",ROUND(IFERROR(INDEX(PMIS_Data!$E:$E,MATCH("80",PMIS_Data!$A:$A,0)),0)*10,0))&REPT("░",10-ROUND(IFERROR(INDEX(PMIS_Data!$E:$E,MATCH("80",PMIS_Data!$A:$A,0)),0)*10,0))&CHAR(10)&"⚠ "&IFERROR(INDEX(PMIS_Data!$H:$H,MATCH("80",PMIS_Data!$A:$A,0)),"-")&" ❓ "&IFERROR(INDEX(PMIS_Data!$I:$I,MATCH("80",PMIS_Data!$A:$A,0)),"-")&CHAR(10)&" ") -> B80 50% █████░░░░░ ⚠ 0 ❓ 0 | I10: =HYPERLINK("#'B82_Assessment'!A1","B82"&CHAR(10)&TEXT(IFERROR(INDEX(PMIS_Data!$E:$E,MATCH("82",PMIS_Data!$A:$A,0)),0),"0%")&" "&REPT("█",ROUND(IFERROR(INDEX(PMIS_Data!$E:$E,MATCH("82",PMIS_Data!$A:$A,0)),0)*10,0))&REPT("░",10-ROUND(IFERROR(INDEX(PMIS_Data!$E:$E,MATCH("82",PMIS_Data!$A:$A,0)),0)*10,0))&CHAR(10)&"⚠ "&IFERROR(INDEX(PMIS_Data!$H:$H,MATCH("82",PMIS_Data!$A:$A,0)),"-")&" ❓ "&IFERROR(INDEX(PMIS_Data!$I:$I,MATCH("82",PMIS_Data!$A:$A,0)),"-")&CHAR(10)&" ") -> B82 50% █████░░░░░ ⚠ 0 ❓ 0 | M10: =HYPERLINK("#'BCH_Assessment'!A1","BCH"&CHAR(10)&TEXT(IFERROR(INDEX(PMIS_Data!$E:$E,MATCH("BCH",PMIS_Data!$A:$A,0)),0),"0%")&" "&REPT("█",ROUND(IFERROR(INDEX(PMIS_Data!$E:$E,MATCH("BCH",PMIS_Data!$A:$A,0)),0)*10,0))&REPT("░",10-ROUND(IFERROR(INDEX(PMIS_Data!$E:$E,MATCH("BCH",PMIS_Data!$A:$A,0)),0)*10,0))&CHAR(10)&"⚠ "&IFERROR(INDEX(PMIS_Data!$H:$H,MATCH("BCH",PMIS_Data!$A:$A,0)),"-")&" ❓ "&IFERROR(INDEX(PMIS_Data!$I:$I,MATCH("BCH",PMIS_Data!$A:$A,0)),"-")&CHAR(10)&" ") -> BCH 50% █████░░░░░ ⚠ 0 ❓ 0
A11: =HYPERLINK("#'MCR_Assessment'!A1","MCR"&CHAR(10)&TEXT(IFERROR(INDEX(PMIS_Data!$E:$E,MATCH("MCR",PMIS_Data!$A:$A,0)),0),"0%")&" "&REPT("█",ROUND(IFERROR(INDEX(PMIS_Data!$E:$E,MATCH("MCR",PMIS_Data!$A:$A,0)),0)*10,0))&REPT("░",10-ROUND(IFERROR(INDEX(PMIS_Data!$E:$E,MATCH("MCR",PMIS_Data!$A:$A,0)),0)*10,0))&CHAR(10)&"⚠ "&IFERROR(INDEX(PMIS_Data!$H:$H,MATCH("MCR",PMIS_Data!$A:$A,0)),"-")&" ❓ "&IFERROR(INDEX(PMIS_Data!$I:$I,MATCH("MCR",PMIS_Data!$A:$A,0)),"-")&CHAR(10)&" ") -> MCR 50% █████░░░░░ ⚠ 0 ❓ 0 | E11: =HYPERLINK("#'SITE_Assesment'!A1","SITE"&CHAR(10)&TEXT(IFERROR(INDEX(PMIS_Data!$E:$E,MATCH("SITE",PMIS_Data!$A:$A,0)),0),"0%")&" "&REPT("█",ROUND(IFERROR(INDEX(PMIS_Data!$E:$E,MATCH("SITE",PMIS_Data!$A:$A,0)),0)*10,0))&REPT("░",10-ROUND(IFERROR(INDEX(PMIS_Data!$E:$E,MATCH("SITE",PMIS_Data!$A:$A,0)),0)*10,0))&CHAR(10)&"⚠ "&IFERROR(INDEX(PMIS_Data!$H:$H,MATCH("SITE",PMIS_Data!$A:$A,0)),"-")&" ❓ "&IFERROR(INDEX(PMIS_Data!$I:$I,MATCH("SITE",PMIS_Data!$A:$A,0)),"-")&CHAR(10)&" ") -> SITE 50% █████░░░░░ ⚠ 0 ❓ 0 | I11: =HYPERLINK("#'SPEC_Assessment'!A1","SPEC"&CHAR(10)&TEXT(IFERROR(INDEX(PMIS_Data!$E:$E,MATCH("SPEC",PMIS_Data!$A:$A,0)),0),"0%")&" "&REPT("█",ROUND(IFERROR(INDEX(PMIS_Data!$E:$E,MATCH("SPEC",PMIS_Data!$A:$A,0)),0)*10,0))&REPT("░",10-ROUND(IFERROR(INDEX(PMIS_Data!$E:$E,MATCH("SPEC",PMIS_Data!$A:$A,0)),0)*10,0))&CHAR(10)&"⚠ "&IFERROR(INDEX(PMIS_Data!$H:$H,MATCH("SPEC",PMIS_Data!$A:$A,0)),"-")&" ❓ "&IFERROR(INDEX(PMIS_Data!$I:$I,MATCH("SPEC",PMIS_Data!$A:$A,0)),"-")&CHAR(10)&" ") -> SPEC 0% ░░░░░░░░░░ ⚠ - ❓ - | R11: QA | S11: =HYPERLINK("#'Data_Health'!A1","Data Health") -> Data Health
R12: Guide | S12: =HYPERLINK("#'README_ARCHITECTURE'!A1","Architecture") -> Architecture
B13: CAMPUS HEALTH | D13: BUILDINGS ASSESSED | F13: OPEN RISKS | H13: OPEN QUESTIONS | J13: OPEN PHOTOS | L13: ACTIVE SHUTDOWNS | N13: NOT READY | R13: Focus | S13: =HYPERLINK("#'Today''s_Focus'!A1","Today's Focus") -> Today's Focus
B14: =IFERROR(AVERAGE(PMIS_Data!$E$3:$E$32),0) -> 0.50666667 | D14: =COUNTA(PMIS_Data!$A$3:$A$32) -> 30 | F14: =SUM(PMIS_Data!$H$3:$H$32) -> 0 | H14: =SUM(PMIS_Data!$I$3:$I$32) -> 0 | J14: =SUM(PMIS_Data!$J$3:$J$32) -> 0 | L14: =SUM(PMIS_Data!$X$3:$X$32) -> 0 | N14: =COUNTIF(PMIS_Data!$F$3:$F$32,"No") -> 29
B16: ACTIVE MISSION | J16: PROGRESS OVERVIEW
B17: MISSION TARGET | C17: 61 | F17: READINESS SIGNAL
B18: SELECTED ASSET | C18: ="Building "&TEXT($C$17,"00") -> Building 61 | F18: BAR | G18: =REPT("█",ROUND($F$19*12,0))&REPT("░",12-ROUND($F$19*12,0)) -> ███████░░░░░ | J18: ="ROOMS"&CHAR(10)&IFERROR(INDEX(PMIS_Data!$G$3:$G$100,$Z$2),0) -> ROOMS 29 | L18: ="FIRE"&CHAR(10)&IF(IFERROR(INDEX(PMIS_Data!$N$3:$N$100,$Z$2),"")="Pass","✓ PASS",IFERROR(INDEX(PMIS_Data!$N$3:$N$100,$Z$2),"REVIEW")) -> FIRE Not Started
B19: MISSION STATUS | C19: =IF($F$19>=0.9,"OPERATIONAL",IF($F$19>=0.75,"WATCH",IF($F$19>=0.5,"AT RISK","CRITICAL"))) -> AT RISK | F19: =IFERROR(INDEX(PMIS_Data!$E$3:$E$94,$Z$2),0) -> 0.55
B20: ASSESSMENT SHEET | C20: =IFERROR(INDEX(PMIS_Data!$B$3:$B$94,$Z$2),"") -> B61_Assessment
J21: ="HVAC"&CHAR(10)&IF(IFERROR(INDEX(PMIS_Data!$K$3:$K$100,$Z$2),"")="Pass","✓ PASS",IFERROR(INDEX(PMIS_Data!$K$3:$K$100,$Z$2),"REVIEW")) -> HVAC Not Started | L21: ="ELECTRICAL"&CHAR(10)&IF(IFERROR(INDEX(PMIS_Data!$L$3:$L$100,$Z$2),"")="Pass","✓ PASS",IFERROR(INDEX(PMIS_Data!$L$3:$L$100,$Z$2),"REVIEW")) -> ELECTRICAL Not Started
B22: OVERALL STATUS | C22: =IFERROR(INDEX(PMIS_Data!$C$3:$C$94,$Z$2),"") -> PILOT PHASE
B24: CONSTRUCTION READY | C24: =IFERROR(INDEX(PMIS_Data!$F$3:$F$94,$Z$2),"") -> YES | J24: ="TELECOM"&CHAR(10)&IF(IFERROR(INDEX(PMIS_Data!$M$3:$M$100,$Z$2),"")="Pass","✓ PASS",IFERROR(INDEX(PMIS_Data!$M$3:$M$100,$Z$2),"REVIEW")) -> TELECOM Not Started | L24: ="SECURITY"&CHAR(10)&IF(IFERROR(INDEX(PMIS_Data!$P$3:$P$100,$Z$2),"")="Pass","✓ PASS",IFERROR(INDEX(PMIS_Data!$P$3:$P$100,$Z$2),"REVIEW")) -> SECURITY Not Started
B30: RISK SUMMARY | F30: OPEN QUESTIONS | J30: DOCUMENTS / PHOTOS | N30: SHUTDOWNS
B32: Open Risks | D32: =IFERROR(INDEX(PMIS_Data!$H$3:$H$94,$Z$2),0) -> 0 | F32: Selected Open | H32: =IFERROR(INDEX(PMIS_Data!$I$3:$I$94,$Z$2),0) -> 0 | J32: Open Photos | L32: =IFERROR(INDEX(PMIS_Data!$J$3:$J$94,$Z$2),0) -> 0 | N32: Selected Active | P32: =IFERROR(INDEX(PMIS_Data!$X$3:$X$94,$Z$2),0) -> 0
B34: Campus Open | D34: =SUM(PMIS_Data!$H$3:$H$32) -> 0 | F34: Campus Open | H34: =SUM(PMIS_Data!$I$3:$I$32) -> 0 | J34: Campus Docs | L34: =COUNTA(Doc_Register!$A$5:$A$300) -> 40 | N34: Campus Active | P34: =SUM(PMIS_Data!$X$3:$X$32) -> 0
B36: Selected Rank | D36: =IFERROR(INDEX(_V4_ActionQueue!$A$4:$A$33,MATCH($C$17,_V4_ActionQueue!$B$4:$B$33,0)),"") -> 30 | F36: High Priority | H36: =COUNTIFS(#REF!,"High",#REF!,"Open") -> #REF! | J36: Campus Photos | L36: =COUNTA(#REF!) -> 1 | N36: Not Ready | P36: =COUNTIF(PMIS_Data!$F$3:$F$32,"No") -> 29
B40: SELECTED BUILDING DETAIL — LIVE FROM PMIS_Data
B41: =HYPERLINK("#'"&$AA$2&"'!A1","Open selected Building Assessment") -> Open selected Building Assessment
A42: Building | B42: Sheet | C42: Status | D42: Readiness | E42: Ready | F42: Rooms | G42: Risks | H42: Questions | I42: Photos | J42: Shutdowns | K42: Pilot Gate | L42: Open Gates
A43: =$C$17&"" -> 61 | B43: =IFERROR(INDEX(PMIS_Data!$B$3:$B$94,$Z$2),"") -> B61_Assessment | C43: =IFERROR(INDEX(PMIS_Data!$C$3:$C$94,$Z$2),"") -> PILOT PHASE | D43: =IFERROR(INDEX(PMIS_Data!$E$3:$E$94,$Z$2),0) -> 0.55 | E43: =IFERROR(INDEX(PMIS_Data!$F$3:$F$94,$Z$2),"") -> YES | F43: =IFERROR(INDEX(PMIS_Data!$G$3:$G$94,$Z$2),0) -> 29 | G43: =IFERROR(INDEX(PMIS_Data!$H$3:$H$94,$Z$2),0) -> 0 | H43: =IFERROR(INDEX(PMIS_Data!$I$3:$I$94,$Z$2),0) -> 0 | I43: =IFERROR(INDEX(PMIS_Data!$J$3:$J$94,$Z$2),0) -> 0 | J43: =IFERROR(INDEX(PMIS_Data!$X$3:$X$94,$Z$2),0) -> 0 | K43: =IFERROR(INDEX(PMIS_Data!$AK:$AK,MATCH($A$46,PMIS_Data!$A:$A,0)),0) -> 0 | L43: =IFERROR(INDEX(PMIS_Data!$AL:$AL,MATCH($A$46,PMIS_Data!$A:$A,0)),0) -> 0 | AA43: Selected_Assessment_Sheet | AB43: =IF($Z$46="Campus","Select a building tile for trade-level notes.",IFERROR(INDEX(_Command_Trade_Notes!$B:$B,MATCH($Z$46,_Command_Trade_Notes!$A:$A,0)),"No fire/life safety notes captured.")) -> • Dedicated TR scope includes fire protection drawings. Verify sprinkler modifications, fire alarm devices, clean-agent 2A:10B:C FEC within 75 ft, rated penetrations, and temporary firestopping. • Verify sprinkler/fire alarm modifications, clean-agent FEC location, penetrations, cable tray/riser openings, and final UL firestop systems. • Verify second-level TR sprinkler/fire alarm modifications, clean-agent FEC location, vertical riser penetrations, and firestopping. • Existing demarc/server rooms may remain active; verify protection-in-place, FA/FP continuity, and no unsealed penetrations after cabling work. | AC43: =IF($Z$46="Campus","Select a building tile for trade-level notes.",IFERROR(INDEX(_Command_Trade_Notes!$C:$C,MATCH($Z$46,_Command_Trade_Notes!$A:$A,0)),"No HVAC/cooling notes captured.")) -> • Mechanical sheets identify dedicated split-system cooling with BACnet adapter mounted adjacent to unit in telecom room. Confirm capacity, emergency source, condensate, disconnect, controls, and alarms. • Mechanical/electrical plans identify IU-1-01/CU-1-01 for first-level TR. Confirm 24/7 operation, emergency/standby source and high-temp alarm. • Mechanical/electrical plans identify IU-2-01/CU-2-01 for second-level TR. Confirm refrigerant route, condensate route, controls and alarm tie-in. • Existing demarc/server equipment likely has existing cooling dependencies. Verify active equipment heat load, airflow, operational temperatures and whether any existing cooling is modified or protected. | AD43: =IF($Z$46="Campus","Select a building tile for trade-level notes.",IFERROR(INDEX(_Command_Trade_Notes!$D:$D,MATCH($Z$46,_Command_Trade_Notes!$A:$A,0)),"No electrical/UPS notes captured.")) -> • Electrical enlarged plans and schedules identify rack receptacles, UPS circuits, PDUs, panelboards, SPD devices and dedicated cooling power for B13H-A. Verify B61-TRB13A/B source, LOTO and labels. • Electrical schedules identify B61-TR124A/B and rack receptacles. Verify apparent room-name mismatch with RM137B rack receptacles in schedules. • Electrical schedules identify B61-TR226A/B, rack receptacles, CU-2-01 and SPD requirements. Verify source circuits and labels. • Existing rack inventory includes APC UPS/PDU and server/demarc equipment. Electrical one-line/schedules list B61-TR137AA/AB and PD-B61-TR137 panels; verify active sources and transition impact. | AE43: =IF($Z$46="Campus","Select a building tile for trade-level notes.",IFERROR(INDEX(_Command_Trade_Notes!$E:$E,MATCH($Z$46,_Command_Trade_Notes!$A:$A,0)),"No telecom/fiber notes captured.")) -> • 61T-701: 88 WAO total, 74 active ports, 129 scheduled ports, 142 with 10% allowance. Rack ID TR01-B13H-A-1. Basement cable tray included in 890 ft basement total. • 61T-701: first-level Room 124 / Rack ID TR01-124-1. Schedule data runs across first-level outlets. Include labels, Fiber LIU, Cat6A patch panels, UPS/PDU and VA/OIT acceptance. • 61T-702: 109 WAO total, 126 active ports, 156 scheduled ports, 172 with 10% allowance. Rack ID TR01-226-1. Verify second-level cable tray and riser penetrations. • 61T-402/606/607 inventory existing demarc/server racks and equipment. Protect active systems, coordinate cutover, preserve labels, document equipment remaining in service. | AF43: =IF($Z$46="Campus","Select a building tile for trade-level notes.",IFERROR(INDEX(_Command_Trade_Notes!$F:$F,MATCH($Z$46,_Command_Trade_Notes!$A:$A,0)),"No security/PACS/CCTV notes captured.")) -> • Telecom plans call for wall-mounted CCTV at TRs and PACS for TR doors. Verify camera, controller, CR/RX/DC/ES/MD, and VMS/PACS integration. • Verify TR door hardware and access control, CCTV camera, network door controller and integration. • Verify second-level TR access control, CCTV camera, door hardware, and VMS/PACS integration. • Existing PACS/equipment racks are referenced. Verify existing security devices protected-in-place and any new recabling or integration scope. | AG43: =IF($Z$46="Campus","Select a building tile for risk notes.",IFERROR(INDEX(_Command_Trade_Notes!$G:$G,MATCH($Z$46,_Command_Trade_Notes!$A:$A,0)),"No owner risk notes captured.")) -> • High: Existing conditions and active equipment across B13H-A, 124, 226 and 137/137A not field verified — Perform existing conditions survey with photos and active-service inventory before mobilization • High: Hazardous material abatement plans exist for first and second levels — Coordinate IH/abatement review before penetrations, wall/ceiling work, cabling or mechanical/electrical installation • Critical: Existing server/demarc equipment may remain active during cutover — Document active services, service provider circuits, rack inventory, OIT windows, temporary utilities and rollback path • Critical: Dedicated cooling sequence, emergency power, condensate, BACnet and alarms not verified — Confirm IU/CU-0/1/2 power source, condensate, controls, BACnet adapter, thermostat and high-temp alarm • Critical: Panel source, UPS/PDU and rack receptacle coordination could delay energization — Verify B61-TRB13A/B, B61-TR124A/B, B61-TR226A/B, B61-TR137AA/AB, PD panels, SPDs and load measurements • High: Large cable tray scope creates coordination and firestop risk — Verify 1,966 ft cable tray route, supports, seismic bracing, 40% fill, MEP conflicts, sleeves and final firestop assemblies
A45: Selected Building | B45: Selected Sheet | C45: Payment Confidence | D45: Payment Decision | E45: OIT Readiness | F45: OIT Status | G45: OIT Blocker | H45: Material Compliance | I45: Productivity | J45: Acceptance Readiness | K45: Owner Decision | L45: Signal | Z45: Selected_Display_Label
A46: =IFERROR(TEXT(VALUE($C$17),"00"),$C$17&"") -> 61 | B46: =IFERROR(INDEX(PMIS_Data!$B:$B,MATCH($A$46,PMIS_Data!$A:$A,0)),"") -> B61_Assessment | C46: =IFERROR(INDEX(PMIS_Data!$Z:$Z,MATCH($A$46,PMIS_Data!$A:$A,0)),0) -> 0 | D46: =IFERROR(INDEX(PMIS_Data!$AA:$AA,MATCH($A$46,PMIS_Data!$A:$A,0)),"") -> Withhold / Review | E46: =IFERROR(INDEX(PMIS_Data!$AB:$AB,MATCH($A$46,PMIS_Data!$A:$A,0)),0) -> 0 | F46: =IFERROR(INDEX(PMIS_Data!$AC:$AC,MATCH($A$46,PMIS_Data!$A:$A,0)),"") -> Blocked | G46: =IFERROR(INDEX(PMIS_Data!$AD:$AD,MATCH($A$46,PMIS_Data!$A:$A,0)),"") -> No blocker documented | H46: =IFERROR(INDEX(PMIS_Data!$AE:$AE,MATCH($A$46,PMIS_Data!$A:$A,0)),0) -> 0 | I46: =IFERROR(INDEX(PMIS_Data!$AG:$AG,MATCH($A$46,PMIS_Data!$A:$A,0)),0) -> 0 | J46: =IFERROR(INDEX(PMIS_Data!$AI:$AI,MATCH($A$46,PMIS_Data!$A:$A,0)),0) -> 0 | K46: =IFERROR(INDEX(PMIS_Data!$AM:$AM,MATCH($A$46,PMIS_Data!$A:$A,0)),"") -> Resolve OIT Blocker | L46: =IFERROR(INDEX(PMIS_Data!$AN:$AN,MATCH($A$46,PMIS_Data!$A:$A,0)),"") -> 🔴 ATTENTION | Z46: =IF($G$48="Campus","Campus",IFERROR(INDEX(_Command_Lists!$B$2:$B$33,MATCH($G$48,_Command_Lists!$A$2:$A$33,0)),$G$48)) -> 61
AA47: =IFERROR(INDEX(_Command_Source!$B:$B,MATCH($Z$46,_Command_Source!$A:$A,0)),"") -> B61_Assessment
A48: BUILDING MISSION MODULES — CLICK TILE TO OPEN ASSESSMENT | G48: =IFERROR(INDEX(_Command_Lists!$A$2:$A$33,MATCH($C$17&"",_Command_Lists!$B$2:$B$33,0)),IFERROR("B"&TEXT(VALUE($C$17),"00"),$C$17&"")) -> B61 | I48: Use the selector to refresh the Command Center. Tiles are hyperlinks to source assessment sheets.
A50: ="SELECTED BUILDING WORKSPACE — "&$G$48&" OPERATIONAL PICTURE" -> SELECTED BUILDING WORKSPACE — B61 OPERATIONAL PICTURE
A51: =IF($Z$46="Campus","🌐 CAMPUS PROGRAM VIEW"&CHAR(10)&"Readiness: "&TEXT(AVERAGEIF(PMIS_Data!$E$3:$E$44,">0"),"0%")&CHAR(10)&"Open Risks: "&SUM(PMIS_Data!$H$3:$H$44)&CHAR(10)&"Open RFIs: "&SUM(PMIS_Data!$I$3:$I$44),IFERROR("🏢 BUILDING "&$G$48&CHAR(10)&"Status: "&INDEX(PMIS_Data!$C:$C,MATCH($Z$46,PMIS_Data!$A:$A,0))&CHAR(10)&"Readiness: "&TEXT(INDEX(PMIS_Data!$E:$E,MATCH($Z$46,PMIS_Data!$A:$A,0)),"0%")&CHAR(10)&"Construction Ready: "&INDEX(PMIS_Data!$F:$F,MATCH($Z$46,PMIS_Data!$A:$A,0))&CHAR(10)&"Rooms Captured: "&INDEX(PMIS_Data!$G:$G,MATCH($Z$46,PMIS_Data!$A:$A,0)),"No profile available.")) -> 🏢 BUILDING B61 Status: PILOT PHASE Readiness: 55% Construction Ready: YES Rooms Captured: 29 | E51: =IF($Z$46="Campus","⚠ CAMPUS BLOCKERS"&CHAR(10)&"Risks: "&SUM(PMIS_Data!$H$3:$H$44)&CHAR(10)&"RFIs: "&SUM(PMIS_Data!$I$3:$I$44)&CHAR(10)&"Review red/yellow building modules.",IFERROR("⚠ CURRENT BLOCKERS"&CHAR(10)&"Open Risks: "&INDEX(PMIS_Data!$H:$H,MATCH($Z$46,PMIS_Data!$A:$A,0))&CHAR(10)&"Open Questions: "&INDEX(PMIS_Data!$I:$I,MATCH($Z$46,PMIS_Data!$A:$A,0))&CHAR(10)&"Major Blocker: "&INDEX(PMIS_Data!$R:$R,MATCH($Z$46,PMIS_Data!$A:$A,0)),"No blocker data.")) -> ⚠ CURRENT BLOCKERS Open Risks: 0 Open Questions: 0 Major Blocker: Building 61 is a large full-scope TR building with hazardous abatement, architectural, fire protection, plumbing, mechanical, electrical, security, telecom, server/demarc and rack elevation scope. Primary new telecom rooms include basement B13H-A, first-level 124, second-level 226, and existing Room 137/137A demarc/server equipment. Major open issues include active-service cutover, dedicated cooling IU/CU-0-01/1-01/2-01, panel source coordination, rack UPS/PDU power, cable tray coordination, firestopping, PACS/CCTV, and turnover testing. | I51: =IF($Z$46="Campus","📷 FIELD CAPTURE"&CHAR(10)&"Open Photos: "&SUM(PMIS_Data!$J$3:$J$44)&CHAR(10)&"Documents: review register.",IFERROR("📷 FIELD CAPTURE"&CHAR(10)&"Open Photo Items: "&INDEX(PMIS_Data!$J:$J,MATCH($Z$46,PMIS_Data!$A:$A,0))&CHAR(10)&"HVAC: "&INDEX(PMIS_Data!$K:$K,MATCH($Z$46,PMIS_Data!$A:$A,0))&CHAR(10)&"Electrical: "&INDEX(PMIS_Data!$L:$L,MATCH($Z$46,PMIS_Data!$A:$A,0))&CHAR(10)&"Telecom: "&INDEX(PMIS_Data!$M:$M,MATCH($Z$46,PMIS_Data!$A:$A,0)),"No field data.")) -> 📷 FIELD CAPTURE Open Photo Items: 0 HVAC: Not Started Electrical: Not Started Telecom: Not Started | M51: =IF($Z$46="Campus","✅ NEXT REQUIRED ACTION"&CHAR(10)&"Triage campus-wide red/yellow tiles and issue closeout tasks.",IFERROR("✅ NEXT REQUIRED ACTION"&CHAR(10)&INDEX(PMIS_Data!$Q:$Q,MATCH($Z$46,PMIS_Data!$A:$A,0))&CHAR(10)&"Source: "&INDEX(PMIS_Data!$B:$B,MATCH($Z$46,PMIS_Data!$A:$A,0)),"No action data.")) -> ✅ NEXT REQUIRED ACTION Field verify B13H-A, 124, 226, and existing 137/137A; confirm active services, rack/equipment transfer, B61-TRB13A/B, B61-TR124A/B, B61-TR226A/B, B61-TR137AA/AB panel sources, IU/CU equipment, fire alarm/sprinkler impacts, FEC locations, PACS/CCTV scope, hazardous/abatement impacts, 1,966 ft cable tray routes, and cutover sequence. Source: B61_Assessment
A60: MISSION FEED — NEXT ACTIONS / RELEASE POSTURE
A61: =IF($Z$46="Campus","🌐 Campus: review critical modules, open risks, RFIs, shutdowns, and field capture gaps."&CHAR(10)&"• Select a building for module-level feed."&CHAR(10)&"• Building tiles open assessment source sheets.",IFERROR("🏢 "&$G$48&" Mission Feed"&CHAR(10)&"• Next Action: "&INDEX(PMIS_Data!$Q:$Q,MATCH($Z$46,PMIS_Data!$A:$A,0))&CHAR(10)&"• Major Blocker: "&INDEX(PMIS_Data!$R:$R,MATCH($Z$46,PMIS_Data!$A:$A,0))&CHAR(10)&"• Risks/RFIs/Photos: "&INDEX(PMIS_Data!$H:$H,MATCH($Z$46,PMIS_Data!$A:$A,0))&" / "&INDEX(PMIS_Data!$I:$I,MATCH($Z$46,PMIS_Data!$A:$A,0))&" / "&INDEX(PMIS_Data!$J:$J,MATCH($Z$46,PMIS_Data!$A:$A,0)),"No mission feed available.")) -> 🏢 B61 Mission Feed • Next Action: Field verify B13H-A, 124, 226, and existing 137/137A; confirm active services, rack/equipment transfer, B61-TRB13A/B, B61-TR124A/B, B61-TR226A/B, B61-TR137AA/AB panel sources, IU/CU equipment, fire alarm/sprinkler impacts, FEC locations, PACS/CCTV scope, hazardous/abatement impacts, 1,966 ft cable tray routes, and cutover sequence. • Major Blocker: Building 61 is a large full-scope TR building with hazardous abatement, architectural, fire protection, plumbing, mechanical, electrical, security, telecom, server/demarc and rack elevation scope. Primary new telecom rooms include basement B13H-A, first-level 124, second-level 226, and existing Room 137/137A demarc/server equipment. Major open issues include active-service cutover, dedicated cooling IU/CU-0-01/1-01/2-01, panel source coordination, rack UPS/PDU power, cable tray coordination, firestopping, PACS/CCTV, and turnover testing. • Risks/RFIs/Photos: 0 / 0 / 0
A70: TRADE SECTION CARDS — SELECTED BUILDING NOTES
A71: ="🔥 FIRE / LIFE SAFETY"&CHAR(10)&AB43 -> 🔥 FIRE / LIFE SAFETY • Dedicated TR scope includes fire protection drawings. Verify sprinkler modifications, fire alarm devices, clean-agent 2A:10B:C FEC within 75 ft, rated penetrations, and temporary firestopping. • Verify sprinkler/fire alarm modifications, clean-agent FEC location, penetrations, cable tray/riser openings, and final UL firestop systems. • Verify second-level TR sprinkler/fire alarm modifications, clean-agent FEC location, vertical riser penetrations, and firestopping. • Existing demarc/server rooms may remain active; verify protection-in-place, FA/FP continuity, and no unsealed penetrations after cabling work. | I71: ="❄ HVAC / COOLING"&CHAR(10)&AC43 -> ❄ HVAC / COOLING • Mechanical sheets identify dedicated split-system cooling with BACnet adapter mounted adjacent to unit in telecom room. Confirm capacity, emergency source, condensate, disconnect, controls, and alarms. • Mechanical/electrical plans identify IU-1-01/CU-1-01 for first-level TR. Confirm 24/7 operation, emergency/standby source and high-temp alarm. • Mechanical/electrical plans identify IU-2-01/CU-2-01 for second-level TR. Confirm refrigerant route, condensate route, controls and alarm tie-in. • Existing demarc/server equipment likely has existing cooling dependencies. Verify active equipment heat load, airflow, operational temperatures and whether any existing cooling is modified or protected.
A78: ="⚡ ELECTRICAL / UPS"&CHAR(10)&AD43 -> ⚡ ELECTRICAL / UPS • Electrical enlarged plans and schedules identify rack receptacles, UPS circuits, PDUs, panelboards, SPD devices and dedicated cooling power for B13H-A. Verify B61-TRB13A/B source, LOTO and labels. • Electrical schedules identify B61-TR124A/B and rack receptacles. Verify apparent room-name mismatch with RM137B rack receptacles in schedules. • Electrical schedules identify B61-TR226A/B, rack receptacles, CU-2-01 and SPD requirements. Verify source circuits and labels. • Existing rack inventory includes APC UPS/PDU and server/demarc equipment. Electrical one-line/schedules list B61-TR137AA/AB and PD-B61-TR137 panels; verify active sources and transition impact. | I78: ="📡 TELECOM / FIBER"&CHAR(10)&AE43 -> 📡 TELECOM / FIBER • 61T-701: 88 WAO total, 74 active ports, 129 scheduled ports, 142 with 10% allowance. Rack ID TR01-B13H-A-1. Basement cable tray included in 890 ft basement total. • 61T-701: first-level Room 124 / Rack ID TR01-124-1. Schedule data runs across first-level outlets. Include labels, Fiber LIU, Cat6A patch panels, UPS/PDU and VA/OIT acceptance. • 61T-702: 109 WAO total, 126 active ports, 156 scheduled ports, 172 with 10% allowance. Rack ID TR01-226-1. Verify second-level cable tray and riser penetrations. • 61T-402/606/607 inventory existing demarc/server racks and equipment. Protect active systems, coordinate cutover, preserve labels, document equipment remaining in service.
A85: ="🔐 SECURITY / PACS / CCTV"&CHAR(10)&AF43 -> 🔐 SECURITY / PACS / CCTV • Telecom plans call for wall-mounted CCTV at TRs and PACS for TR doors. Verify camera, controller, CR/RX/DC/ES/MD, and VMS/PACS integration. • Verify TR door hardware and access control, CCTV camera, network door controller and integration. • Verify second-level TR access control, CCTV camera, door hardware, and VMS/PACS integration. • Existing PACS/equipment racks are referenced. Verify existing security devices protected-in-place and any new recabling or integration scope. | I85: ="❓ RISKS / OPEN QUESTIONS"&CHAR(10)&"Owner Risks:"&CHAR(10)&AG43&CHAR(10)&"Open Questions:"&CHAR(10)&AH43 -> ❓ RISKS / OPEN QUESTIONS Owner Risks: • High: Existing conditions and active equipment across B13H-A, 124, 226 and 137/137A not field verified — Perform existing conditions survey with photos and active-service inventory before mobilization • High: Hazardous material abatement plans exist for first and second levels — Coordinate IH/abatement review before penetrations, wall/ceiling work, cabling or mechanical/electrical installation • Critical: Existing server/demarc equipment may remain active during cutover — Document active services, service provider circuits, rack inventory, OIT windows, temporary utilities and rollback path • Critical: Dedicated cooling sequence, emergency power, condensate, BACnet and alarms not verified — Confirm IU/CU-0/1/2 power source, condensate, controls, BACnet adapter, thermostat and high-temp alarm • Critical: Panel source, UPS/PDU and rack receptacle coordination could delay energization — Verify B61-TRB13A/B, B61-TR124A/B, B61-TR226A/B, B61-TR137AA/AB, PD panels, SPDs and load measurements • High: Large cable tray scope creates coordination and firestop risk — Verify 1,966 ft cable tray route, supports, seismic bracing, 40% fill, MEP conflicts, sleeves and final firestop assemblies Open Questions:
A92: SOURCE OF TRUTH: Building assessment sheets remain authoritative. The Command Center reads from PMIS_Data, _Command_Card_Index, and _Assessment_Full_View.
A95: SELECTED BUILDING SOURCE DETAIL — FIRST 25 ASSESSMENT ROWS (HIDDEN)
A96: Section | C96: Room / Area | E96: Item / System | H96: Impact / Detail | K96: Status / Owner | N96: Notes
A97: =IFERROR(INDEX(_Assessment_Full_View!$E:$E,MATCH($Z$46&"|"&ROWS($A$97:A97),_Assessment_Full_View!$Q:$Q,0)),"") -> 1. ROOM INVENTORY | C97: =IFERROR(INDEX(_Assessment_Full_View!$G:$G,MATCH($Z$46&"|"&ROWS($A$97:A97),_Assessment_Full_View!$Q:$Q,0))&" / "&INDEX(_Assessment_Full_View!$H:$H,MATCH($Z$46&"|"&ROWS($A$97:A97),_Assessment_Full_View!$Q:$Q,0)),"") -> 1. ROOM INVENTORY / 0 | E97: =IFERROR(INDEX(_Assessment_Full_View!$I:$I,MATCH($Z$46&"|"&ROWS($A$97:A97),_Assessment_Full_View!$Q:$Q,0))&" / "&INDEX(_Assessment_Full_View!$J:$J,MATCH($Z$46&"|"&ROWS($A$97:A97),_Assessment_Full_View!$Q:$Q,0)),"") -> 0 / 0 | H97: =IFERROR(INDEX(_Assessment_Full_View!$K:$K,MATCH($Z$46&"|"&ROWS($A$97:A97),_Assessment_Full_View!$Q:$Q,0))&" / "&INDEX(_Assessment_Full_View!$L:$L,MATCH($Z$46&"|"&ROWS($A$97:A97),_Assessment_Full_View!$Q:$Q,0)),"") -> 0 / 0 | K97: =IFERROR(INDEX(_Assessment_Full_View!$O:$O,MATCH($Z$46&"|"&ROWS($A$97:A97),_Assessment_Full_View!$Q:$Q,0)),"") -> 0 | N97: =IFERROR(INDEX(_Assessment_Full_View!$P:$P,MATCH($Z$46&"|"&ROWS($A$97:A97),_Assessment_Full_View!$Q:$Q,0)),"") -> 0
A98: =IFERROR(INDEX(_Assessment_Full_View!$E:$E,MATCH($Z$46&"|"&ROWS($A$97:A98),_Assessment_Full_View!$Q:$Q,0)),"") -> 1. ROOM INVENTORY | C98: =IFERROR(INDEX(_Assessment_Full_View!$G:$G,MATCH($Z$46&"|"&ROWS($A$97:A98),_Assessment_Full_View!$Q:$Q,0))&" / "&INDEX(_Assessment_Full_View!$H:$H,MATCH($Z$46&"|"&ROWS($A$97:A98),_Assessment_Full_View!$Q:$Q,0)),"") -> Building / Room | E98: =IFERROR(INDEX(_Assessment_Full_View!$I:$I,MATCH($Z$46&"|"&ROWS($A$97:A98),_Assessment_Full_View!$Q:$Q,0))&" / "&INDEX(_Assessment_Full_View!$J:$J,MATCH($Z$46&"|"&ROWS($A$97:A98),_Assessment_Full_View!$Q:$Q,0)),"") -> Floor / Existing Use | H98: =IFERROR(INDEX(_Assessment_Full_View!$K:$K,MATCH($Z$46&"|"&ROWS($A$97:A98),_Assessment_Full_View!$Q:$Q,0))&" / "&INDEX(_Assessment_Full_View!$L:$L,MATCH($Z$46&"|"&ROWS($A$97:A98),_Assessment_Full_View!$Q:$Q,0)),"") -> New Use / Rack Count | K98: =IFERROR(INDEX(_Assessment_Full_View!$O:$O,MATCH($Z$46&"|"&ROWS($A$97:A98),_Assessment_Full_View!$Q:$Q,0)),"") -> Drawing Ref | N98: =IFERROR(INDEX(_Assessment_Full_View!$P:$P,MATCH($Z$46&"|"&ROWS($A$97:A98),_Assessment_Full_View!$Q:$Q,0)),"") -> Notes
A99: =IFERROR(INDEX(_Assessment_Full_View!$E:$E,MATCH($Z$46&"|"&ROWS($A$97:A99),_Assessment_Full_View!$Q:$Q,0)),"") -> 1. ROOM INVENTORY | C99: =IFERROR(INDEX(_Assessment_Full_View!$G:$G,MATCH($Z$46&"|"&ROWS($A$97:A99),_Assessment_Full_View!$Q:$Q,0))&" / "&INDEX(_Assessment_Full_View!$H:$H,MATCH($Z$46&"|"&ROWS($A$97:A99),_Assessment_Full_View!$Q:$Q,0)),"") -> 61 / B13H-A | E99: =IFERROR(INDEX(_Assessment_Full_View!$I:$I,MATCH($Z$46&"|"&ROWS($A$97:A99),_Assessment_Full_View!$Q:$Q,0))&" / "&INDEX(_Assessment_Full_View!$J:$J,MATCH($Z$46&"|"&ROWS($A$97:A99),_Assessment_Full_View!$Q:$Q,0)),"") -> Basement / Basement telecom / support area | H99: =IFERROR(INDEX(_Assessment_Full_View!$K:$K,MATCH($Z$46&"|"&ROWS($A$97:A99),_Assessment_Full_View!$Q:$Q,0))&" / "&INDEX(_Assessment_Full_View!$L:$L,MATCH($Z$46&"|"&ROWS($A$97:A99),_Assessment_Full_View!$Q:$Q,0)),"") -> Telecom Room / 1 | K99: =IFERROR(INDEX(_Assessment_Full_View!$O:$O,MATCH($Z$46&"|"&ROWS($A$97:A99),_Assessment_Full_View!$Q:$Q,0)),"") -> 61A-400 / 61E-401 / 61T-100 / 61T-401 / 61T-604 / 61T-701 | N99: =IFERROR(INDEX(_Assessment_Full_View!$P:$P,MATCH($Z$46&"|"&ROWS($A$97:A99),_Assessment_Full_View!$Q:$Q,0)),"") -> Basement TR identified as RM B13H-A with Rack ID TR01-B13H-A-1. Schedules identify 88 WAO total, 74 active ports, 129 scheduled ports, 142 ports with 10% allowance. Electrical panels include B61-TRB13A/B. Mechanical cooling includes IU-0-01/CU-0-01.
A100: =IFERROR(INDEX(_Assessment_Full_View!$E:$E,MATCH($Z$46&"|"&ROWS($A$97:A100),_Assessment_Full_View!$Q:$Q,0)),"") -> 1. ROOM INVENTORY | C100: =IFERROR(INDEX(_Assessment_Full_View!$G:$G,MATCH($Z$46&"|"&ROWS($A$97:A100),_Assessment_Full_View!$Q:$Q,0))&" / "&INDEX(_Assessment_Full_View!$H:$H,MATCH($Z$46&"|"&ROWS($A$97:A100),_Assessment_Full_View!$Q:$Q,0)),"") -> 61 / 124 | E100: =IFERROR(INDEX(_Assessment_Full_View!$I:$I,MATCH($Z$46&"|"&ROWS($A$97:A100),_Assessment_Full_View!$Q:$Q,0))&" / "&INDEX(_Assessment_Full_View!$J:$J,MATCH($Z$46&"|"&ROWS($A$97:A100),_Assessment_Full_View!$Q:$Q,0)),"") -> First / First-level telecom area | H100: =IFERROR(INDEX(_Assessment_Full_View!$K:$K,MATCH($Z$46&"|"&ROWS($A$97:A100),_Assessment_Full_View!$Q:$Q,0))&" / "&INDEX(_Assessment_Full_View!$L:$L,MATCH($Z$46&"|"&ROWS($A$97:A100),_Assessment_Full_View!$Q:$Q,0)),"") -> Telecom Room / 1 | K100: =IFERROR(INDEX(_Assessment_Full_View!$O:$O,MATCH($Z$46&"|"&ROWS($A$97:A100),_Assessment_Full_View!$Q:$Q,0)),"") -> 61A-400 / 61E-402 / 61T-101 / 61T-401 / 61T-604 / 61T-701 | N100: =IFERROR(INDEX(_Assessment_Full_View!$P:$P,MATCH($Z$46&"|"&ROWS($A$97:A100),_Assessment_Full_View!$Q:$Q,0)),"") -> First-level TR identified as Room 124 / Rack ID TR01-124-1. Electrical panels include B61-TR124A/B. Mechanical cooling includes IU-1-01/CU-1-01. Verify room naming against electrical schedule references that also call out RM137B rack receptacles.
A101: =IFERROR(INDEX(_Assessment_Full_View!$E:$E,MATCH($Z$46&"|"&ROWS($A$97:A101),_Assessment_Full_View!$Q:$Q,0)),"") -> 1. ROOM INVENTORY | C101: =IFERROR(INDEX(_Assessment_Full_View!$G:$G,MATCH($Z$46&"|"&ROWS($A$97:A101),_Assessment_Full_View!$Q:$Q,0))&" / "&INDEX(_Assessment_Full_View!$H:$H,MATCH($Z$46&"|"&ROWS($A$97:A101),_Assessment_Full_View!$Q:$Q,0)),"") -> 61 / 226 | E101: =IFERROR(INDEX(_Assessment_Full_View!$I:$I,MATCH($Z$46&"|"&ROWS($A$97:A101),_Assessment_Full_View!$Q:$Q,0))&" / "&INDEX(_Assessment_Full_View!$J:$J,MATCH($Z$46&"|"&ROWS($A$97:A101),_Assessment_Full_View!$Q:$Q,0)),"") -> Second / Second-level telecom area | H101: =IFERROR(INDEX(_Assessment_Full_View!$K:$K,MATCH($Z$46&"|"&ROWS($A$97:A101),_Assessment_Full_View!$Q:$Q,0))&" / "&INDEX(_Assessment_Full_View!$L:$L,MATCH($Z$46&"|"&ROWS($A$97:A101),_Assessment_Full_View!$Q:$Q,0)),"") -> Telecom Room / 1 | K101: =IFERROR(INDEX(_Assessment_Full_View!$O:$O,MATCH($Z$46&"|"&ROWS($A$97:A101),_Assessment_Full_View!$Q:$Q,0)),"") -> 61A-401 / 61E-402 / 61T-102 / 61T-401 / 61T-605 / 61T-702 | N101: =IFERROR(INDEX(_Assessment_Full_View!$P:$P,MATCH($Z$46&"|"&ROWS($A$97:A101),_Assessment_Full_View!$Q:$Q,0)),"") -> Second-level TR identified as Room 226 / Rack ID TR01-226-1. Schedules identify 109 WAO total, 126 active ports, 156 scheduled ports, 172 ports with 10% allowance. Electrical panels include B61-TR226A/B. Mechanical cooling includes IU-2-01/CU-2-01.
A102: =IFERROR(INDEX(_Assessment_Full_View!$E:$E,MATCH($Z$46&"|"&ROWS($A$97:A102),_Assessment_Full_View!$Q:$Q,0)),"") -> 1. ROOM INVENTORY | C102: =IFERROR(INDEX(_Assessment_Full_View!$G:$G,MATCH($Z$46&"|"&ROWS($A$97:A102),_Assessment_Full_View!$Q:$Q,0))&" / "&INDEX(_Assessment_Full_View!$H:$H,MATCH($Z$46&"|"&ROWS($A$97:A102),_Assessment_Full_View!$Q:$Q,0)),"") -> 61 / 137 / 137A | E102: =IFERROR(INDEX(_Assessment_Full_View!$I:$I,MATCH($Z$46&"|"&ROWS($A$97:A102),_Assessment_Full_View!$Q:$Q,0))&" / "&INDEX(_Assessment_Full_View!$J:$J,MATCH($Z$46&"|"&ROWS($A$97:A102),_Assessment_Full_View!$Q:$Q,0)),"") -> First / Existing server/demarc/telecom equipment rooms | H102: =IFERROR(INDEX(_Assessment_Full_View!$K:$K,MATCH($Z$46&"|"&ROWS($A$97:A102),_Assessment_Full_View!$Q:$Q,0))&" / "&INDEX(_Assessment_Full_View!$L:$L,MATCH($Z$46&"|"&ROWS($A$97:A102),_Assessment_Full_View!$Q:$Q,0)),"") -> Existing demarc / server transition point / 11 | K102: =IFERROR(INDEX(_Assessment_Full_View!$O:$O,MATCH($Z$46&"|"&ROWS($A$97:A102),_Assessment_Full_View!$Q:$Q,0)),"") -> 61T-402 / 61T-606 / 61T-607 / 61R-900 | N102: =IFERROR(INDEX(_Assessment_Full_View!$P:$P,MATCH($Z$46&"|"&ROWS($A$97:A102),_Assessment_Full_View!$Q:$Q,0)),"") -> Existing Room 137/137A rack inventory and demarc/server equipment include existing 4-post racks, PACS/equipment racks, APC UPS/PDU equipment, Fujitsu FLM equipment, wall-mounted patch panels, and local elevations. Protect active services and verify what remains, transfers, or is modified.
A103: =IFERROR(INDEX(_Assessment_Full_View!$E:$E,MATCH($Z$46&"|"&ROWS($A$97:A103),_Assessment_Full_View!$Q:$Q,0)),"") -> 1. ROOM INVENTORY | C103: =IFERROR(INDEX(_Assessment_Full_View!$G:$G,MATCH($Z$46&"|"&ROWS($A$97:A103),_Assessment_Full_View!$Q:$Q,0))&" / "&INDEX(_Assessment_Full_View!$H:$H,MATCH($Z$46&"|"&ROWS($A$97:A103),_Assessment_Full_View!$Q:$Q,0)),"") -> 0 / 0 | E103: =IFERROR(INDEX(_Assessment_Full_View!$I:$I,MATCH($Z$46&"|"&ROWS($A$97:A103),_Assessment_Full_View!$Q:$Q,0))&" / "&INDEX(_Assessment_Full_View!$J:$J,MATCH($Z$46&"|"&ROWS($A$97:A103),_Assessment_Full_View!$Q:$Q,0)),"") -> 0 / 0 | H103: =IFERROR(INDEX(_Assessment_Full_View!$K:$K,MATCH($Z$46&"|"&ROWS($A$97:A103),_Assessment_Full_View!$Q:$Q,0))&" / "&INDEX(_Assessment_Full_View!$L:$L,MATCH($Z$46&"|"&ROWS($A$97:A103),_Assessment_Full_View!$Q:$Q,0)),"") -> 0 / 0 | K103: =IFERROR(INDEX(_Assessment_Full_View!$O:$O,MATCH($Z$46&"|"&ROWS($A$97:A103),_Assessment_Full_View!$Q:$Q,0)),"") -> 0 | N103: =IFERROR(INDEX(_Assessment_Full_View!$P:$P,MATCH($Z$46&"|"&ROWS($A$97:A103),_Assessment_Full_View!$Q:$Q,0)),"") -> 0
A104: =IFERROR(INDEX(_Assessment_Full_View!$E:$E,MATCH($Z$46&"|"&ROWS($A$97:A104),_Assessment_Full_View!$Q:$Q,0)),"") -> 2. ROOM READINESS | C104: =IFERROR(INDEX(_Assessment_Full_View!$G:$G,MATCH($Z$46&"|"&ROWS($A$97:A104),_Assessment_Full_View!$Q:$Q,0))&" / "&INDEX(_Assessment_Full_View!$H:$H,MATCH($Z$46&"|"&ROWS($A$97:A104),_Assessment_Full_View!$Q:$Q,0)),"") -> 2. ROOM READINESS / 0 | E104: =IFERROR(INDEX(_Assessment_Full_View!$I:$I,MATCH($Z$46&"|"&ROWS($A$97:A104),_Assessment_Full_View!$Q:$Q,0))&" / "&INDEX(_Assessment_Full_View!$J:$J,MATCH($Z$46&"|"&ROWS($A$97:A104),_Assessment_Full_View!$Q:$Q,0)),"") -> 0 / 0 | H104: =IFERROR(INDEX(_Assessment_Full_View!$K:$K,MATCH($Z$46&"|"&ROWS($A$97:A104),_Assessment_Full_View!$Q:$Q,0))&" / "&INDEX(_Assessment_Full_View!$L:$L,MATCH($Z$46&"|"&ROWS($A$97:A104),_Assessment_Full_View!$Q:$Q,0)),"") -> 0 / 0 | K104: =IFERROR(INDEX(_Assessment_Full_View!$O:$O,MATCH($Z$46&"|"&ROWS($A$97:A104),_Assessment_Full_View!$Q:$Q,0)),"") -> 0 | N104: =IFERROR(INDEX(_Assessment_Full_View!$P:$P,MATCH($Z$46&"|"&ROWS($A$97:A104),_Assessment_Full_View!$Q:$Q,0)),"") -> 0
A105: =IFERROR(INDEX(_Assessment_Full_View!$E:$E,MATCH($Z$46&"|"&ROWS($A$97:A105),_Assessment_Full_View!$Q:$Q,0)),"") -> 2. ROOM READINESS | C105: =IFERROR(INDEX(_Assessment_Full_View!$G:$G,MATCH($Z$46&"|"&ROWS($A$97:A105),_Assessment_Full_View!$Q:$Q,0))&" / "&INDEX(_Assessment_Full_View!$H:$H,MATCH($Z$46&"|"&ROWS($A$97:A105),_Assessment_Full_View!$Q:$Q,0)),"") -> Room / Walls / 1-hr Rating | E105: =IFERROR(INDEX(_Assessment_Full_View!$I:$I,MATCH($Z$46&"|"&ROWS($A$97:A105),_Assessment_Full_View!$Q:$Q,0))&" / "&INDEX(_Assessment_Full_View!$J:$J,MATCH($Z$46&"|"&ROWS($A$97:A105),_Assessment_Full_View!$Q:$Q,0)),"") -> Ceiling / Floor / SDC | H105: =IFERROR(INDEX(_Assessment_Full_View!$K:$K,MATCH($Z$46&"|"&ROWS($A$97:A105),_Assessment_Full_View!$Q:$Q,0))&" / "&INDEX(_Assessment_Full_View!$L:$L,MATCH($Z$46&"|"&ROWS($A$97:A105),_Assessment_Full_View!$Q:$Q,0)),"") -> Penetrations / Access Control | K105: =IFERROR(INDEX(_Assessment_Full_View!$O:$O,MATCH($Z$46&"|"&ROWS($A$97:A105),_Assessment_Full_View!$Q:$Q,0)),"") -> Overall | N105: =IFERROR(INDEX(_Assessment_Full_View!$P:$P,MATCH($Z$46&"|"&ROWS($A$97:A105),_Assessment_Full_View!$Q:$Q,0)),"") -> Comments
A106: =IFERROR(INDEX(_Assessment_Full_View!$E:$E,MATCH($Z$46&"|"&ROWS($A$97:A106),_Assessment_Full_View!$Q:$Q,0)),"") -> 2. ROOM READINESS | C106: =IFERROR(INDEX(_Assessment_Full_View!$G:$G,MATCH($Z$46&"|"&ROWS($A$97:A106),_Assessment_Full_View!$Q:$Q,0))&" / "&INDEX(_Assessment_Full_View!$H:$H,MATCH($Z$46&"|"&ROWS($A$97:A106),_Assessment_Full_View!$Q:$Q,0)),"") -> B13H-A / Verify | E106: =IFERROR(INDEX(_Assessment_Full_View!$I:$I,MATCH($Z$46&"|"&ROWS($A$97:A106),_Assessment_Full_View!$Q:$Q,0))&" / "&INDEX(_Assessment_Full_View!$J:$J,MATCH($Z$46&"|"&ROWS($A$97:A106),_Assessment_Full_View!$Q:$Q,0)),"") -> Verify / Verify | H106: =IFERROR(INDEX(_Assessment_Full_View!$K:$K,MATCH($Z$46&"|"&ROWS($A$97:A106),_Assessment_Full_View!$Q:$Q,0))&" / "&INDEX(_Assessment_Full_View!$L:$L,MATCH($Z$46&"|"&ROWS($A$97:A106),_Assessment_Full_View!$Q:$Q,0)),"") -> Verify / Verify | K106: =IFERROR(INDEX(_Assessment_Full_View!$O:$O,MATCH($Z$46&"|"&ROWS($A$97:A106),_Assessment_Full_View!$Q:$Q,0)),"") -> Verify | N106: =IFERROR(INDEX(_Assessment_Full_View!$P:$P,MATCH($Z$46&"|"&ROWS($A$97:A106),_Assessment_Full_View!$Q:$Q,0)),"") -> Basement TR; verify rated walls/open-to-deck conditions, door/security, floor finish, ladder rack/cable tray, future rack clearance, wall backing, and pathway entries.
A107: =IFERROR(INDEX(_Assessment_Full_View!$E:$E,MATCH($Z$46&"|"&ROWS($A$97:A107),_Assessment_Full_View!$Q:$Q,0)),"") -> 2. ROOM READINESS | C107: =IFERROR(INDEX(_Assessment_Full_View!$G:$G,MATCH($Z$46&"|"&ROWS($A$97:A107),_Assessment_Full_View!$Q:$Q,0))&" / "&INDEX(_Assessment_Full_View!$H:$H,MATCH($Z$46&"|"&ROWS($A$97:A107),_Assessment_Full_View!$Q:$Q,0)),"") -> 124 / Verify | E107: =IFERROR(INDEX(_Assessment_Full_View!$I:$I,MATCH($Z$46&"|"&ROWS($A$97:A107),_Assessment_Full_View!$Q:$Q,0))&" / "&INDEX(_Assessment_Full_View!$J:$J,MATCH($Z$46&"|"&ROWS($A$97:A107),_Assessment_Full_View!$Q:$Q,0)),"") -> Verify / Verify | H107: =IFERROR(INDEX(_Assessment_Full_View!$K:$K,MATCH($Z$46&"|"&ROWS($A$97:A107),_Assessment_Full_View!$Q:$Q,0))&" / "&INDEX(_Assessment_Full_View!$L:$L,MATCH($Z$46&"|"&ROWS($A$97:A107),_Assessment_Full_View!$Q:$Q,0)),"") -> Verify / Verify | K107: =IFERROR(INDEX(_Assessment_Full_View!$O:$O,MATCH($Z$46&"|"&ROWS($A$97:A107),_Assessment_Full_View!$Q:$Q,0)),"") -> Verify | N107: =IFERROR(INDEX(_Assessment_Full_View!$P:$P,MATCH($Z$46&"|"&ROWS($A$97:A107),_Assessment_Full_View!$Q:$Q,0)),"") -> First-level TR; verify rated construction, door hardware, ceiling/deck, rack/future rack clearances, wall backing, and riser/pathway entries.
A108: =IFERROR(INDEX(_Assessment_Full_View!$E:$E,MATCH($Z$46&"|"&ROWS($A$97:A108),_Assessment_Full_View!$Q:$Q,0)),"") -> 2. ROOM READINESS | C108: =IFERROR(INDEX(_Assessment_Full_View!$G:$G,MATCH($Z$46&"|"&ROWS($A$97:A108),_Assessment_Full_View!$Q:$Q,0))&" / "&INDEX(_Assessment_Full_View!$H:$H,MATCH($Z$46&"|"&ROWS($A$97:A108),_Assessment_Full_View!$Q:$Q,0)),"") -> 226 / Verify | E108: =IFERROR(INDEX(_Assessment_Full_View!$I:$I,MATCH($Z$46&"|"&ROWS($A$97:A108),_Assessment_Full_View!$Q:$Q,0))&" / "&INDEX(_Assessment_Full_View!$J:$J,MATCH($Z$46&"|"&ROWS($A$97:A108),_Assessment_Full_View!$Q:$Q,0)),"") -> Verify / Verify | H108: =IFERROR(INDEX(_Assessment_Full_View!$K:$K,MATCH($Z$46&"|"&ROWS($A$97:A108),_Assessment_Full_View!$Q:$Q,0))&" / "&INDEX(_Assessment_Full_View!$L:$L,MATCH($Z$46&"|"&ROWS($A$97:A108),_Assessment_Full_View!$Q:$Q,0)),"") -> Verify / Verify | K108: =IFERROR(INDEX(_Assessment_Full_View!$O:$O,MATCH($Z$46&"|"&ROWS($A$97:A108),_Assessment_Full_View!$Q:$Q,0)),"") -> Verify | N108: =IFERROR(INDEX(_Assessment_Full_View!$P:$P,MATCH($Z$46&"|"&ROWS($A$97:A108),_Assessment_Full_View!$Q:$Q,0)),"") -> Second-level TR; verify rated construction, door hardware, ceiling/deck, rack/future rack clearances, wall backing, and riser/pathway entries.
... A121: =IFERROR(INDEX(_Assessment_Full_View!$E:$E,MATCH($Z$46&"|"&ROWS($A$97:A121),_Assessment_Full_View!$Q:$Q,0)),"") -> 4. HVAC / COOLING | C121: =IFERROR(INDEX(_Assessment_Full_View!$G:$G,MATCH($Z$46&"|"&ROWS($A$97:A121),_Assessment_Full_View!$Q:$Q,0))&" / "&INDEX(_Assessment_Full_View!$H:$H,MATCH($Z$46&"|"&ROWS($A$97:A121),_Assessment_Full_View!$Q:$Q,0)),"") -> 124 / IU-1-01 / CU-1-01 | E121: =IFERROR(INDEX(_Assessment_Full_View!$I:$I,MATCH($Z$46&"|"&ROWS($A$97:A121),_Assessment_Full_View!$Q:$Q,0))&" / "&INDEX(_Assessment_Full_View!$J:$J,MATCH($Z$46&"|"&ROWS($A$97:A121),_Assessment_Full_View!$Q:$Q,0)),"") -> Verify / Verify | H121: =IFERROR(INDEX(_Assessment_Full_View!$K:$K,MATCH($Z$46&"|"&ROWS($A$97:A121),_Assessment_Full_View!$Q:$Q,0))&" / "&INDEX(_Assessment_Full_View!$L:$L,MATCH($Z$46&"|"&ROWS($A$97:A121),_Assessment_Full_View!$Q:$Q,0)),"") -> Verify / Verify | K121: =IFERROR(INDEX(_Assessment_Full_View!$O:$O,MATCH($Z$46&"|"&ROWS($A$97:A121),_Assessment_Full_View!$Q:$Q,0)),"") -> Verify | N121: =IFERROR(INDEX(_Assessment_Full_View!$P:$P,MATCH($Z$46&"|"&ROWS($A$97:A121),_Assessment_Full_View!$Q:$Q,0)),"") -> Mechanical/electrical plans identify IU-1-01/CU-1-01 for first-level TR. Confirm 24/7 operation, emergency/standby source and high-temp alarm.

Sheet COMMAND CENTERS
A1: BEDFORD VA EHRM — CAMPUS COMMAND STATUS | S1: Last refresh | T1: =NOW() -> 46220.364 | Z1: SelectedIndex | AA1: SelectedSheet | AB1: SelectedBuilding
B2: =IF($B$14>=0.9,"MISSION STATUS: OPERATIONAL ",IF($B$14>=0.75,"MISSION STATUS: WATCH ",IF($B$14>=0.5,"MISSION STATUS: AT RISK ","MISSION STATUS: CRITICAL ")))&REPT("█",ROUND($B$14*20,0))&REPT("░",20-ROUND($B$14*20,0))&" "&TEXT($B$14,"0%") -> MISSION STATUS: AT RISK ██████████░░░░░░░░░░ 51% | Z2: =IFERROR(MATCH($C$17,PMIS_Data!$A$3:$A$32,0),1) -> 22 | AA2: =IFERROR(INDEX(PMIS_Data!$B$3:$B$32,$Z$2),"") -> B61_Assessment | AB2: =$C$17&"" -> 61
A3: SELECTED BUILDING SOURCE DETAIL — ASSESSMENT SHEETS
A4: =HYPERLINK("#'B01_Assessment'!A1","B01"&CHAR(10)&TEXT(IFERROR(INDEX(PMIS_Data!$E:$E,MATCH("01",PMIS_Data!$A:$A,0)),0),"0%")&" "&REPT("█",ROUND(IFERROR(INDEX(PMIS_Data!$E:$E,MATCH("01",PMIS_Data!$A:$A,0)),0)*10,0))&REPT("░",10-ROUND(IFERROR(INDEX(PMIS_Data!$E:$E,MATCH("01",PMIS_Data!$A:$A,0)),0)*10,0))&CHAR(10)&"⚠ "&IFERROR(INDEX(PMIS_Data!$H:$H,MATCH("01",PMIS_Data!$A:$A,0)),"-")&" ❓ "&IFERROR(INDEX(PMIS_Data!$I:$I,MATCH("01",PMIS_Data!$A:$A,0)),"-")&CHAR(10)&" ") -> B01 50% █████░░░░░ ⚠ 0 ❓ 0 | E4: =HYPERLINK("#'B02_Assessment'!A1","B02"&CHAR(10)&TEXT(IFERROR(INDEX(PMIS_Data!$E:$E,MATCH("02",PMIS_Data!$A:$A,0)),0),"0%")&" "&REPT("█",ROUND(IFERROR(INDEX(PMIS_Data!$E:$E,MATCH("02",PMIS_Data!$A:$A,0)),0)*10,0))&REPT("░",10-ROUND(IFERROR(INDEX(PMIS_Data!$E:$E,MATCH("02",PMIS_Data!$A:$A,0)),0)*10,0))&CHAR(10)&"⚠ "&IFERROR(INDEX(PMIS_Data!$H:$H,MATCH("02",PMIS_Data!$A:$A,0)),"-")&" ❓ "&IFERROR(INDEX(PMIS_Data!$I:$I,MATCH("02",PMIS_Data!$A:$A,0)),"-")&CHAR(10)&" ") -> B02 50% █████░░░░░ ⚠ 0 ❓ 0 | I4: =HYPERLINK("#'B03_Assessment'!A1","B03"&CHAR(10)&TEXT(IFERROR(INDEX(PMIS_Data!$E:$E,MATCH("03",PMIS_Data!$A:$A,0)),0),"0%")&" "&REPT("█",ROUND(IFERROR(INDEX(PMIS_Data!$E:$E,MATCH("03",PMIS_Data!$A:$A,0)),0)*10,0))&REPT("░",10-ROUND(IFERROR(INDEX(PMIS_Data!$E:$E,MATCH("03",PMIS_Data!$A:$A,0)),0)*10,0))&CHAR(10)&"⚠ "&IFERROR(INDEX(PMIS_Data!$H:$H,MATCH("03",PMIS_Data!$A:$A,0)),"-")&" ❓ "&IFERROR(INDEX(PMIS_Data!$I:$I,MATCH("03",PMIS_Data!$A:$A,0)),"-")&CHAR(10)&" ") -> B03 50% █████░░░░░ ⚠ 0 ❓ 0 | M4: =HYPERLINK("#'B04_Assessment'!A1","B04"&CHAR(10)&TEXT(IFERROR(INDEX(PMIS_Data!$E:$E,MATCH("04",PMIS_Data!$A:$A,0)),0),"0%")&" "&REPT("█",ROUND(IFERROR(INDEX(PMIS_Data!$E:$E,MATCH("04",PMIS_Data!$A:$A,0)),0)*10,0))&REPT("░",10-ROUND(IFERROR(INDEX(PMIS_Data!$E:$E,MATCH("04",PMIS_Data!$A:$A,0)),0)*10,0))&CHAR(10)&"⚠ "&IFERROR(INDEX(PMIS_Data!$H:$H,MATCH("04",PMIS_Data!$A:$A,0)),"-")&" ❓ "&IFERROR(INDEX(PMIS_Data!$I:$I,MATCH("04",PMIS_Data!$A:$A,0)),"-")&CHAR(10)&" ") -> B04 50% █████░░░░░ ⚠ 0 ❓ 0
A5: =HYPERLINK("#'B05_Assessment'!A1","B05"&CHAR(10)&TEXT(IFERROR(INDEX(PMIS_Data!$E:$E,MATCH("05",PMIS_Data!$A:$A,0)),0),"0%")&" "&REPT("█",ROUND(IFERROR(INDEX(PMIS_Data!$E:$E,MATCH("05",PMIS_Data!$A:$A,0)),0)*10,0))&REPT("░",10-ROUND(IFERROR(INDEX(PMIS_Data!$E:$E,MATCH("05",PMIS_Data!$A:$A,0)),0)*10,0))&CHAR(10)&"⚠ "&IFERROR(INDEX(PMIS_Data!$H:$H,MATCH("05",PMIS_Data!$A:$A,0)),"-")&" ❓ "&IFERROR(INDEX(PMIS_Data!$I:$I,MATCH("05",PMIS_Data!$A:$A,0)),"-")&CHAR(10)&" ") -> B05 55% ██████░░░░ ⚠ 0 ❓ 0 | E5: =HYPERLINK("#'B06_Assessment'!A1","B06"&CHAR(10)&TEXT(IFERROR(INDEX(PMIS_Data!$E:$E,MATCH("06",PMIS_Data!$A:$A,0)),0),"0%")&" "&REPT("█",ROUND(IFERROR(INDEX(PMIS_Data!$E:$E,MATCH("06",PMIS_Data!$A:$A,0)),0)*10,0))&REPT("░",10-ROUND(IFERROR(INDEX(PMIS_Data!$E:$E,MATCH("06",PMIS_Data!$A:$A,0)),0)*10,0))&CHAR(10)&"⚠ "&IFERROR(INDEX(PMIS_Data!$H:$H,MATCH("06",PMIS_Data!$A:$A,0)),"-")&" ❓ "&IFERROR(INDEX(PMIS_Data!$I:$I,MATCH("06",PMIS_Data!$A:$A,0)),"-")&CHAR(10)&" ") -> B06 50% █████░░░░░ ⚠ 0 ❓ 0 | I5: =HYPERLINK("#'B07_Assessment'!A1","B07"&CHAR(10)&TEXT(IFERROR(INDEX(PMIS_Data!$E:$E,MATCH("07",PMIS_Data!$A:$A,0)),0),"0%")&" "&REPT("█",ROUND(IFERROR(INDEX(PMIS_Data!$E:$E,MATCH("07",PMIS_Data!$A:$A,0)),0)*10,0))&REPT("░",10-ROUND(IFERROR(INDEX(PMIS_Data!$E:$E,MATCH("07",PMIS_Data!$A:$A,0)),0)*10,0))&CHAR(10)&"⚠ "&IFERROR(INDEX(PMIS_Data!$H:$H,MATCH("07",PMIS_Data!$A:$A,0)),"-")&" ❓ "&IFERROR(INDEX(PMIS_Data!$I:$I,MATCH("07",PMIS_Data!$A:$A,0)),"-")&CHAR(10)&" ") -> B07 50% █████░░░░░ ⚠ 0 ❓ 0 | M5: =HYPERLINK("#'B08_Assessment'!A1","B08"&CHAR(10)&TEXT(IFERROR(INDEX(PMIS_Data!$E:$E,MATCH("08",PMIS_Data!$A:$A,0)),0),"0%")&" "&REPT("█",ROUND(IFERROR(INDEX(PMIS_Data!$E:$E,MATCH("08",PMIS_Data!$A:$A,0)),0)*10,0))&REPT("░",10-ROUND(IFERROR(INDEX(PMIS_Data!$E:$E,MATCH("08",PMIS_Data!$A:$A,0)),0)*10,0))&CHAR(10)&"⚠ "&IFERROR(INDEX(PMIS_Data!$H:$H,MATCH("08",PMIS_Data!$A:$A,0)),"-")&" ❓ "&IFERROR(INDEX(PMIS_Data!$I:$I,MATCH("08",PMIS_Data!$A:$A,0)),"-")&CHAR(10)&" ") -> B08 50% █████░░░░░ ⚠ 0 ❓ 0
A6: =HYPERLINK("#'B09_Assessment'!A1","B09"&CHAR(10)&TEXT(IFERROR(INDEX(PMIS_Data!$E:$E,MATCH("09",PMIS_Data!$A:$A,0)),0),"0%")&" "&REPT("█",ROUND(IFERROR(INDEX(PMIS_Data!$E:$E,MATCH("09",PMIS_Data!$A:$A,0)),0)*10,0))&REPT("░",10-ROUND(IFERROR(INDEX(PMIS_Data!$E:$E,MATCH("09",PMIS_Data!$A:$A,0)),0)*10,0))&CHAR(10)&"⚠ "&IFERROR(INDEX(PMIS_Data!$H:$H,MATCH("09",PMIS_Data!$A:$A,0)),"-")&" ❓ "&IFERROR(INDEX(PMIS_Data!$I:$I,MATCH("09",PMIS_Data!$A:$A,0)),"-")&CHAR(10)&" ") -> B09 50% █████░░░░░ ⚠ 0 ❓ 0 | E6: =HYPERLINK("#'B10_Assessment'!A1","B10"&CHAR(10)&TEXT(IFERROR(INDEX(PMIS_Data!$E:$E,MATCH("10",PMIS_Data!$A:$A,0)),0),"0%")&" "&REPT("█",ROUND(IFERROR(INDEX(PMIS_Data!$E:$E,MATCH("10",PMIS_Data!$A:$A,0)),0)*10,0))&REPT("░",10-ROUND(IFERROR(INDEX(PMIS_Data!$E:$E,MATCH("10",PMIS_Data!$A:$A,0)),0)*10,0))&CHAR(10)&"⚠ "&IFERROR(INDEX(PMIS_Data!$H:$H,MATCH("10",PMIS_Data!$A:$A,0)),"-")&" ❓ "&IFERROR(INDEX(PMIS_Data!$I:$I,MATCH("10",PMIS_Data!$A:$A,0)),"-")&CHAR(10)&" ") -> B10 50% █████░░░░░ ⚠ 0 ❓ 0 | I6: =HYPERLINK("#'B12_Assessment'!A1","B12"&CHAR(10)&TEXT(IFERROR(INDEX(PMIS_Data!$E:$E,MATCH("12",PMIS_Data!$A:$A,0)),0),"0%")&" "&REPT("█",ROUND(IFERROR(INDEX(PMIS_Data!$E:$E,MATCH("12",PMIS_Data!$A:$A,0)),0)*10,0))&REPT("░",10-ROUND(IFERROR(INDEX(PMIS_Data!$E:$E,MATCH("12",PMIS_Data!$A:$A,0)),0)*10,0))&CHAR(10)&"⚠ "&IFERROR(INDEX(PMIS_Data!$H:$H,MATCH("12",PMIS_Data!$A:$A,0)),"-")&" ❓ "&IFERROR(INDEX(PMIS_Data!$I:$I,MATCH("12",PMIS_Data!$A:$A,0)),"-")&CHAR(10)&" ") -> B12 60% ██████░░░░ ⚠ 0 ❓ 0 | M6: =HYPERLINK("#'B13_Assessment'!A1","B13"&CHAR(10)&TEXT(IFERROR(INDEX(PMIS_Data!$E:$E,MATCH("13",PMIS_Data!$A:$A,0)),0),"0%")&" "&REPT("█",ROUND(IFERROR(INDEX(PMIS_Data!$E:$E,MATCH("13",PMIS_Data!$A:$A,0)),0)*10,0))&REPT("░",10-ROUND(IFERROR(INDEX(PMIS_Data!$E:$E,MATCH("13",PMIS_Data!$A:$A,0)),0)*10,0))&CHAR(10)&"⚠ "&IFERROR(INDEX(PMIS_Data!$H:$H,MATCH("13",PMIS_Data!$A:$A,0)),"-")&" ❓ "&IFERROR(INDEX(PMIS_Data!$I:$I,MATCH("13",PMIS_Data!$A:$A,0)),"-")&CHAR(10)&" ") -> B13 50% █████░░░░░ ⚠ 0 ❓ 0
A7: =HYPERLINK("#'B14_Assessment'!A1","B14"&CHAR(10)&TEXT(IFERROR(INDEX(PMIS_Data!$E:$E,MATCH("14",PMIS_Data!$A:$A,0)),0),"0%")&" "&REPT("█",ROUND(IFERROR(INDEX(PMIS_Data!$E:$E,MATCH("14",PMIS_Data!$A:$A,0)),0)*10,0))&REPT("░",10-ROUND(IFERROR(INDEX(PMIS_Data!$E:$E,MATCH("14",PMIS_Data!$A:$A,0)),0)*10,0))&CHAR(10)&"⚠ "&IFERROR(INDEX(PMIS_Data!$H:$H,MATCH("14",PMIS_Data!$A:$A,0)),"-")&" ❓ "&IFERROR(INDEX(PMIS_Data!$I:$I,MATCH("14",PMIS_Data!$A:$A,0)),"-")&CHAR(10)&" ") -> B14 50% █████░░░░░ ⚠ 0 ❓ 0 | E7: =HYPERLINK("#'B15_Assessment'!A1","B15"&CHAR(10)&TEXT(IFERROR(INDEX(PMIS_Data!$E:$E,MATCH("15",PMIS_Data!$A:$A,0)),0),"0%")&" "&REPT("█",ROUND(IFERROR(INDEX(PMIS_Data!$E:$E,MATCH("15",PMIS_Data!$A:$A,0)),0)*10,0))&REPT("░",10-ROUND(IFERROR(INDEX(PMIS_Data!$E:$E,MATCH("15",PMIS_Data!$A:$A,0)),0)*10,0))&CHAR(10)&"⚠ "&IFERROR(INDEX(PMIS_Data!$H:$H,MATCH("15",PMIS_Data!$A:$A,0)),"-")&" ❓ "&IFERROR(INDEX(PMIS_Data!$I:$I,MATCH("15",PMIS_Data!$A:$A,0)),"-")&CHAR(10)&" ") -> B15 50% █████░░░░░ ⚠ 0 ❓ 0 | I7: =HYPERLINK("#'B16_Assessment'!A1","B16"&CHAR(10)&TEXT(IFERROR(INDEX(PMIS_Data!$E:$E,MATCH("16",PMIS_Data!$A:$A,0)),0),"0%")&" "&REPT("█",ROUND(IFERROR(INDEX(PMIS_Data!$E:$E,MATCH("16",PMIS_Data!$A:$A,0)),0)*10,0))&REPT("░",10-ROUND(IFERROR(INDEX(PMIS_Data!$E:$E,MATCH("16",PMIS_Data!$A:$A,0)),0)*10,0))&CHAR(10)&"⚠ "&IFERROR(INDEX(PMIS_Data!$H:$H,MATCH("16",PMIS_Data!$A:$A,0)),"-")&" ❓ "&IFERROR(INDEX(PMIS_Data!$I:$I,MATCH("16",PMIS_Data!$A:$A,0)),"-")&CHAR(10)&" ") -> B16 50% █████░░░░░ ⚠ 0 ❓ 0 | M7: =HYPERLINK("#'B17_Assessment'!A1","B17"&CHAR(10)&TEXT(IFERROR(INDEX(PMIS_Data!$E:$E,MATCH("17",PMIS_Data!$A:$A,0)),0),"0%")&" "&REPT("█",ROUND(IFERROR(INDEX(PMIS_Data!$E:$E,MATCH("17",PMIS_Data!$A:$A,0)),0)*10,0))&REPT("░",10-ROUND(IFERROR(INDEX(PMIS_Data!$E:$E,MATCH("17",PMIS_Data!$A:$A,0)),0)*10,0))&CHAR(10)&"⚠ "&IFERROR(INDEX(PMIS_Data!$H:$H,MATCH("17",PMIS_Data!$A:$A,0)),"-")&" ❓ "&IFERROR(INDEX(PMIS_Data!$I:$I,MATCH("17",PMIS_Data!$A:$A,0)),"-")&CHAR(10)&" ") -> B17 50% █████░░░░░ ⚠ 0 ❓ 0
A8: =HYPERLINK("#'B18_Assessment'!A1","B18"&CHAR(10)&TEXT(IFERROR(INDEX(PMIS_Data!$E:$E,MATCH("18",PMIS_Data!$A:$A,0)),0),"0%")&" "&REPT("█",ROUND(IFERROR(INDEX(PMIS_Data!$E:$E,MATCH("18",PMIS_Data!$A:$A,0)),0)*10,0))&REPT("░",10-ROUND(IFERROR(INDEX(PMIS_Data!$E:$E,MATCH("18",PMIS_Data!$A:$A,0)),0)*10,0))&CHAR(10)&"⚠ "&IFERROR(INDEX(PMIS_Data!$H:$H,MATCH("18",PMIS_Data!$A:$A,0)),"-")&" ❓ "&IFERROR(INDEX(PMIS_Data!$I:$I,MATCH("18",PMIS_Data!$A:$A,0)),"-")&CHAR(10)&" ") -> B18 50% █████░░░░░ ⚠ 0 ❓ 0 | E8: =HYPERLINK("#'B20_Assessment'!A1","B20"&CHAR(10)&TEXT(IFERROR(INDEX(PMIS_Data!$E:$E,MATCH("20",PMIS_Data!$A:$A,0)),0),"0%")&" "&REPT("█",ROUND(IFERROR(INDEX(PMIS_Data!$E:$E,MATCH("20",PMIS_Data!$A:$A,0)),0)*10,0))&REPT("░",10-ROUND(IFERROR(INDEX(PMIS_Data!$E:$E,MATCH("20",PMIS_Data!$A:$A,0)),0)*10,0))&CHAR(10)&"⚠ "&IFERROR(INDEX(PMIS_Data!$H:$H,MATCH("20",PMIS_Data!$A:$A,0)),"-")&" ❓ "&IFERROR(INDEX(PMIS_Data!$I:$I,MATCH("20",PMIS_Data!$A:$A,0)),"-")&CHAR(10)&" ") -> B20 50% █████░░░░░ ⚠ 0 ❓ 0 | I8: =HYPERLINK("#'B21_Assessment'!A1","B21"&CHAR(10)&TEXT(IFERROR(INDEX(PMIS_Data!$E:$E,MATCH("21",PMIS_Data!$A:$A,0)),0),"0%")&" "&REPT("█",ROUND(IFERROR(INDEX(PMIS_Data!$E:$E,MATCH("21",PMIS_Data!$A:$A,0)),0)*10,0))&REPT("░",10-ROUND(IFERROR(INDEX(PMIS_Data!$E:$E,MATCH("21",PMIS_Data!$A:$A,0)),0)*10,0))&CHAR(10)&"⚠ "&IFERROR(INDEX(PMIS_Data!$H:$H,MATCH("21",PMIS_Data!$A:$A,0)),"-")&" ❓ "&IFERROR(INDEX(PMIS_Data!$I:$I,MATCH("21",PMIS_Data!$A:$A,0)),"-")&CHAR(10)&" ") -> B21 50% █████░░░░░ ⚠ 0 ❓ 0 | M8: =HYPERLINK("#'B22_Assessment'!A1","B22"&CHAR(10)&TEXT(IFERROR(INDEX(PMIS_Data!$E:$E,MATCH("22",PMIS_Data!$A:$A,0)),0),"0%")&" "&REPT("█",ROUND(IFERROR(INDEX(PMIS_Data!$E:$E,MATCH("22",PMIS_Data!$A:$A,0)),0)*10,0))&REPT("░",10-ROUND(IFERROR(INDEX(PMIS_Data!$E:$E,MATCH("22",PMIS_Data!$A:$A,0)),0)*10,0))&CHAR(10)&"⚠ "&IFERROR(INDEX(PMIS_Data!$H:$H,MATCH("22",PMIS_Data!$A:$A,0)),"-")&" ❓ "&IFERROR(INDEX(PMIS_Data!$I:$I,MATCH("22",PMIS_Data!$A:$A,0)),"-")&CHAR(10)&" ") -> B22 50% █████░░░░░ ⚠ 0 ❓ 0
A9: =HYPERLINK("#'B33_Assessment'!A1","B33"&CHAR(10)&TEXT(IFERROR(INDEX(PMIS_Data!$E:$E,MATCH("33",PMIS_Data!$A:$A,0)),0),"0%")&" "&REPT("█",ROUND(IFERROR(INDEX(PMIS_Data!$E:$E,MATCH("33",PMIS_Data!$A:$A,0)),0)*10,0))&REPT("░",10-ROUND(IFERROR(INDEX(PMIS_Data!$E:$E,MATCH("33",PMIS_Data!$A:$A,0)),0)*10,0))&CHAR(10)&"⚠ "&IFERROR(INDEX(PMIS_Data!$H:$H,MATCH("33",PMIS_Data!$A:$A,0)),"-")&" ❓ "&IFERROR(INDEX(PMIS_Data!$I:$I,MATCH("33",PMIS_Data!$A:$A,0)),"-")&CHAR(10)&" ") -> B33 50% █████░░░░░ ⚠ 0 ❓ 0 | E9: =HYPERLINK("#'B61_Assessment'!A1","B61"&CHAR(10)&TEXT(IFERROR(INDEX(PMIS_Data!$E:$E,MATCH("61",PMIS_Data!$A:$A,0)),0),"0%")&" "&REPT("█",ROUND(IFERROR(INDEX(PMIS_Data!$E:$E,MATCH("61",PMIS_Data!$A:$A,0)),0)*10,0))&REPT("░",10-ROUND(IFERROR(INDEX(PMIS_Data!$E:$E,MATCH("61",PMIS_Data!$A:$A,0)),0)*10,0))&CHAR(10)&"⚠ "&IFERROR(INDEX(PMIS_Data!$H:$H,MATCH("61",PMIS_Data!$A:$A,0)),"-")&" ❓ "&IFERROR(INDEX(PMIS_Data!$I:$I,MATCH("61",PMIS_Data!$A:$A,0)),"-")&CHAR(10)&"PILOT ") -> B61 55% ██████░░░░ ⚠ 0 ❓ 0 PILOT | I9: =HYPERLINK("#'B62_TR_Assessment'!A1","B62"&CHAR(10)&TEXT(IFERROR(INDEX(PMIS_Data!$E:$E,MATCH("62",PMIS_Data!$A:$A,0)),0),"0%")&" "&REPT("█",ROUND(IFERROR(INDEX(PMIS_Data!$E:$E,MATCH("62",PMIS_Data!$A:$A,0)),0)*10,0))&REPT("░",10-ROUND(IFERROR(INDEX(PMIS_Data!$E:$E,MATCH("62",PMIS_Data!$A:$A,0)),0)*10,0))&CHAR(10)&"⚠ "&IFERROR(INDEX(PMIS_Data!$H:$H,MATCH("62",PMIS_Data!$A:$A,0)),"-")&" ❓ "&IFERROR(INDEX(PMIS_Data!$I:$I,MATCH("62",PMIS_Data!$A:$A,0)),"-")&CHAR(10)&" ") -> B62 50% █████░░░░░ ⚠ 0 ❓ 0 | M9: =HYPERLINK("#'B70_TR_Assessment'!A1","B70"&CHAR(10)&TEXT(IFERROR(INDEX(PMIS_Data!$E:$E,MATCH("70",PMIS_Data!$A:$A,0)),0),"0%")&" "&REPT("█",ROUND(IFERROR(INDEX(PMIS_Data!$E:$E,MATCH("70",PMIS_Data!$A:$A,0)),0)*10,0))&REPT("░",10-ROUND(IFERROR(INDEX(PMIS_Data!$E:$E,MATCH("70",PMIS_Data!$A:$A,0)),0)*10,0))&CHAR(10)&"⚠ "&IFERROR(INDEX(PMIS_Data!$H:$H,MATCH("70",PMIS_Data!$A:$A,0)),"-")&" ❓ "&IFERROR(INDEX(PMIS_Data!$I:$I,MATCH("70",PMIS_Data!$A:$A,0)),"-")&CHAR(10)&" ") -> B70 50% █████░░░░░ ⚠ 0 ❓ 0
A10: =HYPERLINK("#'B78_Assessment'!A1","B78"&CHAR(10)&TEXT(IFERROR(INDEX(PMIS_Data!$E:$E,MATCH("78",PMIS_Data!$A:$A,0)),0),"0%")&" "&REPT("█",ROUND(IFERROR(INDEX(PMIS_Data!$E:$E,MATCH("78",PMIS_Data!$A:$A,0)),0)*10,0))&REPT("░",10-ROUND(IFERROR(INDEX(PMIS_Data!$E:$E,MATCH("78",PMIS_Data!$A:$A,0)),0)*10,0))&CHAR(10)&"⚠ "&IFERROR(INDEX(PMIS_Data!$H:$H,MATCH("78",PMIS_Data!$A:$A,0)),"-")&" ❓ "&IFERROR(INDEX(PMIS_Data!$I:$I,MATCH("78",PMIS_Data!$A:$A,0)),"-")&CHAR(10)&" ") -> B78 50% █████░░░░░ ⚠ 0 ❓ 0 | E10: =HYPERLINK("#'B80_Assessment'!A1","B80"&CHAR(10)&TEXT(IFERROR(INDEX(PMIS_Data!$E:$E,MATCH("80",PMIS_Data!$A:$A,0)),0),"0%")&" "&REPT("█",ROUND(IFERROR(INDEX(PMIS_Data!$E:$E,MATCH("80",PMIS_Data!$A:$A,0)),0)*10,0))&REPT("░",10-ROUND(IFERROR(INDEX(PMIS_Data!$E:$E,MATCH("80",PMIS_Data!$A:$A,0)),0)*10,0))&CHAR(10)&"⚠ "&IFERROR(INDEX(PMIS_Data!$H:$H,MATCH("80",PMIS_Data!$A:$A,0)),"-")&" ❓ "&IFERROR(INDEX(PMIS_Data!$I:$I,MATCH("80",PMIS_Data!$A:$A,0)),"-")&CHAR(10)&" ") -> B80 50% █████░░░░░ ⚠ 0 ❓ 0 | I10: =HYPERLINK("#'B82_Assessment'!A1","B82"&CHAR(10)&TEXT(IFERROR(INDEX(PMIS_Data!$E:$E,MATCH("82",PMIS_Data!$A:$A,0)),0),"0%")&" "&REPT("█",ROUND(IFERROR(INDEX(PMIS_Data!$E:$E,MATCH("82",PMIS_Data!$A:$A,0)),0)*10,0))&REPT("░",10-ROUND(IFERROR(INDEX(PMIS_Data!$E:$E,MATCH("82",PMIS_Data!$A:$A,0)),0)*10,0))&CHAR(10)&"⚠ "&IFERROR(INDEX(PMIS_Data!$H:$H,MATCH("82",PMIS_Data!$A:$A,0)),"-")&" ❓ "&IFERROR(INDEX(PMIS_Data!$I:$I,MATCH("82",PMIS_Data!$A:$A,0)),"-")&CHAR(10)&" ") -> B82 50% █████░░░░░ ⚠ 0 ❓ 0 | M10: =HYPERLINK("#'BCH_Assessment'!A1","BCH"&CHAR(10)&TEXT(IFERROR(INDEX(PMIS_Data!$E:$E,MATCH("BCH",PMIS_Data!$A:$A,0)),0),"0%")&" "&REPT("█",ROUND(IFERROR(INDEX(PMIS_Data!$E:$E,MATCH("BCH",PMIS_Data!$A:$A,0)),0)*10,0))&REPT("░",10-ROUND(IFERROR(INDEX(PMIS_Data!$E:$E,MATCH("BCH",PMIS_Data!$A:$A,0)),0)*10,0))&CHAR(10)&"⚠ "&IFERROR(INDEX(PMIS_Data!$H:$H,MATCH("BCH",PMIS_Data!$A:$A,0)),"-")&" ❓ "&IFERROR(INDEX(PMIS_Data!$I:$I,MATCH("BCH",PMIS_Data!$A:$A,0)),"-")&CHAR(10)&" ") -> BCH 50% █████░░░░░ ⚠ 0 ❓ 0
A11: =HYPERLINK("#'MCR_Assessment'!A1","MCR"&CHAR(10)&TEXT(IFERROR(INDEX(PMIS_Data!$E:$E,MATCH("MCR",PMIS_Data!$A:$A,0)),0),"0%")&" "&REPT("█",ROUND(IFERROR(INDEX(PMIS_Data!$E:$E,MATCH("MCR",PMIS_Data!$A:$A,0)),0)*10,0))&REPT("░",10-ROUND(IFERROR(INDEX(PMIS_Data!$E:$E,MATCH("MCR",PMIS_Data!$A:$A,0)),0)*10,0))&CHAR(10)&"⚠ "&IFERROR(INDEX(PMIS_Data!$H:$H,MATCH("MCR",PMIS_Data!$A:$A,0)),"-")&" ❓ "&IFERROR(INDEX(PMIS_Data!$I:$I,MATCH("MCR",PMIS_Data!$A:$A,0)),"-")&CHAR(10)&" ") -> MCR 50% █████░░░░░ ⚠ 0 ❓ 0 | E11: =HYPERLINK("#'SITE_Assesment'!A1","SITE"&CHAR(10)&TEXT(IFERROR(INDEX(PMIS_Data!$E:$E,MATCH("SITE",PMIS_Data!$A:$A,0)),0),"0%")&" "&REPT("█",ROUND(IFERROR(INDEX(PMIS_Data!$E:$E,MATCH("SITE",PMIS_Data!$A:$A,0)),0)*10,0))&REPT("░",10-ROUND(IFERROR(INDEX(PMIS_Data!$E:$E,MATCH("SITE",PMIS_Data!$A:$A,0)),0)*10,0))&CHAR(10)&"⚠ "&IFERROR(INDEX(PMIS_Data!$H:$H,MATCH("SITE",PMIS_Data!$A:$A,0)),"-")&" ❓ "&IFERROR(INDEX(PMIS_Data!$I:$I,MATCH("SITE",PMIS_Data!$A:$A,0)),"-")&CHAR(10)&" ") -> SITE 50% █████░░░░░ ⚠ 0 ❓ 0 | I11: =HYPERLINK("#'SPEC_Assessment'!A1","SPEC"&CHAR(10)&TEXT(IFERROR(INDEX(PMIS_Data!$E:$E,MATCH("SPEC",PMIS_Data!$A:$A,0)),0),"0%")&" "&REPT("█",ROUND(IFERROR(INDEX(PMIS_Data!$E:$E,MATCH("SPEC",PMIS_Data!$A:$A,0)),0)*10,0))&REPT("░",10-ROUND(IFERROR(INDEX(PMIS_Data!$E:$E,MATCH("SPEC",PMIS_Data!$A:$A,0)),0)*10,0))&CHAR(10)&"⚠ "&IFERROR(INDEX(PMIS_Data!$H:$H,MATCH("SPEC",PMIS_Data!$A:$A,0)),"-")&" ❓ "&IFERROR(INDEX(PMIS_Data!$I:$I,MATCH("SPEC",PMIS_Data!$A:$A,0)),"-")&CHAR(10)&" ") -> SPEC 0% ░░░░░░░░░░ ⚠ - ❓ - | R11: QA | S11: =HYPERLINK("#'Data_Health'!A1","Data Health") -> Data Health
R12: Guide | S12: =HYPERLINK("#'README_ARCHITECTURE'!A1","Architecture") -> Architecture
B13: CAMPUS HEALTH | D13: BUILDINGS ASSESSED | F13: OPEN RISKS | H13: OPEN QUESTIONS | J13: OPEN PHOTOS | L13: ACTIVE SHUTDOWNS | N13: NOT READY | R13: Focus | S13: =HYPERLINK("#'Today''s_Focus'!A1","Today's Focus") -> Today's Focus
B14: =IFERROR(AVERAGE(PMIS_Data!$E$3:$E$32),0) -> 0.50666667 | D14: =COUNTA(PMIS_Data!$A$3:$A$32) -> 30 | F14: =SUM(PMIS_Data!$H$3:$H$32) -> 0 | H14: =SUM(PMIS_Data!$I$3:$I$32) -> 0 | J14: =SUM(PMIS_Data!$J$3:$J$32) -> 0 | L14: =SUM(PMIS_Data!$X$3:$X$32) -> 0 | N14: =COUNTIF(PMIS_Data!$F$3:$F$32,"No") -> 29
B16: ACTIVE MISSION | J16: PROGRESS OVERVIEW
B17: MISSION TARGET | C17: 61 | F17: READINESS SIGNAL
F18: BAR | G18: =REPT("█",ROUND($F$19*12,0))&REPT("░",12-ROUND($F$19*12,0)) -> ███████░░░░░ | J18: ="ROOMS"&CHAR(10)&IFERROR(INDEX(PMIS_Data!$G$3:$G$100,$Z$2),0) -> ROOMS 29 | L18: ="FIRE"&CHAR(10)&IF(IFERROR(INDEX(PMIS_Data!$N$3:$N$100,$Z$2),"")="Pass","✓ PASS",IFERROR(INDEX(PMIS_Data!$N$3:$N$100,$Z$2),"REVIEW")) -> FIRE Not Started
B19: MISSION STATUS | C19: =IF($F$19>=0.9,"OPERATIONAL",IF($F$19>=0.75,"WATCH",IF($F$19>=0.5,"AT RISK","CRITICAL"))) -> AT RISK | F19: =IFERROR(INDEX(PMIS_Data!$E$3:$E$94,$Z$2),0) -> 0.55
J21: ="HVAC"&CHAR(10)&IF(IFERROR(INDEX(PMIS_Data!$K$3:$K$100,$Z$2),"")="Pass","✓ PASS",IFERROR(INDEX(PMIS_Data!$K$3:$K$100,$Z$2),"REVIEW")) -> HVAC Not Started | L21: ="ELECTRICAL"&CHAR(10)&IF(IFERROR(INDEX(PMIS_Data!$L$3:$L$100,$Z$2),"")="Pass","✓ PASS",IFERROR(INDEX(PMIS_Data!$L$3:$L$100,$Z$2),"REVIEW")) -> ELECTRICAL Not Started
B22: OVERALL STATUS | C22: =IFERROR(INDEX(PMIS_Data!$C$3:$C$94,$Z$2),"") -> PILOT PHASE
B24: CONSTRUCTION READY | C24: =IFERROR(INDEX(PMIS_Data!$F$3:$F$94,$Z$2),"") -> YES | J24: ="TELECOM"&CHAR(10)&IF(IFERROR(INDEX(PMIS_Data!$M$3:$M$100,$Z$2),"")="Pass","✓ PASS",IFERROR(INDEX(PMIS_Data!$M$3:$M$100,$Z$2),"REVIEW")) -> TELECOM Not Started | L24: ="SECURITY"&CHAR(10)&IF(IFERROR(INDEX(PMIS_Data!$P$3:$P$100,$Z$2),"")="Pass","✓ PASS",IFERROR(INDEX(PMIS_Data!$P$3:$P$100,$Z$2),"REVIEW")) -> SECURITY Not Started
B30: RISK SUMMARY | F30: OPEN QUESTIONS | J30: DOCUMENTS / PHOTOS | N30: SHUTDOWNS
B32: Open Risks | D32: =IFERROR(INDEX(PMIS_Data!$H$3:$H$94,$Z$2),0) -> 0 | F32: Selected Open | H32: =IFERROR(INDEX(PMIS_Data!$I$3:$I$94,$Z$2),0) -> 0 | J32: Open Photos | L32: =IFERROR(INDEX(PMIS_Data!$J$3:$J$94,$Z$2),0) -> 0 | N32: Selected Active | P32: =IFERROR(INDEX(PMIS_Data!$X$3:$X$94,$Z$2),0) -> 0
B34: Campus Open | D34: =SUM(PMIS_Data!$H$3:$H$32) -> 0 | F34: Campus Open | H34: =SUM(PMIS_Data!$I$3:$I$32) -> 0 | J34: Campus Docs | L34: =COUNTA([4]Doc_Register!$A$5:$A$300) -> 40 | N34: Campus Active | P34: =SUM(PMIS_Data!$X$3:$X$32) -> 0
B36: Selected Rank | D36: =IFERROR(INDEX([4]_V4_ActionQueue!$A$4:$A$33,MATCH($C$17,[4]_V4_ActionQueue!$B$4:$B$33,0)),"") -> 29 | F36: High Priority | H36: =COUNTIFS(#REF!,"High",#REF!,"Open") -> #REF! | J36: Campus Photos | L36: =COUNTA(#REF!) -> 1 | N36: Not Ready | P36: =COUNTIF(PMIS_Data!$F$3:$F$32,"No") -> 29
B41: =HYPERLINK("#'"&$AA$2&"'!A1","Open selected Building Assessment") -> Open selected Building Assessment
A42: Building | B42: Sheet | C42: Status | D42: Readiness | E42: Ready | F42: Rooms | G42: Risks | H42: Questions | I42: Photos | J42: Shutdowns
A43: =$C$17&"" -> 61 | B43: =IFERROR(INDEX(PMIS_Data!$B$3:$B$94,$Z$2),"") -> B61_Assessment | C43: =IFERROR(INDEX(PMIS_Data!$C$3:$C$94,$Z$2),"") -> PILOT PHASE | D43: =IFERROR(INDEX(PMIS_Data!$E$3:$E$94,$Z$2),0) -> 0.55 | E43: =IFERROR(INDEX(PMIS_Data!$F$3:$F$94,$Z$2),"") -> YES | F43: =IFERROR(INDEX(PMIS_Data!$G$3:$G$94,$Z$2),0) -> 29 | G43: =IFERROR(INDEX(PMIS_Data!$H$3:$H$94,$Z$2),0) -> 0 | H43: =IFERROR(INDEX(PMIS_Data!$I$3:$I$94,$Z$2),0) -> 0 | I43: =IFERROR(INDEX(PMIS_Data!$J$3:$J$94,$Z$2),0) -> 0 | J43: =IFERROR(INDEX(PMIS_Data!$X$3:$X$94,$Z$2),0) -> 0 | AA43: Selected_Assessment_Sheet | AB43: =IF($Z$46="Campus","Select a building tile for trade-level notes.",IFERROR(INDEX([4]_Command_Trade_Notes!$B:$B,MATCH($Z$46,[4]_Command_Trade_Notes!$A:$A,0)),"No fire/life safety notes captured.")) -> • Dedicated TR scope includes fire protection drawings. Verify sprinkler modifications, fire alarm devices, clean-agent 2A:10B:C FEC within 75 ft, rated penetrations, and temporary firestopping. • Verify sprinkler/fire alarm modifications, clean-agent FEC location, penetrations, cable tray/riser openings, and final UL firestop systems. • Verify second-level TR sprinkler/fire alarm modifications, clean-agent FEC location, vertical riser penetrations, and firestopping. • Existing demarc/server rooms may remain active; verify protection-in-place, FA/FP continuity, and no unsealed penetrations after cabling work. | AC43: =IF($Z$46="Campus","Select a building tile for trade-level notes.",IFERROR(INDEX([4]_Command_Trade_Notes!$C:$C,MATCH($Z$46,[4]_Command_Trade_Notes!$A:$A,0)),"No HVAC/cooling notes captured.")) -> • Mechanical sheets identify dedicated split-system cooling with BACnet adapter mounted adjacent to unit in telecom room. Confirm capacity, emergency source, condensate, disconnect, controls, and alarms. • Mechanical/electrical plans identify IU-1-01/CU-1-01 for first-level TR. Confirm 24/7 operation, emergency/standby source and high-temp alarm. • Mechanical/electrical plans identify IU-2-01/CU-2-01 for second-level TR. Confirm refrigerant route, condensate route, controls and alarm tie-in. • Existing demarc/server equipment likely has existing cooling dependencies. Verify active equipment heat load, airflow, operational temperatures and whether any existing cooling is modified or protected. | AD43: =IF($Z$46="Campus","Select a building tile for trade-level notes.",IFERROR(INDEX([4]_Command_Trade_Notes!$D:$D,MATCH($Z$46,[4]_Command_Trade_Notes!$A:$A,0)),"No electrical/UPS notes captured.")) -> • Electrical enlarged plans and schedules identify rack receptacles, UPS circuits, PDUs, panelboards, SPD devices and dedicated cooling power for B13H-A. Verify B61-TRB13A/B source, LOTO and labels. • Electrical schedules identify B61-TR124A/B and rack receptacles. Verify apparent room-name mismatch with RM137B rack receptacles in schedules. • Electrical schedules identify B61-TR226A/B, rack receptacles, CU-2-01 and SPD requirements. Verify source circuits and labels. • Existing rack inventory includes APC UPS/PDU and server/demarc equipment. Electrical one-line/schedules list B61-TR137AA/AB and PD-B61-TR137 panels; verify active sources and transition impact. | AE43: =IF($Z$46="Campus","Select a building tile for trade-level notes.",IFERROR(INDEX([4]_Command_Trade_Notes!$E:$E,MATCH($Z$46,[4]_Command_Trade_Notes!$A:$A,0)),"No telecom/fiber notes captured.")) -> • 61T-701: 88 WAO total, 74 active ports, 129 scheduled ports, 142 with 10% allowance. Rack ID TR01-B13H-A-1. Basement cable tray included in 890 ft basement total. • 61T-701: first-level Room 124 / Rack ID TR01-124-1. Schedule data runs across first-level outlets. Include labels, Fiber LIU, Cat6A patch panels, UPS/PDU and VA/OIT acceptance. • 61T-702: 109 WAO total, 126 active ports, 156 scheduled ports, 172 with 10% allowance. Rack ID TR01-226-1. Verify second-level cable tray and riser penetrations. • 61T-402/606/607 inventory existing demarc/server racks and equipment. Protect active systems, coordinate cutover, preserve labels, document equipment remaining in service. | AF43: =IF($Z$46="Campus","Select a building tile for trade-level notes.",IFERROR(INDEX([4]_Command_Trade_Notes!$F:$F,MATCH($Z$46,[4]_Command_Trade_Notes!$A:$A,0)),"No security/PACS/CCTV notes captured.")) -> 0 | AG43: =IF($Z$46="Campus","Select a building tile for risk notes.",IFERROR(INDEX([4]_Command_Trade_Notes!$G:$G,MATCH($Z$46,[4]_Command_Trade_Notes!$A:$A,0)),"No owner risk notes captured.")) -> • High: Existing conditions and active equipment across B13H-A, 124, 226 and 137/137A not field verified — Perform existing conditions survey with photos and active-service inventory before mobilization • High: Hazardous material abatement plans exist for first and second levels — Coordinate IH/abatement review before penetrations, wall/ceiling work, cabling or mechanical/electrical installation • Critical: Existing server/demarc equipment may remain active during cutover — Document active services, service provider circuits, rack inventory, OIT windows, temporary utilities and rollback path • Critical: Dedicated cooling sequence, emergency power, condensate, BACnet and alarms not verified — Confirm IU/CU-0/1/2 power source, condensate, controls, BACnet adapter, thermostat and high-temp alarm • Critical: Panel source, UPS/PDU and rack receptacle coordination could delay energization — Verify B61-TRB13A/B, B61-TR124A/B, B61-TR226A/B, B61-TR137AA/AB, PD panels, SPDs and load measurements • High: Large cable tray scope creates coordination and firestop risk — Verify 1,966 ft cable tray route, supports, seismic bracing, 40% fill, MEP conflicts, sleeves and final firestop assemblies | AH43: =IF($Z$46="Campus","Select a building tile for open questions.",IFERROR(INDEX([4]_Command_Trade_Notes!$H:$H,MATCH($Z$46,[4]_Command_Trade_Notes!$A:$A,0)),"No open questions captured.")) -> • B61-Q1 — Confirm final telecom room list and PMIS mapping: B13H-A, 124, 226 and existing 137/137A demarc/server rooms? [Open] Impact: Room inventory could miss scope • B61-Q2 — What active services and circuits are currently housed in Room 137/137A? [Open] Impact: Potential outage/cutover risk • B61-Q3 — Are B61-TR137AA/AB panel references tied to Room 137 or a schedule naming mismatch for Room 124? [Open] Impact: Electrical PMIS mapping risk • B61-Q4 — Are IU/CU-0-01, 1-01 and 2-01 on emergency/backup power and dedicated to the TRs they serve? [Open] Impact: Cooling continuity unclear • B61-Q5 — Where are clean-agent/CO2 FEC cabinets located within 75 ft of each new TR? [Open] Impact: Life-safety acceptance risk • B61-Q6 — Are rack UPS/PDU circuits, SPDs, labels, load measurements and LOTO requirements approved for all TR panelboards? [Open] Impact: Electrical readiness unknown
A45: Selected Building | B45: Selected Sheet | C45: Payment Confidence | D45: Payment Decision | E45: OIT Readiness | F45: OIT Status | G45: OIT Blocker | H45: Material Compliance | I45: Productivity | J45: Acceptance Readiness | K45: Owner Decision | L45: Signal | Z45: Selected_Display_Label
A46: =IFERROR(TEXT(VALUE($C$17),"00"),$C$17&"") -> 61 | B46: =IFERROR(INDEX(PMIS_Data!$B:$B,MATCH($A$46,PMIS_Data!$A:$A,0)),"") -> B61_Assessment | C46: =IFERROR(INDEX(PMIS_Data!$Z:$Z,MATCH($A$46,PMIS_Data!$A:$A,0)),0) -> 0 | D46: =IFERROR(INDEX(PMIS_Data!$AA:$AA,MATCH($A$46,PMIS_Data!$A:$A,0)),"") -> Withhold / Review | E46: =IFERROR(INDEX(PMIS_Data!$AB:$AB,MATCH($A$46,PMIS_Data!$A:$A,0)),0) -> 0 | F46: =IFERROR(INDEX(PMIS_Data!$AC:$AC,MATCH($A$46,PMIS_Data!$A:$A,0)),"") -> Blocked | G46: =IFERROR(INDEX(PMIS_Data!$AD:$AD,MATCH($A$46,PMIS_Data!$A:$A,0)),"") -> No blocker documented | H46: =IFERROR(INDEX(PMIS_Data!$AE:$AE,MATCH($A$46,PMIS_Data!$A:$A,0)),0) -> 0 | I46: =IFERROR(INDEX(PMIS_Data!$AG:$AG,MATCH($A$46,PMIS_Data!$A:$A,0)),0) -> 0 | J46: =IFERROR(INDEX(PMIS_Data!$AI:$AI,MATCH($A$46,PMIS_Data!$A:$A,0)),0) -> 0 | K46: =IFERROR(INDEX(PMIS_Data!$AM:$AM,MATCH($A$46,PMIS_Data!$A:$A,0)),"") -> Resolve OIT Blocker | L46: =IFERROR(INDEX(PMIS_Data!$AN:$AN,MATCH($A$46,PMIS_Data!$A:$A,0)),"") -> 🔴 ATTENTION | Z46: =IF($G$48="Campus","Campus",IFERROR(INDEX([4]_Command_Lists!$B$2:$B$33,MATCH($G$48,[4]_Command_Lists!$A$2:$A$33,0)),$G$48)) -> 61
AA47: =IFERROR(INDEX([4]_Command_Source!$B:$B,MATCH($Z$46,[4]_Command_Source!$A:$A,0)),"") -> B61_Assessment
A48: BUILDING MISSION MODULES — CLICK TILE TO OPEN ASSESSMENT | G48: =IFERROR(INDEX([4]_Command_Lists!$A$2:$A$33,MATCH($C$17&"",[4]_Command_Lists!$B$2:$B$33,0)),IFERROR("B"&TEXT(VALUE($C$17),"00"),$C$17&"")) -> B61 | I48: Use the selector to refresh the Command Center. Tiles are hyperlinks to source assessment sheets.
A50: ="SELECTED BUILDING WORKSPACE — "&$G$48&" OPERATIONAL PICTURE" -> SELECTED BUILDING WORKSPACE — B61 OPERATIONAL PICTURE
A51: =IF($Z$46="Campus","🌐 CAMPUS PROGRAM VIEW"&CHAR(10)&"Readiness: "&TEXT(AVERAGEIF(PMIS_Data!$E$3:$E$44,">0"),"0%")&CHAR(10)&"Open Risks: "&SUM(PMIS_Data!$H$3:$H$44)&CHAR(10)&"Open RFIs: "&SUM(PMIS_Data!$I$3:$I$44),IFERROR("🏢 BUILDING "&$G$48&CHAR(10)&"Status: "&INDEX(PMIS_Data!$C:$C,MATCH($Z$46,PMIS_Data!$A:$A,0))&CHAR(10)&"Readiness: "&TEXT(INDEX(PMIS_Data!$E:$E,MATCH($Z$46,PMIS_Data!$A:$A,0)),"0%")&CHAR(10)&"Construction Ready: "&INDEX(PMIS_Data!$F:$F,MATCH($Z$46,PMIS_Data!$A:$A,0))&CHAR(10)&"Rooms Captured: "&INDEX(PMIS_Data!$G:$G,MATCH($Z$46,PMIS_Data!$A:$A,0)),"No profile available.")) -> 🏢 BUILDING B61 Status: PILOT PHASE Readiness: 55% Construction Ready: YES Rooms Captured: 29 | E51: =IF($Z$46="Campus","⚠ CAMPUS BLOCKERS"&CHAR(10)&"Risks: "&SUM(PMIS_Data!$H$3:$H$44)&CHAR(10)&"RFIs: "&SUM(PMIS_Data!$I$3:$I$44)&CHAR(10)&"Review red/yellow building modules.",IFERROR("⚠ CURRENT BLOCKERS"&CHAR(10)&"Open Risks: "&INDEX(PMIS_Data!$H:$H,MATCH($Z$46,PMIS_Data!$A:$A,0))&CHAR(10)&"Open Questions: "&INDEX(PMIS_Data!$I:$I,MATCH($Z$46,PMIS_Data!$A:$A,0))&CHAR(10)&"Major Blocker: "&INDEX(PMIS_Data!$R:$R,MATCH($Z$46,PMIS_Data!$A:$A,0)),"No blocker data.")) -> ⚠ CURRENT BLOCKERS Open Risks: 0 Open Questions: 0 Major Blocker: Building 61 is a large full-scope TR building with hazardous abatement, architectural, fire protection, plumbing, mechanical, electrical, security, telecom, server/demarc and rack elevation scope. Primary new telecom rooms include basement B13H-A, first-level 124, second-level 226, and existing Room 137/137A demarc/server equipment. Major open issues include active-service cutover, dedicated cooling IU/CU-0-01/1-01/2-01, panel source coordination, rack UPS/PDU power, cable tray coordination, firestopping, PACS/CCTV, and turnover testing. | I51: =IF($Z$46="Campus","📷 FIELD CAPTURE"&CHAR(10)&"Open Photos: "&SUM(PMIS_Data!$J$3:$J$44)&CHAR(10)&"Documents: review register.",IFERROR("📷 FIELD CAPTURE"&CHAR(10)&"Open Photo Items: "&INDEX(PMIS_Data!$J:$J,MATCH($Z$46,PMIS_Data!$A:$A,0))&CHAR(10)&"HVAC: "&INDEX(PMIS_Data!$K:$K,MATCH($Z$46,PMIS_Data!$A:$A,0))&CHAR(10)&"Electrical: "&INDEX(PMIS_Data!$L:$L,MATCH($Z$46,PMIS_Data!$A:$A,0))&CHAR(10)&"Telecom: "&INDEX(PMIS_Data!$M:$M,MATCH($Z$46,PMIS_Data!$A:$A,0)),"No field data.")) -> 📷 FIELD CAPTURE Open Photo Items: 0 HVAC: Not Started Electrical: Not Started Telecom: Not Started | M51: =IF($Z$46="Campus","✅ NEXT REQUIRED ACTION"&CHAR(10)&"Triage campus-wide red/yellow tiles and issue closeout tasks.",IFERROR("✅ NEXT REQUIRED ACTION"&CHAR(10)&INDEX(PMIS_Data!$Q:$Q,MATCH($Z$46,PMIS_Data!$A:$A,0))&CHAR(10)&"Source: "&INDEX(PMIS_Data!$B:$B,MATCH($Z$46,PMIS_Data!$A:$A,0)),"No action data.")) -> ✅ NEXT REQUIRED ACTION Field verify B13H-A, 124, 226, and existing 137/137A; confirm active services, rack/equipment transfer, B61-TRB13A/B, B61-TR124A/B, B61-TR226A/B, B61-TR137AA/AB panel sources, IU/CU equipment, fire alarm/sprinkler impacts, FEC locations, PACS/CCTV scope, hazardous/abatement impacts, 1,966 ft cable tray routes, and cutover sequence. Source: B61_Assessment
A60: MISSION FEED — NEXT ACTIONS / RELEASE POSTURE
A61: =IF($Z$46="Campus","🌐 Campus: review critical modules, open risks, RFIs, shutdowns, and field capture gaps."&CHAR(10)&"• Select a building for module-level feed."&CHAR(10)&"• Building tiles open assessment source sheets.",IFERROR("🏢 "&$G$48&" Mission Feed"&CHAR(10)&"• Next Action: "&INDEX(PMIS_Data!$Q:$Q,MATCH($Z$46,PMIS_Data!$A:$A,0))&CHAR(10)&"• Major Blocker: "&INDEX(PMIS_Data!$R:$R,MATCH($Z$46,PMIS_Data!$A:$A,0))&CHAR(10)&"• Risks/RFIs/Photos: "&INDEX(PMIS_Data!$H:$H,MATCH($Z$46,PMIS_Data!$A:$A,0))&" / "&INDEX(PMIS_Data!$I:$I,MATCH($Z$46,PMIS_Data!$A:$A,0))&" / "&INDEX(PMIS_Data!$J:$J,MATCH($Z$46,PMIS_Data!$A:$A,0)),"No mission feed available.")) -> 🏢 B61 Mission Feed • Next Action: Field verify B13H-A, 124, 226, and existing 137/137A; confirm active services, rack/equipment transfer, B61-TRB13A/B, B61-TR124A/B, B61-TR226A/B, B61-TR137AA/AB panel sources, IU/CU equipment, fire alarm/sprinkler impacts, FEC locations, PACS/CCTV scope, hazardous/abatement impacts, 1,966 ft cable tray routes, and cutover sequence. • Major Blocker: Building 61 is a large full-scope TR building with hazardous abatement, architectural, fire protection, plumbing, mechanical, electrical, security, telecom, server/demarc and rack elevation scope. Primary new telecom rooms include basement B13H-A, first-level 124, second-level 226, and existing Room 137/137A demarc/server equipment. Major open issues include active-service cutover, dedicated cooling IU/CU-0-01/1-01/2-01, panel source coordination, rack UPS/PDU power, cable tray coordination, firestopping, PACS/CCTV, and turnover testing. • Risks/RFIs/Photos: 0 / 0 / 0
A70: TRADE SECTION CARDS — SELECTED BUILDING NOTES
A71: ="🔥 FIRE / LIFE SAFETY"&CHAR(10)&AB43 -> 🔥 FIRE / LIFE SAFETY • Dedicated TR scope includes fire protection drawings. Verify sprinkler modifications, fire alarm devices, clean-agent 2A:10B:C FEC within 75 ft, rated penetrations, and temporary firestopping. • Verify sprinkler/fire alarm modifications, clean-agent FEC location, penetrations, cable tray/riser openings, and final UL firestop systems. • Verify second-level TR sprinkler/fire alarm modifications, clean-agent FEC location, vertical riser penetrations, and firestopping. • Existing demarc/server rooms may remain active; verify protection-in-place, FA/FP continuity, and no unsealed penetrations after cabling work. | I71: ="❄ HVAC / COOLING"&CHAR(10)&AC43 -> ❄ HVAC / COOLING • Mechanical sheets identify dedicated split-system cooling with BACnet adapter mounted adjacent to unit in telecom room. Confirm capacity, emergency source, condensate, disconnect, controls, and alarms. • Mechanical/electrical plans identify IU-1-01/CU-1-01 for first-level TR. Confirm 24/7 operation, emergency/standby source and high-temp alarm. • Mechanical/electrical plans identify IU-2-01/CU-2-01 for second-level TR. Confirm refrigerant route, condensate route, controls and alarm tie-in. • Existing demarc/server equipment likely has existing cooling dependencies. Verify active equipment heat load, airflow, operational temperatures and whether any existing cooling is modified or protected.
A78: ="⚡ ELECTRICAL / UPS"&CHAR(10)&AD43 -> ⚡ ELECTRICAL / UPS • Electrical enlarged plans and schedules identify rack receptacles, UPS circuits, PDUs, panelboards, SPD devices and dedicated cooling power for B13H-A. Verify B61-TRB13A/B source, LOTO and labels. • Electrical schedules identify B61-TR124A/B and rack receptacles. Verify apparent room-name mismatch with RM137B rack receptacles in schedules. • Electrical schedules identify B61-TR226A/B, rack receptacles, CU-2-01 and SPD requirements. Verify source circuits and labels. • Existing rack inventory includes APC UPS/PDU and server/demarc equipment. Electrical one-line/schedules list B61-TR137AA/AB and PD-B61-TR137 panels; verify active sources and transition impact. | I78: ="📡 TELECOM / FIBER"&CHAR(10)&AE43 -> 📡 TELECOM / FIBER • 61T-701: 88 WAO total, 74 active ports, 129 scheduled ports, 142 with 10% allowance. Rack ID TR01-B13H-A-1. Basement cable tray included in 890 ft basement total. • 61T-701: first-level Room 124 / Rack ID TR01-124-1. Schedule data runs across first-level outlets. Include labels, Fiber LIU, Cat6A patch panels, UPS/PDU and VA/OIT acceptance. • 61T-702: 109 WAO total, 126 active ports, 156 scheduled ports, 172 with 10% allowance. Rack ID TR01-226-1. Verify second-level cable tray and riser penetrations. • 61T-402/606/607 inventory existing demarc/server racks and equipment. Protect active systems, coordinate cutover, preserve labels, document equipment remaining in service.
A85: 🔐 SECURITY / PACS / CCTV • Telecom plans call for wall-mounted CCTV at TRs and PACS for TR doors. Verify camera, controller, CR/RX/DC/ES/MD, and VMS/PACS integration. • Verify TR door hardware and access control, CCTV camera, network door controller and integration. • Verify second-level TR access control, CCTV camera, door hardware, and VMS/PACS integration. • Existing PACS/equipment racks are referenced. Verify existing security devices protected-in-place and any new recabling or integration scope. | I85: ="❓ RISKS / OPEN QUESTIONS"&CHAR(10)&"Owner Risks:"&CHAR(10)&AG43&CHAR(10)&"Open Questions:"&CHAR(10)&AH43 -> ❓ RISKS / OPEN QUESTIONS Owner Risks: • High: Existing conditions and active equipment across B13H-A, 124, 226 and 137/137A not field verified — Perform existing conditions survey with photos and active-service inventory before mobilization • High: Hazardous material abatement plans exist for first and second levels — Coordinate IH/abatement review before penetrations, wall/ceiling work, cabling or mechanical/electrical installation • Critical: Existing server/demarc equipment may remain active during cutover — Document active services, service provider circuits, rack inventory, OIT windows, temporary utilities and rollback path • Critical: Dedicated cooling sequence, emergency power, condensate, BACnet and alarms not verified — Confirm IU/CU-0/1/2 power source, condensate, controls, BACnet adapter, thermostat and high-temp alarm • Critical: Panel source, UPS/PDU and rack receptacle coordination could delay energization — Verify B61-TRB13A/B, B61-TR124A/B, B61-TR226A/B, B61-TR137AA/AB, PD panels, SPDs and load measurements • High: Large cable tray scope creates coordination and firestop risk — Verify 1,966 ft cable tray route, supports, seismic bracing, 40% fill, MEP conflicts, sleeves and final firestop assemblies Open Questions: • B61-Q1 — Confirm final telecom room list and PMIS mapping: B13H-A, 124, 226 and existing 137/137A demarc/server rooms? [Open] Impact: Room inventory could miss scope • B61-Q2 — What active services and circuits are currently housed in Room 137/137A? [Open] Impact: Potential outage/cutover risk • B61-Q3 — Are B61-TR137AA/AB panel references tied to Room 137 or a schedule naming mismatch for Room 124? [Open] Impact: Electrical PMIS mapping risk • B61-Q4 — Are IU/CU-0-01, 1-01 and 2-01 on emergency/backup power and dedicated to the TRs they serve? [Open] Impact: Cooling continuity unclear • B61-Q5 — Where are clean-agent/CO2 FEC cabinets located within 75 ft of each new TR? [Open] Impact: Life-safety acceptance risk • B61-Q6 — Are rack UPS/PDU circuits, SPDs, labels, load measurements and LOTO requirements approved for all TR panelboards? [Open] Impact: Electrical readiness unknown
A92: SOURCE OF TRUTH: Building assessment sheets remain authoritative. The Command Center reads from PMIS_Data, _Command_Card_Index, and _Assessment_Full_View.
A95: SELECTED BUILDING SOURCE DETAIL — FIRST 25 ASSESSMENT ROWS (HIDDEN)
A96: Section | C96: Room / Area | E96: Item / System | H96: Impact / Detail | K96: Status / Owner | N96: Notes
A97: =IFERROR(INDEX([4]_Assessment_Full_View!$E:$E,MATCH($Z$46&"|"&ROWS($A$97:A97),[4]_Assessment_Full_View!$Q:$Q,0)),"") -> 1. ROOM INVENTORY | C97: =IFERROR(INDEX([4]_Assessment_Full_View!$G:$G,MATCH($Z$46&"|"&ROWS($A$97:A97),[4]_Assessment_Full_View!$Q:$Q,0))&" / "&INDEX([4]_Assessment_Full_View!$H:$H,MATCH($Z$46&"|"&ROWS($A$97:A97),[4]_Assessment_Full_View!$Q:$Q,0)),"") -> 1. ROOM INVENTORY / 0 | E97: =IFERROR(INDEX([4]_Assessment_Full_View!$I:$I,MATCH($Z$46&"|"&ROWS($A$97:A97),[4]_Assessment_Full_View!$Q:$Q,0))&" / "&INDEX([4]_Assessment_Full_View!$J:$J,MATCH($Z$46&"|"&ROWS($A$97:A97),[4]_Assessment_Full_View!$Q:$Q,0)),"") -> 0 / 0 | H97: =IFERROR(INDEX([4]_Assessment_Full_View!$K:$K,MATCH($Z$46&"|"&ROWS($A$97:A97),[4]_Assessment_Full_View!$Q:$Q,0))&" / "&INDEX([4]_Assessment_Full_View!$L:$L,MATCH($Z$46&"|"&ROWS($A$97:A97),[4]_Assessment_Full_View!$Q:$Q,0)),"") -> 0 / 0 | K97: =IFERROR(INDEX([4]_Assessment_Full_View!$O:$O,MATCH($Z$46&"|"&ROWS($A$97:A97),[4]_Assessment_Full_View!$Q:$Q,0)),"") -> 0 | N97: =IFERROR(INDEX([4]_Assessment_Full_View!$P:$P,MATCH($Z$46&"|"&ROWS($A$97:A97),[4]_Assessment_Full_View!$Q:$Q,0)),"") -> 0
A98: =IFERROR(INDEX([5]_Assessment_Full_View!$E:$E,MATCH($Z$46&"|"&ROWS($A$97:A98),[5]_Assessment_Full_View!$Q:$Q,0)),"") -> 1. ROOM INVENTORY | C98: =IFERROR(INDEX([5]_Assessment_Full_View!$G:$G,MATCH($Z$46&"|"&ROWS($A$97:A98),[5]_Assessment_Full_View!$Q:$Q,0))&" / "&INDEX([5]_Assessment_Full_View!$H:$H,MATCH($Z$46&"|"&ROWS($A$97:A98),[5]_Assessment_Full_View!$Q:$Q,0)),"") -> Building / Room | E98: =IFERROR(INDEX([5]_Assessment_Full_View!$I:$I,MATCH($Z$46&"|"&ROWS($A$97:A98),[5]_Assessment_Full_View!$Q:$Q,0))&" / "&INDEX([5]_Assessment_Full_View!$J:$J,MATCH($Z$46&"|"&ROWS($A$97:A98),[5]_Assessment_Full_View!$Q:$Q,0)),"") -> Floor / Existing Use | H98: =IFERROR(INDEX([5]_Assessment_Full_View!$K:$K,MATCH($Z$46&"|"&ROWS($A$97:A98),[5]_Assessment_Full_View!$Q:$Q,0))&" / "&INDEX([5]_Assessment_Full_View!$L:$L,MATCH($Z$46&"|"&ROWS($A$97:A98),[5]_Assessment_Full_View!$Q:$Q,0)),"") -> New Use / Rack Count | K98: =IFERROR(INDEX([5]_Assessment_Full_View!$O:$O,MATCH($Z$46&"|"&ROWS($A$97:A98),[5]_Assessment_Full_View!$Q:$Q,0)),"") -> Drawing Ref | N98: =IFERROR(INDEX([5]_Assessment_Full_View!$P:$P,MATCH($Z$46&"|"&ROWS($A$97:A98),[5]_Assessment_Full_View!$Q:$Q,0)),"") -> Notes
A99: =IFERROR(INDEX([5]_Assessment_Full_View!$E:$E,MATCH($Z$46&"|"&ROWS($A$97:A99),[5]_Assessment_Full_View!$Q:$Q,0)),"") -> 1. ROOM INVENTORY | C99: =IFERROR(INDEX([5]_Assessment_Full_View!$G:$G,MATCH($Z$46&"|"&ROWS($A$97:A99),[5]_Assessment_Full_View!$Q:$Q,0))&" / "&INDEX([5]_Assessment_Full_View!$H:$H,MATCH($Z$46&"|"&ROWS($A$97:A99),[5]_Assessment_Full_View!$Q:$Q,0)),"") -> 61 / B13H-A | E99: =IFERROR(INDEX([5]_Assessment_Full_View!$I:$I,MATCH($Z$46&"|"&ROWS($A$97:A99),[5]_Assessment_Full_View!$Q:$Q,0))&" / "&INDEX([5]_Assessment_Full_View!$J:$J,MATCH($Z$46&"|"&ROWS($A$97:A99),[5]_Assessment_Full_View!$Q:$Q,0)),"") -> Basement / Basement telecom / support area | H99: =IFERROR(INDEX([5]_Assessment_Full_View!$K:$K,MATCH($Z$46&"|"&ROWS($A$97:A99),[5]_Assessment_Full_View!$Q:$Q,0))&" / "&INDEX([5]_Assessment_Full_View!$L:$L,MATCH($Z$46&"|"&ROWS($A$97:A99),[5]_Assessment_Full_View!$Q:$Q,0)),"") -> Telecom Room / 1 | K99: =IFERROR(INDEX([5]_Assessment_Full_View!$O:$O,MATCH($Z$46&"|"&ROWS($A$97:A99),[5]_Assessment_Full_View!$Q:$Q,0)),"") -> 61A-400 / 61E-401 / 61T-100 / 61T-401 / 61T-604 / 61T-701 | N99: =IFERROR(INDEX([5]_Assessment_Full_View!$P:$P,MATCH($Z$46&"|"&ROWS($A$97:A99),[5]_Assessment_Full_View!$Q:$Q,0)),"") -> Basement TR identified as RM B13H-A with Rack ID TR01-B13H-A-1. Schedules identify 88 WAO total, 74 active ports, 129 scheduled ports, 142 ports with 10% allowance. Electrical panels include B61-TRB13A/B. Mechanical cooling includes IU-0-01/CU-0-01.
A100: =IFERROR(INDEX([5]_Assessment_Full_View!$E:$E,MATCH($Z$46&"|"&ROWS($A$97:A100),[5]_Assessment_Full_View!$Q:$Q,0)),"") -> 1. ROOM INVENTORY | C100: =IFERROR(INDEX([5]_Assessment_Full_View!$G:$G,MATCH($Z$46&"|"&ROWS($A$97:A100),[5]_Assessment_Full_View!$Q:$Q,0))&" / "&INDEX([5]_Assessment_Full_View!$H:$H,MATCH($Z$46&"|"&ROWS($A$97:A100),[5]_Assessment_Full_View!$Q:$Q,0)),"") -> 61 / 124 | E100: =IFERROR(INDEX([5]_Assessment_Full_View!$I:$I,MATCH($Z$46&"|"&ROWS($A$97:A100),[5]_Assessment_Full_View!$Q:$Q,0))&" / "&INDEX([5]_Assessment_Full_View!$J:$J,MATCH($Z$46&"|"&ROWS($A$97:A100),[5]_Assessment_Full_View!$Q:$Q,0)),"") -> First / First-level telecom area | H100: =IFERROR(INDEX([5]_Assessment_Full_View!$K:$K,MATCH($Z$46&"|"&ROWS($A$97:A100),[5]_Assessment_Full_View!$Q:$Q,0))&" / "&INDEX([5]_Assessment_Full_View!$L:$L,MATCH($Z$46&"|"&ROWS($A$97:A100),[5]_Assessment_Full_View!$Q:$Q,0)),"") -> Telecom Room / 1 | K100: =IFERROR(INDEX([5]_Assessment_Full_View!$O:$O,MATCH($Z$46&"|"&ROWS($A$97:A100),[5]_Assessment_Full_View!$Q:$Q,0)),"") -> 61A-400 / 61E-402 / 61T-101 / 61T-401 / 61T-604 / 61T-701 | N100: =IFERROR(INDEX([5]_Assessment_Full_View!$P:$P,MATCH($Z$46&"|"&ROWS($A$97:A100),[5]_Assessment_Full_View!$Q:$Q,0)),"") -> First-level TR identified as Room 124 / Rack ID TR01-124-1. Electrical panels include B61-TR124A/B. Mechanical cooling includes IU-1-01/CU-1-01. Verify room naming against electrical schedule references that also call out RM137B rack receptacles.
A101: =IFERROR(INDEX([5]_Assessment_Full_View!$E:$E,MATCH($Z$46&"|"&ROWS($A$97:A101),[5]_Assessment_Full_View!$Q:$Q,0)),"") -> 1. ROOM INVENTORY | C101: =IFERROR(INDEX([5]_Assessment_Full_View!$G:$G,MATCH($Z$46&"|"&ROWS($A$97:A101),[5]_Assessment_Full_View!$Q:$Q,0))&" / "&INDEX([5]_Assessment_Full_View!$H:$H,MATCH($Z$46&"|"&ROWS($A$97:A101),[5]_Assessment_Full_View!$Q:$Q,0)),"") -> 61 / 226 | E101: =IFERROR(INDEX([5]_Assessment_Full_View!$I:$I,MATCH($Z$46&"|"&ROWS($A$97:A101),[5]_Assessment_Full_View!$Q:$Q,0))&" / "&INDEX([5]_Assessment_Full_View!$J:$J,MATCH($Z$46&"|"&ROWS($A$97:A101),[5]_Assessment_Full_View!$Q:$Q,0)),"") -> Second / Second-level telecom area | H101: =IFERROR(INDEX([5]_Assessment_Full_View!$K:$K,MATCH($Z$46&"|"&ROWS($A$97:A101),[5]_Assessment_Full_View!$Q:$Q,0))&" / "&INDEX([5]_Assessment_Full_View!$L:$L,MATCH($Z$46&"|"&ROWS($A$97:A101),[5]_Assessment_Full_View!$Q:$Q,0)),"") -> Telecom Room / 1 | K101: =IFERROR(INDEX([5]_Assessment_Full_View!$O:$O,MATCH($Z$46&"|"&ROWS($A$97:A101),[5]_Assessment_Full_View!$Q:$Q,0)),"") -> 61A-401 / 61E-402 / 61T-102 / 61T-401 / 61T-605 / 61T-702 | N101: =IFERROR(INDEX([5]_Assessment_Full_View!$P:$P,MATCH($Z$46&"|"&ROWS($A$97:A101),[5]_Assessment_Full_View!$Q:$Q,0)),"") -> Second-level TR identified as Room 226 / Rack ID TR01-226-1. Schedules identify 109 WAO total, 126 active ports, 156 scheduled ports, 172 ports with 10% allowance. Electrical panels include B61-TR226A/B. Mechanical cooling includes IU-2-01/CU-2-01.
A102: =IFERROR(INDEX([5]_Assessment_Full_View!$E:$E,MATCH($Z$46&"|"&ROWS($A$97:A102),[5]_Assessment_Full_View!$Q:$Q,0)),"") -> 1. ROOM INVENTORY | C102: =IFERROR(INDEX([5]_Assessment_Full_View!$G:$G,MATCH($Z$46&"|"&ROWS($A$97:A102),[5]_Assessment_Full_View!$Q:$Q,0))&" / "&INDEX([5]_Assessment_Full_View!$H:$H,MATCH($Z$46&"|"&ROWS($A$97:A102),[5]_Assessment_Full_View!$Q:$Q,0)),"") -> 61 / 137 / 137A | E102: =IFERROR(INDEX([5]_Assessment_Full_View!$I:$I,MATCH($Z$46&"|"&ROWS($A$97:A102),[5]_Assessment_Full_View!$Q:$Q,0))&" / "&INDEX([5]_Assessment_Full_View!$J:$J,MATCH($Z$46&"|"&ROWS($A$97:A102),[5]_Assessment_Full_View!$Q:$Q,0)),"") -> First / Existing server/demarc/telecom equipment rooms | H102: =IFERROR(INDEX([5]_Assessment_Full_View!$K:$K,MATCH($Z$46&"|"&ROWS($A$97:A102),[5]_Assessment_Full_View!$Q:$Q,0))&" / "&INDEX([5]_Assessment_Full_View!$L:$L,MATCH($Z$46&"|"&ROWS($A$97:A102),[5]_Assessment_Full_View!$Q:$Q,0)),"") -> Existing demarc / server transition point / 11 | K102: =IFERROR(INDEX([5]_Assessment_Full_View!$O:$O,MATCH($Z$46&"|"&ROWS($A$97:A102),[5]_Assessment_Full_View!$Q:$Q,0)),"") -> 61T-402 / 61T-606 / 61T-607 / 61R-900 | N102: =IFERROR(INDEX([5]_Assessment_Full_View!$P:$P,MATCH($Z$46&"|"&ROWS($A$97:A102),[5]_Assessment_Full_View!$Q:$Q,0)),"") -> Existing Room 137/137A rack inventory and demarc/server equipment include existing 4-post racks, PACS/equipment racks, APC UPS/PDU equipment, Fujitsu FLM equipment, wall-mounted patch panels, and local elevations. Protect active services and verify what remains, transfers, or is modified.
A103: =IFERROR(INDEX([5]_Assessment_Full_View!$E:$E,MATCH($Z$46&"|"&ROWS($A$97:A103),[5]_Assessment_Full_View!$Q:$Q,0)),"") -> 1. ROOM INVENTORY | C103: =IFERROR(INDEX([5]_Assessment_Full_View!$G:$G,MATCH($Z$46&"|"&ROWS($A$97:A103),[5]_Assessment_Full_View!$Q:$Q,0))&" / "&INDEX([5]_Assessment_Full_View!$H:$H,MATCH($Z$46&"|"&ROWS($A$97:A103),[5]_Assessment_Full_View!$Q:$Q,0)),"") -> 0 / 0 | E103: =IFERROR(INDEX([5]_Assessment_Full_View!$I:$I,MATCH($Z$46&"|"&ROWS($A$97:A103),[5]_Assessment_Full_View!$Q:$Q,0))&" / "&INDEX([5]_Assessment_Full_View!$J:$J,MATCH($Z$46&"|"&ROWS($A$97:A103),[5]_Assessment_Full_View!$Q:$Q,0)),"") -> 0 / 0 | H103: =IFERROR(INDEX([5]_Assessment_Full_View!$K:$K,MATCH($Z$46&"|"&ROWS($A$97:A103),[5]_Assessment_Full_View!$Q:$Q,0))&" / "&INDEX([5]_Assessment_Full_View!$L:$L,MATCH($Z$46&"|"&ROWS($A$97:A103),[5]_Assessment_Full_View!$Q:$Q,0)),"") -> 0 / 0 | K103: =IFERROR(INDEX([5]_Assessment_Full_View!$O:$O,MATCH($Z$46&"|"&ROWS($A$97:A103),[5]_Assessment_Full_View!$Q:$Q,0)),"") -> 0 | N103: =IFERROR(INDEX([5]_Assessment_Full_View!$P:$P,MATCH($Z$46&"|"&ROWS($A$97:A103),[5]_Assessment_Full_View!$Q:$Q,0)),"") -> 0
A104: =IFERROR(INDEX([5]_Assessment_Full_View!$E:$E,MATCH($Z$46&"|"&ROWS($A$97:A104),[5]_Assessment_Full_View!$Q:$Q,0)),"") -> 2. ROOM READINESS | C104: =IFERROR(INDEX([5]_Assessment_Full_View!$G:$G,MATCH($Z$46&"|"&ROWS($A$97:A104),[5]_Assessment_Full_View!$Q:$Q,0))&" / "&INDEX([5]_Assessment_Full_View!$H:$H,MATCH($Z$46&"|"&ROWS($A$97:A104),[5]_Assessment_Full_View!$Q:$Q,0)),"") -> 2. ROOM READINESS / 0 | E104: =IFERROR(INDEX([5]_Assessment_Full_View!$I:$I,MATCH($Z$46&"|"&ROWS($A$97:A104),[5]_Assessment_Full_View!$Q:$Q,0))&" / "&INDEX([5]_Assessment_Full_View!$J:$J,MATCH($Z$46&"|"&ROWS($A$97:A104),[5]_Assessment_Full_View!$Q:$Q,0)),"") -> 0 / 0 | H104: =IFERROR(INDEX([5]_Assessment_Full_View!$K:$K,MATCH($Z$46&"|"&ROWS($A$97:A104),[5]_Assessment_Full_View!$Q:$Q,0))&" / "&INDEX([5]_Assessment_Full_View!$L:$L,MATCH($Z$46&"|"&ROWS($A$97:A104),[5]_Assessment_Full_View!$Q:$Q,0)),"") -> 0 / 0 | K104: =IFERROR(INDEX([5]_Assessment_Full_View!$O:$O,MATCH($Z$46&"|"&ROWS($A$97:A104),[5]_Assessment_Full_View!$Q:$Q,0)),"") -> 0 | N104: =IFERROR(INDEX([5]_Assessment_Full_View!$P:$P,MATCH($Z$46&"|"&ROWS($A$97:A104),[5]_Assessment_Full_View!$Q:$Q,0)),"") -> 0
A105: =IFERROR(INDEX([5]_Assessment_Full_View!$E:$E,MATCH($Z$46&"|"&ROWS($A$97:A105),[5]_Assessment_Full_View!$Q:$Q,0)),"") -> 2. ROOM READINESS | C105: =IFERROR(INDEX([5]_Assessment_Full_View!$G:$G,MATCH($Z$46&"|"&ROWS($A$97:A105),[5]_Assessment_Full_View!$Q:$Q,0))&" / "&INDEX([5]_Assessment_Full_View!$H:$H,MATCH($Z$46&"|"&ROWS($A$97:A105),[5]_Assessment_Full_View!$Q:$Q,0)),"") -> Room / Walls / 1-hr Rating | E105: =IFERROR(INDEX([5]_Assessment_Full_View!$I:$I,MATCH($Z$46&"|"&ROWS($A$97:A105),[5]_Assessment_Full_View!$Q:$Q,0))&" / "&INDEX([5]_Assessment_Full_View!$J:$J,MATCH($Z$46&"|"&ROWS($A$97:A105),[5]_Assessment_Full_View!$Q:$Q,0)),"") -> Ceiling / Floor / SDC | H105: =IFERROR(INDEX([5]_Assessment_Full_View!$K:$K,MATCH($Z$46&"|"&ROWS($A$97:A105),[5]_Assessment_Full_View!$Q:$Q,0))&" / "&INDEX([5]_Assessment_Full_View!$L:$L,MATCH($Z$46&"|"&ROWS($A$97:A105),[5]_Assessment_Full_View!$Q:$Q,0)),"") -> Penetrations / Access Control | K105: =IFERROR(INDEX([5]_Assessment_Full_View!$O:$O,MATCH($Z$46&"|"&ROWS($A$97:A105),[5]_Assessment_Full_View!$Q:$Q,0)),"") -> Overall | N105: =IFERROR(INDEX([5]_Assessment_Full_View!$P:$P,MATCH($Z$46&"|"&ROWS($A$97:A105),[5]_Assessment_Full_View!$Q:$Q,0)),"") -> Comments
A106: =IFERROR(INDEX([5]_Assessment_Full_View!$E:$E,MATCH($Z$46&"|"&ROWS($A$97:A106),[5]_Assessment_Full_View!$Q:$Q,0)),"") -> 2. ROOM READINESS | C106: =IFERROR(INDEX([5]_Assessment_Full_View!$G:$G,MATCH($Z$46&"|"&ROWS($A$97:A106),[5]_Assessment_Full_View!$Q:$Q,0))&" / "&INDEX([5]_Assessment_Full_View!$H:$H,MATCH($Z$46&"|"&ROWS($A$97:A106),[5]_Assessment_Full_View!$Q:$Q,0)),"") -> B13H-A / Verify | E106: =IFERROR(INDEX([5]_Assessment_Full_View!$I:$I,MATCH($Z$46&"|"&ROWS($A$97:A106),[5]_Assessment_Full_View!$Q:$Q,0))&" / "&INDEX([5]_Assessment_Full_View!$J:$J,MATCH($Z$46&"|"&ROWS($A$97:A106),[5]_Assessment_Full_View!$Q:$Q,0)),"") -> Verify / Verify | H106: =IFERROR(INDEX([5]_Assessment_Full_View!$K:$K,MATCH($Z$46&"|"&ROWS($A$97:A106),[5]_Assessment_Full_View!$Q:$Q,0))&" / "&INDEX([5]_Assessment_Full_View!$L:$L,MATCH($Z$46&"|"&ROWS($A$97:A106),[5]_Assessment_Full_View!$Q:$Q,0)),"") -> Verify / Verify | K106: =IFERROR(INDEX([5]_Assessment_Full_View!$O:$O,MATCH($Z$46&"|"&ROWS($A$97:A106),[5]_Assessment_Full_View!$Q:$Q,0)),"") -> Verify | N106: =IFERROR(INDEX([5]_Assessment_Full_View!$P:$P,MATCH($Z$46&"|"&ROWS($A$97:A106),[5]_Assessment_Full_View!$Q:$Q,0)),"") -> Basement TR; verify rated walls/open-to-deck conditions, door/security, floor finish, ladder rack/cable tray, future rack clearance, wall backing, and pathway entries.
A107: =IFERROR(INDEX([5]_Assessment_Full_View!$E:$E,MATCH($Z$46&"|"&ROWS($A$97:A107),[5]_Assessment_Full_View!$Q:$Q,0)),"") -> 2. ROOM READINESS | C107: =IFERROR(INDEX([5]_Assessment_Full_View!$G:$G,MATCH($Z$46&"|"&ROWS($A$97:A107),[5]_Assessment_Full_View!$Q:$Q,0))&" / "&INDEX([5]_Assessment_Full_View!$H:$H,MATCH($Z$46&"|"&ROWS($A$97:A107),[5]_Assessment_Full_View!$Q:$Q,0)),"") -> 124 / Verify | E107: =IFERROR(INDEX([5]_Assessment_Full_View!$I:$I,MATCH($Z$46&"|"&ROWS($A$97:A107),[5]_Assessment_Full_View!$Q:$Q,0))&" / "&INDEX([5]_Assessment_Full_View!$J:$J,MATCH($Z$46&"|"&ROWS($A$97:A107),[5]_Assessment_Full_View!$Q:$Q,0)),"") -> Verify / Verify | H107: =IFERROR(INDEX([5]_Assessment_Full_View!$K:$K,MATCH($Z$46&"|"&ROWS($A$97:A107),[5]_Assessment_Full_View!$Q:$Q,0))&" / "&INDEX([5]_Assessment_Full_View!$L:$L,MATCH($Z$46&"|"&ROWS($A$97:A107),[5]_Assessment_Full_View!$Q:$Q,0)),"") -> Verify / Verify | K107: =IFERROR(INDEX([5]_Assessment_Full_View!$O:$O,MATCH($Z$46&"|"&ROWS($A$97:A107),[5]_Assessment_Full_View!$Q:$Q,0)),"") -> Verify | N107: =IFERROR(INDEX([5]_Assessment_Full_View!$P:$P,MATCH($Z$46&"|"&ROWS($A$97:A107),[5]_Assessment_Full_View!$Q:$Q,0)),"") -> First-level TR; verify rated construction, door hardware, ceiling/deck, rack/future rack clearances, wall backing, and riser/pathway entries.
A108: =IFERROR(INDEX([5]_Assessment_Full_View!$E:$E,MATCH($Z$46&"|"&ROWS($A$97:A108),[5]_Assessment_Full_View!$Q:$Q,0)),"") -> 2. ROOM READINESS | C108: =IFERROR(INDEX([5]_Assessment_Full_View!$G:$G,MATCH($Z$46&"|"&ROWS($A$97:A108),[5]_Assessment_Full_View!$Q:$Q,0))&" / "&INDEX([5]_Assessment_Full_View!$H:$H,MATCH($Z$46&"|"&ROWS($A$97:A108),[5]_Assessment_Full_View!$Q:$Q,0)),"") -> 226 / Verify | E108: =IFERROR(INDEX([5]_Assessment_Full_View!$I:$I,MATCH($Z$46&"|"&ROWS($A$97:A108),[5]_Assessment_Full_View!$Q:$Q,0))&" / "&INDEX([5]_Assessment_Full_View!$J:$J,MATCH($Z$46&"|"&ROWS($A$97:A108),[5]_Assessment_Full_View!$Q:$Q,0)),"") -> Verify / Verify | H108: =IFERROR(INDEX([5]_Assessment_Full_View!$K:$K,MATCH($Z$46&"|"&ROWS($A$97:A108),[5]_Assessment_Full_View!$Q:$Q,0))&" / "&INDEX([5]_Assessment_Full_View!$L:$L,MATCH($Z$46&"|"&ROWS($A$97:A108),[5]_Assessment_Full_View!$Q:$Q,0)),"") -> Verify / Verify | K108: =IFERROR(INDEX([5]_Assessment_Full_View!$O:$O,MATCH($Z$46&"|"&ROWS($A$97:A108),[5]_Assessment_Full_View!$Q:$Q,0)),"") -> Verify | N108: =IFERROR(INDEX([5]_Assessment_Full_View!$P:$P,MATCH($Z$46&"|"&ROWS($A$97:A108),[5]_Assessment_Full_View!$Q:$Q,0)),"") -> Second-level TR; verify rated construction, door hardware, ceiling/deck, rack/future rack clearances, wall backing, and riser/pathway entries.
A109: =IFERROR(INDEX([5]_Assessment_Full_View!$E:$E,MATCH($Z$46&"|"&ROWS($A$97:A109),[5]_Assessment_Full_View!$Q:$Q,0)),"") -> 2. ROOM READINESS | C109: =IFERROR(INDEX([5]_Assessment_Full_View!$G:$G,MATCH($Z$46&"|"&ROWS($A$97:A109),[5]_Assessment_Full_View!$Q:$Q,0))&" / "&INDEX([5]_Assessment_Full_View!$H:$H,MATCH($Z$46&"|"&ROWS($A$97:A109),[5]_Assessment_Full_View!$Q:$Q,0)),"") -> 137 / 137A / Existing / Verify | E109: =IFERROR(INDEX([5]_Assessment_Full_View!$I:$I,MATCH($Z$46&"|"&ROWS($A$97:A109),[5]_Assessment_Full_View!$Q:$Q,0))&" / "&INDEX([5]_Assessment_Full_View!$J:$J,MATCH($Z$46&"|"&ROWS($A$97:A109),[5]_Assessment_Full_View!$Q:$Q,0)),"") -> Existing / Verify / Existing / Verify | H109: =IFERROR(INDEX([5]_Assessment_Full_View!$K:$K,MATCH($Z$46&"|"&ROWS($A$97:A109),[5]_Assessment_Full_View!$Q:$Q,0))&" / "&INDEX([5]_Assessment_Full_View!$L:$L,MATCH($Z$46&"|"&ROWS($A$97:A109),[5]_Assessment_Full_View!$Q:$Q,0)),"") -> Verify / Verify | K109: =IFERROR(INDEX([5]_Assessment_Full_View!$O:$O,MATCH($Z$46&"|"&ROWS($A$97:A109),[5]_Assessment_Full_View!$Q:$Q,0)),"") -> Verify | N109: =IFERROR(INDEX([5]_Assessment_Full_View!$P:$P,MATCH($Z$46&"|"&ROWS($A$97:A109),[5]_Assessment_Full_View!$Q:$Q,0)),"") -> Existing demarc/server rooms; verify existing rack inventory, operational continuity, active circuits, access control, airflow and protection-in-place.
... A120: =IFERROR(INDEX([5]_Assessment_Full_View!$E:$E,MATCH($Z$46&"|"&ROWS($A$97:A120),[5]_Assessment_Full_View!$Q:$Q,0)),"") -> 4. HVAC / COOLING | C120: =IFERROR(INDEX([5]_Assessment_Full_View!$G:$G,MATCH($Z$46&"|"&ROWS($A$97:A120),[5]_Assessment_Full_View!$Q:$Q,0))&" / "&INDEX([5]_Assessment_Full_View!$H:$H,MATCH($Z$46&"|"&ROWS($A$97:A120),[5]_Assessment_Full_View!$Q:$Q,0)),"") -> B13H-A / IU-0-01 / CU-0-01 | E120: =IFERROR(INDEX([5]_Assessment_Full_View!$I:$I,MATCH($Z$46&"|"&ROWS($A$97:A120),[5]_Assessment_Full_View!$Q:$Q,0))&" / "&INDEX([5]_Assessment_Full_View!$J:$J,MATCH($Z$46&"|"&ROWS($A$97:A120),[5]_Assessment_Full_View!$Q:$Q,0)),"") -> Verify / Verify | H120: =IFERROR(INDEX([5]_Assessment_Full_View!$K:$K,MATCH($Z$46&"|"&ROWS($A$97:A120),[5]_Assessment_Full_View!$Q:$Q,0))&" / "&INDEX([5]_Assessment_Full_View!$L:$L,MATCH($Z$46&"|"&ROWS($A$97:A120),[5]_Assessment_Full_View!$Q:$Q,0)),"") -> Verify / Verify | K120: =IFERROR(INDEX([5]_Assessment_Full_View!$O:$O,MATCH($Z$46&"|"&ROWS($A$97:A120),[5]_Assessment_Full_View!$Q:$Q,0)),"") -> Verify | N120: =IFERROR(INDEX([5]_Assessment_Full_View!$P:$P,MATCH($Z$46&"|"&ROWS($A$97:A120),[5]_Assessment_Full_View!$Q:$Q,0)),"") -> Mechanical sheets identify dedicated split-system cooling with BACnet adapter mounted adjacent to unit in telecom room. Confirm capacity, emergency source, condensate, disconnect, controls, and alarms.
A121: =IFERROR(INDEX([5]_Assessment_Full_View!$E:$E,MATCH($Z$46&"|"&ROWS($A$97:A121),[5]_Assessment_Full_View!$Q:$Q,0)),"") -> 4. HVAC / COOLING | C121: =IFERROR(INDEX([5]_Assessment_Full_View!$G:$G,MATCH($Z$46&"|"&ROWS($A$97:A121),[5]_Assessment_Full_View!$Q:$Q,0))&" / "&INDEX([5]_Assessment_Full_View!$H:$H,MATCH($Z$46&"|"&ROWS($A$97:A121),[5]_Assessment_Full_View!$Q:$Q,0)),"") -> 124 / IU-1-01 / CU-1-01 | E121: =IFERROR(INDEX([4]_Assessment_Full_View!$I:$I,MATCH($Z$46&"|"&ROWS($A$97:A121),[4]_Assessment_Full_View!$Q:$Q,0))&" / "&INDEX([4]_Assessment_Full_View!$J:$J,MATCH($Z$46&"|"&ROWS($A$97:A121),[4]_Assessment_Full_View!$Q:$Q,0)),"") -> Verify / Verify | H121: =IFERROR(INDEX([4]_Assessment_Full_View!$K:$K,MATCH($Z$46&"|"&ROWS($A$97:A121),[4]_Assessment_Full_View!$Q:$Q,0))&" / "&INDEX([4]_Assessment_Full_View!$L:$L,MATCH($Z$46&"|"&ROWS($A$97:A121),[4]_Assessment_Full_View!$Q:$Q,0)),"") -> Verify / Verify | K121: =IFERROR(INDEX([5]_Assessment_Full_View!$O:$O,MATCH($Z$46&"|"&ROWS($A$97:A121),[5]_Assessment_Full_View!$Q:$Q,0)),"") -> Verify | N121: =IFERROR(INDEX([5]_Assessment_Full_View!$P:$P,MATCH($Z$46&"|"&ROWS($A$97:A121),[5]_Assessment_Full_View!$Q:$Q,0)),"") -> Mechanical/electrical plans identify IU-1-01/CU-1-01 for first-level TR. Confirm 24/7 operation, emergency/standby source and high-temp alarm.

Sheet Command_Tile_Copy_Block
A1: COPY-READY COMMAND CENTER BUILDING TILE BLOCK
A2: Copy A3:P10 from this sheet and paste over Command_Center!A3:P10. Formulas use ⚠ for risks and ❓ for questions; tile fill is conditional on PMIS_Data readiness.
A3: =HYPERLINK("#'B01_Assessment'!A1","B01"&CHAR(10)&TEXT(IFERROR(INDEX(PMIS_Data!$E:$E,MATCH("01",PMIS_Data!$A:$A,0)),0),"0%")&" "&REPT("█",ROUND(IFERROR(INDEX(PMIS_Data!$E:$E,MATCH("01",PMIS_Data!$A:$A,0)),0)*10,0))&REPT("░",10-ROUND(IFERROR(INDEX(PMIS_Data!$E:$E,MATCH("01",PMIS_Data!$A:$A,0)),0)*10,0))&CHAR(10)&"⚠ "&IFERROR(INDEX(PMIS_Data!$H:$H,MATCH("01",PMIS_Data!$A:$A,0)),"-")&" ❓ "&IFERROR(INDEX(PMIS_Data!$I:$I,MATCH("01",PMIS_Data!$A:$A,0)),"-")&CHAR(10)&"↗ OPEN") -> B01 50% █████░░░░░ ⚠ 0 ❓ 0 ↗ OPEN | E3: =HYPERLINK("#'B02_Assessment'!A1","B02"&CHAR(10)&TEXT(IFERROR(INDEX(PMIS_Data!$E:$E,MATCH("02",PMIS_Data!$A:$A,0)),0),"0%")&" "&REPT("█",ROUND(IFERROR(INDEX(PMIS_Data!$E:$E,MATCH("02",PMIS_Data!$A:$A,0)),0)*10,0))&REPT("░",10-ROUND(IFERROR(INDEX(PMIS_Data!$E:$E,MATCH("02",PMIS_Data!$A:$A,0)),0)*10,0))&CHAR(10)&"⚠ "&IFERROR(INDEX(PMIS_Data!$H:$H,MATCH("02",PMIS_Data!$A:$A,0)),"-")&" ❓ "&IFERROR(INDEX(PMIS_Data!$I:$I,MATCH("02",PMIS_Data!$A:$A,0)),"-")&CHAR(10)&"↗ OPEN") -> B02 50% █████░░░░░ ⚠ 0 ❓ 0 ↗ OPEN | I3: =HYPERLINK("#'B03_Assessment'!A1","B03"&CHAR(10)&TEXT(IFERROR(INDEX(PMIS_Data!$E:$E,MATCH("03",PMIS_Data!$A:$A,0)),0),"0%")&" "&REPT("█",ROUND(IFERROR(INDEX(PMIS_Data!$E:$E,MATCH("03",PMIS_Data!$A:$A,0)),0)*10,0))&REPT("░",10-ROUND(IFERROR(INDEX(PMIS_Data!$E:$E,MATCH("03",PMIS_Data!$A:$A,0)),0)*10,0))&CHAR(10)&"⚠ "&IFERROR(INDEX(PMIS_Data!$H:$H,MATCH("03",PMIS_Data!$A:$A,0)),"-")&" ❓ "&IFERROR(INDEX(PMIS_Data!$I:$I,MATCH("03",PMIS_Data!$A:$A,0)),"-")&CHAR(10)&"↗ OPEN") -> B03 50% █████░░░░░ ⚠ 0 ❓ 0 ↗ OPEN | M3: =HYPERLINK("#'B04_Assessment'!A1","B04"&CHAR(10)&TEXT(IFERROR(INDEX(PMIS_Data!$E:$E,MATCH("04",PMIS_Data!$A:$A,0)),0),"0%")&" "&REPT("█",ROUND(IFERROR(INDEX(PMIS_Data!$E:$E,MATCH("04",PMIS_Data!$A:$A,0)),0)*10,0))&REPT("░",10-ROUND(IFERROR(INDEX(PMIS_Data!$E:$E,MATCH("04",PMIS_Data!$A:$A,0)),0)*10,0))&CHAR(10)&"⚠ "&IFERROR(INDEX(PMIS_Data!$H:$H,MATCH("04",PMIS_Data!$A:$A,0)),"-")&" ❓ "&IFERROR(INDEX(PMIS_Data!$I:$I,MATCH("04",PMIS_Data!$A:$A,0)),"-")&CHAR(10)&"↗ OPEN") -> B04 50% █████░░░░░ ⚠ 0 ❓ 0 ↗ OPEN
A4: =HYPERLINK("#'B05_Assessment'!A1","B05"&CHAR(10)&TEXT(IFERROR(INDEX(PMIS_Data!$E:$E,MATCH("05",PMIS_Data!$A:$A,0)),0),"0%")&" "&REPT("█",ROUND(IFERROR(INDEX(PMIS_Data!$E:$E,MATCH("05",PMIS_Data!$A:$A,0)),0)*10,0))&REPT("░",10-ROUND(IFERROR(INDEX(PMIS_Data!$E:$E,MATCH("05",PMIS_Data!$A:$A,0)),0)*10,0))&CHAR(10)&"⚠ "&IFERROR(INDEX(PMIS_Data!$H:$H,MATCH("05",PMIS_Data!$A:$A,0)),"-")&" ❓ "&IFERROR(INDEX(PMIS_Data!$I:$I,MATCH("05",PMIS_Data!$A:$A,0)),"-")&CHAR(10)&"↗ OPEN") -> B05 55% ██████░░░░ ⚠ 0 ❓ 0 ↗ OPEN | E4: =HYPERLINK("#'B06_Assessment'!A1","B06"&CHAR(10)&TEXT(IFERROR(INDEX(PMIS_Data!$E:$E,MATCH("06",PMIS_Data!$A:$A,0)),0),"0%")&" "&REPT("█",ROUND(IFERROR(INDEX(PMIS_Data!$E:$E,MATCH("06",PMIS_Data!$A:$A,0)),0)*10,0))&REPT("░",10-ROUND(IFERROR(INDEX(PMIS_Data!$E:$E,MATCH("06",PMIS_Data!$A:$A,0)),0)*10,0))&CHAR(10)&"⚠ "&IFERROR(INDEX(PMIS_Data!$H:$H,MATCH("06",PMIS_Data!$A:$A,0)),"-")&" ❓ "&IFERROR(INDEX(PMIS_Data!$I:$I,MATCH("06",PMIS_Data!$A:$A,0)),"-")&CHAR(10)&"↗ OPEN") -> B06 50% █████░░░░░ ⚠ 0 ❓ 0 ↗ OPEN | I4: =HYPERLINK("#'B07_Assessment'!A1","B07"&CHAR(10)&TEXT(IFERROR(INDEX(PMIS_Data!$E:$E,MATCH("07",PMIS_Data!$A:$A,0)),0),"0%")&" "&REPT("█",ROUND(IFERROR(INDEX(PMIS_Data!$E:$E,MATCH("07",PMIS_Data!$A:$A,0)),0)*10,0))&REPT("░",10-ROUND(IFERROR(INDEX(PMIS_Data!$E:$E,MATCH("07",PMIS_Data!$A:$A,0)),0)*10,0))&CHAR(10)&"⚠ "&IFERROR(INDEX(PMIS_Data!$H:$H,MATCH("07",PMIS_Data!$A:$A,0)),"-")&" ❓ "&IFERROR(INDEX(PMIS_Data!$I:$I,MATCH("07",PMIS_Data!$A:$A,0)),"-")&CHAR(10)&"↗ OPEN") -> B07 50% █████░░░░░ ⚠ 0 ❓ 0 ↗ OPEN | M4: =HYPERLINK("#'B08_Assessment'!A1","B08"&CHAR(10)&TEXT(IFERROR(INDEX(PMIS_Data!$E:$E,MATCH("08",PMIS_Data!$A:$A,0)),0),"0%")&" "&REPT("█",ROUND(IFERROR(INDEX(PMIS_Data!$E:$E,MATCH("08",PMIS_Data!$A:$A,0)),0)*10,0))&REPT("░",10-ROUND(IFERROR(INDEX(PMIS_Data!$E:$E,MATCH("08",PMIS_Data!$A:$A,0)),0)*10,0))&CHAR(10)&"⚠ "&IFERROR(INDEX(PMIS_Data!$H:$H,MATCH("08",PMIS_Data!$A:$A,0)),"-")&" ❓ "&IFERROR(INDEX(PMIS_Data!$I:$I,MATCH("08",PMIS_Data!$A:$A,0)),"-")&CHAR(10)&"↗ OPEN") -> B08 50% █████░░░░░ ⚠ 0 ❓ 0 ↗ OPEN
A5: =HYPERLINK("#'B09_Assessment'!A1","B09"&CHAR(10)&TEXT(IFERROR(INDEX(PMIS_Data!$E:$E,MATCH("09",PMIS_Data!$A:$A,0)),0),"0%")&" "&REPT("█",ROUND(IFERROR(INDEX(PMIS_Data!$E:$E,MATCH("09",PMIS_Data!$A:$A,0)),0)*10,0))&REPT("░",10-ROUND(IFERROR(INDEX(PMIS_Data!$E:$E,MATCH("09",PMIS_Data!$A:$A,0)),0)*10,0))&CHAR(10)&"⚠ "&IFERROR(INDEX(PMIS_Data!$H:$H,MATCH("09",PMIS_Data!$A:$A,0)),"-")&" ❓ "&IFERROR(INDEX(PMIS_Data!$I:$I,MATCH("09",PMIS_Data!$A:$A,0)),"-")&CHAR(10)&"↗ OPEN") -> B09 50% █████░░░░░ ⚠ 0 ❓ 0 ↗ OPEN | E5: =HYPERLINK("#'B10_Assessment'!A1","B10"&CHAR(10)&TEXT(IFERROR(INDEX(PMIS_Data!$E:$E,MATCH("10",PMIS_Data!$A:$A,0)),0),"0%")&" "&REPT("█",ROUND(IFERROR(INDEX(PMIS_Data!$E:$E,MATCH("10",PMIS_Data!$A:$A,0)),0)*10,0))&REPT("░",10-ROUND(IFERROR(INDEX(PMIS_Data!$E:$E,MATCH("10",PMIS_Data!$A:$A,0)),0)*10,0))&CHAR(10)&"⚠ "&IFERROR(INDEX(PMIS_Data!$H:$H,MATCH("10",PMIS_Data!$A:$A,0)),"-")&" ❓ "&IFERROR(INDEX(PMIS_Data!$I:$I,MATCH("10",PMIS_Data!$A:$A,0)),"-")&CHAR(10)&"↗ OPEN") -> B10 50% █████░░░░░ ⚠ 0 ❓ 0 ↗ OPEN | I5: =HYPERLINK("#'B12_Assessment'!A1","B12"&CHAR(10)&TEXT(IFERROR(INDEX(PMIS_Data!$E:$E,MATCH("12",PMIS_Data!$A:$A,0)),0),"0%")&" "&REPT("█",ROUND(IFERROR(INDEX(PMIS_Data!$E:$E,MATCH("12",PMIS_Data!$A:$A,0)),0)*10,0))&REPT("░",10-ROUND(IFERROR(INDEX(PMIS_Data!$E:$E,MATCH("12",PMIS_Data!$A:$A,0)),0)*10,0))&CHAR(10)&"⚠ "&IFERROR(INDEX(PMIS_Data!$H:$H,MATCH("12",PMIS_Data!$A:$A,0)),"-")&" ❓ "&IFERROR(INDEX(PMIS_Data!$I:$I,MATCH("12",PMIS_Data!$A:$A,0)),"-")&CHAR(10)&"↗ OPEN") -> B12 60% ██████░░░░ ⚠ 0 ❓ 0 ↗ OPEN | M5: =HYPERLINK("#'B13_Assessment'!A1","B13"&CHAR(10)&TEXT(IFERROR(INDEX(PMIS_Data!$E:$E,MATCH("13",PMIS_Data!$A:$A,0)),0),"0%")&" "&REPT("█",ROUND(IFERROR(INDEX(PMIS_Data!$E:$E,MATCH("13",PMIS_Data!$A:$A,0)),0)*10,0))&REPT("░",10-ROUND(IFERROR(INDEX(PMIS_Data!$E:$E,MATCH("13",PMIS_Data!$A:$A,0)),0)*10,0))&CHAR(10)&"⚠ "&IFERROR(INDEX(PMIS_Data!$H:$H,MATCH("13",PMIS_Data!$A:$A,0)),"-")&" ❓ "&IFERROR(INDEX(PMIS_Data!$I:$I,MATCH("13",PMIS_Data!$A:$A,0)),"-")&CHAR(10)&"↗ OPEN") -> B13 50% █████░░░░░ ⚠ 0 ❓ 0 ↗ OPEN
A6: =HYPERLINK("#'B14_Assessment'!A1","B14"&CHAR(10)&TEXT(IFERROR(INDEX(PMIS_Data!$E:$E,MATCH("14",PMIS_Data!$A:$A,0)),0),"0%")&" "&REPT("█",ROUND(IFERROR(INDEX(PMIS_Data!$E:$E,MATCH("14",PMIS_Data!$A:$A,0)),0)*10,0))&REPT("░",10-ROUND(IFERROR(INDEX(PMIS_Data!$E:$E,MATCH("14",PMIS_Data!$A:$A,0)),0)*10,0))&CHAR(10)&"⚠ "&IFERROR(INDEX(PMIS_Data!$H:$H,MATCH("14",PMIS_Data!$A:$A,0)),"-")&" ❓ "&IFERROR(INDEX(PMIS_Data!$I:$I,MATCH("14",PMIS_Data!$A:$A,0)),"-")&CHAR(10)&"↗ OPEN") -> B14 50% █████░░░░░ ⚠ 0 ❓ 0 ↗ OPEN | E6: =HYPERLINK("#'B15_Assessment'!A1","B15"&CHAR(10)&TEXT(IFERROR(INDEX(PMIS_Data!$E:$E,MATCH("15",PMIS_Data!$A:$A,0)),0),"0%")&" "&REPT("█",ROUND(IFERROR(INDEX(PMIS_Data!$E:$E,MATCH("15",PMIS_Data!$A:$A,0)),0)*10,0))&REPT("░",10-ROUND(IFERROR(INDEX(PMIS_Data!$E:$E,MATCH("15",PMIS_Data!$A:$A,0)),0)*10,0))&CHAR(10)&"⚠ "&IFERROR(INDEX(PMIS_Data!$H:$H,MATCH("15",PMIS_Data!$A:$A,0)),"-")&" ❓ "&IFERROR(INDEX(PMIS_Data!$I:$I,MATCH("15",PMIS_Data!$A:$A,0)),"-")&CHAR(10)&"↗ OPEN") -> B15 50% █████░░░░░ ⚠ 0 ❓ 0 ↗ OPEN | I6: =HYPERLINK("#'B16_Assessment'!A1","B16"&CHAR(10)&TEXT(IFERROR(INDEX(PMIS_Data!$E:$E,MATCH("16",PMIS_Data!$A:$A,0)),0),"0%")&" "&REPT("█",ROUND(IFERROR(INDEX(PMIS_Data!$E:$E,MATCH("16",PMIS_Data!$A:$A,0)),0)*10,0))&REPT("░",10-ROUND(IFERROR(INDEX(PMIS_Data!$E:$E,MATCH("16",PMIS_Data!$A:$A,0)),0)*10,0))&CHAR(10)&"⚠ "&IFERROR(INDEX(PMIS_Data!$H:$H,MATCH("16",PMIS_Data!$A:$A,0)),"-")&" ❓ "&IFERROR(INDEX(PMIS_Data!$I:$I,MATCH("16",PMIS_Data!$A:$A,0)),"-")&CHAR(10)&"↗ OPEN") -> B16 50% █████░░░░░ ⚠ 0 ❓ 0 ↗ OPEN | M6: =HYPERLINK("#'B17_Assessment'!A1","B17"&CHAR(10)&TEXT(IFERROR(INDEX(PMIS_Data!$E:$E,MATCH("17",PMIS_Data!$A:$A,0)),0),"0%")&" "&REPT("█",ROUND(IFERROR(INDEX(PMIS_Data!$E:$E,MATCH("17",PMIS_Data!$A:$A,0)),0)*10,0))&REPT("░",10-ROUND(IFERROR(INDEX(PMIS_Data!$E:$E,MATCH("17",PMIS_Data!$A:$A,0)),0)*10,0))&CHAR(10)&"⚠ "&IFERROR(INDEX(PMIS_Data!$H:$H,MATCH("17",PMIS_Data!$A:$A,0)),"-")&" ❓ "&IFERROR(INDEX(PMIS_Data!$I:$I,MATCH("17",PMIS_Data!$A:$A,0)),"-")&CHAR(10)&"↗ OPEN") -> B17 50% █████░░░░░ ⚠ 0 ❓ 0 ↗ OPEN
A7: =HYPERLINK("#'B18_Assessment'!A1","B18"&CHAR(10)&TEXT(IFERROR(INDEX(PMIS_Data!$E:$E,MATCH("18",PMIS_Data!$A:$A,0)),0),"0%")&" "&REPT("█",ROUND(IFERROR(INDEX(PMIS_Data!$E:$E,MATCH("18",PMIS_Data!$A:$A,0)),0)*10,0))&REPT("░",10-ROUND(IFERROR(INDEX(PMIS_Data!$E:$E,MATCH("18",PMIS_Data!$A:$A,0)),0)*10,0))&CHAR(10)&"⚠ "&IFERROR(INDEX(PMIS_Data!$H:$H,MATCH("18",PMIS_Data!$A:$A,0)),"-")&" ❓ "&IFERROR(INDEX(PMIS_Data!$I:$I,MATCH("18",PMIS_Data!$A:$A,0)),"-")&CHAR(10)&"↗ OPEN") -> B18 50% █████░░░░░ ⚠ 0 ❓ 0 ↗ OPEN | E7: =HYPERLINK("#'B20_Assessment'!A1","B20"&CHAR(10)&TEXT(IFERROR(INDEX(PMIS_Data!$E:$E,MATCH("20",PMIS_Data!$A:$A,0)),0),"0%")&" "&REPT("█",ROUND(IFERROR(INDEX(PMIS_Data!$E:$E,MATCH("20",PMIS_Data!$A:$A,0)),0)*10,0))&REPT("░",10-ROUND(IFERROR(INDEX(PMIS_Data!$E:$E,MATCH("20",PMIS_Data!$A:$A,0)),0)*10,0))&CHAR(10)&"⚠ "&IFERROR(INDEX(PMIS_Data!$H:$H,MATCH("20",PMIS_Data!$A:$A,0)),"-")&" ❓ "&IFERROR(INDEX(PMIS_Data!$I:$I,MATCH("20",PMIS_Data!$A:$A,0)),"-")&CHAR(10)&"↗ OPEN") -> B20 50% █████░░░░░ ⚠ 0 ❓ 0 ↗ OPEN | I7: =HYPERLINK("#'B21_Assessment'!A1","B21"&CHAR(10)&TEXT(IFERROR(INDEX(PMIS_Data!$E:$E,MATCH("21",PMIS_Data!$A:$A,0)),0),"0%")&" "&REPT("█",ROUND(IFERROR(INDEX(PMIS_Data!$E:$E,MATCH("21",PMIS_Data!$A:$A,0)),0)*10,0))&REPT("░",10-ROUND(IFERROR(INDEX(PMIS_Data!$E:$E,MATCH("21",PMIS_Data!$A:$A,0)),0)*10,0))&CHAR(10)&"⚠ "&IFERROR(INDEX(PMIS_Data!$H:$H,MATCH("21",PMIS_Data!$A:$A,0)),"-")&" ❓ "&IFERROR(INDEX(PMIS_Data!$I:$I,MATCH("21",PMIS_Data!$A:$A,0)),"-")&CHAR(10)&"↗ OPEN") -> B21 50% █████░░░░░ ⚠ 0 ❓ 0 ↗ OPEN | M7: =HYPERLINK("#'B22_Assessment'!A1","B22"&CHAR(10)&TEXT(IFERROR(INDEX(PMIS_Data!$E:$E,MATCH("22",PMIS_Data!$A:$A,0)),0),"0%")&" "&REPT("█",ROUND(IFERROR(INDEX(PMIS_Data!$E:$E,MATCH("22",PMIS_Data!$A:$A,0)),0)*10,0))&REPT("░",10-ROUND(IFERROR(INDEX(PMIS_Data!$E:$E,MATCH("22",PMIS_Data!$A:$A,0)),0)*10,0))&CHAR(10)&"⚠ "&IFERROR(INDEX(PMIS_Data!$H:$H,MATCH("22",PMIS_Data!$A:$A,0)),"-")&" ❓ "&IFERROR(INDEX(PMIS_Data!$I:$I,MATCH("22",PMIS_Data!$A:$A,0)),"-")&CHAR(10)&"↗ OPEN") -> B22 50% █████░░░░░ ⚠ 0 ❓ 0 ↗ OPEN
A8: =HYPERLINK("#'B33_Assessment'!A1","B33"&CHAR(10)&TEXT(IFERROR(INDEX(PMIS_Data!$E:$E,MATCH("33",PMIS_Data!$A:$A,0)),0),"0%")&" "&REPT("█",ROUND(IFERROR(INDEX(PMIS_Data!$E:$E,MATCH("33",PMIS_Data!$A:$A,0)),0)*10,0))&REPT("░",10-ROUND(IFERROR(INDEX(PMIS_Data!$E:$E,MATCH("33",PMIS_Data!$A:$A,0)),0)*10,0))&CHAR(10)&"⚠ "&IFERROR(INDEX(PMIS_Data!$H:$H,MATCH("33",PMIS_Data!$A:$A,0)),"-")&" ❓ "&IFERROR(INDEX(PMIS_Data!$I:$I,MATCH("33",PMIS_Data!$A:$A,0)),"-")&CHAR(10)&"↗ OPEN") -> B33 50% █████░░░░░ ⚠ 0 ❓ 0 ↗ OPEN | E8: =HYPERLINK("#'B61_Assessment'!A1","B61"&CHAR(10)&TEXT(IFERROR(INDEX(PMIS_Data!$E:$E,MATCH("61",PMIS_Data!$A:$A,0)),0),"0%")&" "&REPT("█",ROUND(IFERROR(INDEX(PMIS_Data!$E:$E,MATCH("61",PMIS_Data!$A:$A,0)),0)*10,0))&REPT("░",10-ROUND(IFERROR(INDEX(PMIS_Data!$E:$E,MATCH("61",PMIS_Data!$A:$A,0)),0)*10,0))&CHAR(10)&"⚠ "&IFERROR(INDEX(PMIS_Data!$H:$H,MATCH("61",PMIS_Data!$A:$A,0)),"-")&" ❓ "&IFERROR(INDEX(PMIS_Data!$I:$I,MATCH("61",PMIS_Data!$A:$A,0)),"-")&CHAR(10)&"↗ OPEN") -> B61 55% ██████░░░░ ⚠ 0 ❓ 0 ↗ OPEN | I8: =HYPERLINK("#'B62_TR_Assessment'!A1","B62"&CHAR(10)&TEXT(IFERROR(INDEX(PMIS_Data!$E:$E,MATCH("62",PMIS_Data!$A:$A,0)),0),"0%")&" "&REPT("█",ROUND(IFERROR(INDEX(PMIS_Data!$E:$E,MATCH("62",PMIS_Data!$A:$A,0)),0)*10,0))&REPT("░",10-ROUND(IFERROR(INDEX(PMIS_Data!$E:$E,MATCH("62",PMIS_Data!$A:$A,0)),0)*10,0))&CHAR(10)&"⚠ "&IFERROR(INDEX(PMIS_Data!$H:$H,MATCH("62",PMIS_Data!$A:$A,0)),"-")&" ❓ "&IFERROR(INDEX(PMIS_Data!$I:$I,MATCH("62",PMIS_Data!$A:$A,0)),"-")&CHAR(10)&"↗ OPEN") -> B62 50% █████░░░░░ ⚠ 0 ❓ 0 ↗ OPEN | M8: =HYPERLINK("#'B70_TR_Assessment'!A1","B70"&CHAR(10)&TEXT(IFERROR(INDEX(PMIS_Data!$E:$E,MATCH("70",PMIS_Data!$A:$A,0)),0),"0%")&" "&REPT("█",ROUND(IFERROR(INDEX(PMIS_Data!$E:$E,MATCH("70",PMIS_Data!$A:$A,0)),0)*10,0))&REPT("░",10-ROUND(IFERROR(INDEX(PMIS_Data!$E:$E,MATCH("70",PMIS_Data!$A:$A,0)),0)*10,0))&CHAR(10)&"⚠ "&IFERROR(INDEX(PMIS_Data!$H:$H,MATCH("70",PMIS_Data!$A:$A,0)),"-")&" ❓ "&IFERROR(INDEX(PMIS_Data!$I:$I,MATCH("70",PMIS_Data!$A:$A,0)),"-")&CHAR(10)&"↗ OPEN") -> B70 50% █████░░░░░ ⚠ 0 ❓ 0 ↗ OPEN
A9: =HYPERLINK("#'B78_Assessment'!A1","B78"&CHAR(10)&TEXT(IFERROR(INDEX(PMIS_Data!$E:$E,MATCH("78",PMIS_Data!$A:$A,0)),0),"0%")&" "&REPT("█",ROUND(IFERROR(INDEX(PMIS_Data!$E:$E,MATCH("78",PMIS_Data!$A:$A,0)),0)*10,0))&REPT("░",10-ROUND(IFERROR(INDEX(PMIS_Data!$E:$E,MATCH("78",PMIS_Data!$A:$A,0)),0)*10,0))&CHAR(10)&"⚠ "&IFERROR(INDEX(PMIS_Data!$H:$H,MATCH("78",PMIS_Data!$A:$A,0)),"-")&" ❓ "&IFERROR(INDEX(PMIS_Data!$I:$I,MATCH("78",PMIS_Data!$A:$A,0)),"-")&CHAR(10)&"↗ OPEN") -> B78 50% █████░░░░░ ⚠ 0 ❓ 0 ↗ OPEN | E9: =HYPERLINK("#'B80_Assessment'!A1","B80"&CHAR(10)&TEXT(IFERROR(INDEX(PMIS_Data!$E:$E,MATCH("80",PMIS_Data!$A:$A,0)),0),"0%")&" "&REPT("█",ROUND(IFERROR(INDEX(PMIS_Data!$E:$E,MATCH("80",PMIS_Data!$A:$A,0)),0)*10,0))&REPT("░",10-ROUND(IFERROR(INDEX(PMIS_Data!$E:$E,MATCH("80",PMIS_Data!$A:$A,0)),0)*10,0))&CHAR(10)&"⚠ "&IFERROR(INDEX(PMIS_Data!$H:$H,MATCH("80",PMIS_Data!$A:$A,0)),"-")&" ❓ "&IFERROR(INDEX(PMIS_Data!$I:$I,MATCH("80",PMIS_Data!$A:$A,0)),"-")&CHAR(10)&"↗ OPEN") -> B80 50% █████░░░░░ ⚠ 0 ❓ 0 ↗ OPEN | I9: =HYPERLINK("#'B82_Assessment'!A1","B82"&CHAR(10)&TEXT(IFERROR(INDEX(PMIS_Data!$E:$E,MATCH("82",PMIS_Data!$A:$A,0)),0),"0%")&" "&REPT("█",ROUND(IFERROR(INDEX(PMIS_Data!$E:$E,MATCH("82",PMIS_Data!$A:$A,0)),0)*10,0))&REPT("░",10-ROUND(IFERROR(INDEX(PMIS_Data!$E:$E,MATCH("82",PMIS_Data!$A:$A,0)),0)*10,0))&CHAR(10)&"⚠ "&IFERROR(INDEX(PMIS_Data!$H:$H,MATCH("82",PMIS_Data!$A:$A,0)),"-")&" ❓ "&IFERROR(INDEX(PMIS_Data!$I:$I,MATCH("82",PMIS_Data!$A:$A,0)),"-")&CHAR(10)&"↗ OPEN") -> B82 50% █████░░░░░ ⚠ 0 ❓ 0 ↗ OPEN | M9: =HYPERLINK("#'BCH_Assessment'!A1","BCH"&CHAR(10)&TEXT(IFERROR(INDEX(PMIS_Data!$E:$E,MATCH("BCH",PMIS_Data!$A:$A,0)),0),"0%")&" "&REPT("█",ROUND(IFERROR(INDEX(PMIS_Data!$E:$E,MATCH("BCH",PMIS_Data!$A:$A,0)),0)*10,0))&REPT("░",10-ROUND(IFERROR(INDEX(PMIS_Data!$E:$E,MATCH("BCH",PMIS_Data!$A:$A,0)),0)*10,0))&CHAR(10)&"⚠ "&IFERROR(INDEX(PMIS_Data!$H:$H,MATCH("BCH",PMIS_Data!$A:$A,0)),"-")&" ❓ "&IFERROR(INDEX(PMIS_Data!$I:$I,MATCH("BCH",PMIS_Data!$A:$A,0)),"-")&CHAR(10)&"↗ OPEN") -> BCH 50% █████░░░░░ ⚠ 0 ❓ 0 ↗ OPEN
A10: =HYPERLINK("#'MCR_Assessment'!A1","MCR"&CHAR(10)&TEXT(IFERROR(INDEX(PMIS_Data!$E:$E,MATCH("MCR",PMIS_Data!$A:$A,0)),0),"0%")&" "&REPT("█",ROUND(IFERROR(INDEX(PMIS_Data!$E:$E,MATCH("MCR",PMIS_Data!$A:$A,0)),0)*10,0))&REPT("░",10-ROUND(IFERROR(INDEX(PMIS_Data!$E:$E,MATCH("MCR",PMIS_Data!$A:$A,0)),0)*10,0))&CHAR(10)&"⚠ "&IFERROR(INDEX(PMIS_Data!$H:$H,MATCH("MCR",PMIS_Data!$A:$A,0)),"-")&" ❓ "&IFERROR(INDEX(PMIS_Data!$I:$I,MATCH("MCR",PMIS_Data!$A:$A,0)),"-")&CHAR(10)&"↗ OPEN") -> MCR 50% █████░░░░░ ⚠ 0 ❓ 0 ↗ OPEN | E10: =HYPERLINK("#'SITE_Assesment'!A1","SITE"&CHAR(10)&TEXT(IFERROR(INDEX(PMIS_Data!$E:$E,MATCH("SITE",PMIS_Data!$A:$A,0)),0),"0%")&" "&REPT("█",ROUND(IFERROR(INDEX(PMIS_Data!$E:$E,MATCH("SITE",PMIS_Data!$A:$A,0)),0)*10,0))&REPT("░",10-ROUND(IFERROR(INDEX(PMIS_Data!$E:$E,MATCH("SITE",PMIS_Data!$A:$A,0)),0)*10,0))&CHAR(10)&"⚠ "&IFERROR(INDEX(PMIS_Data!$H:$H,MATCH("SITE",PMIS_Data!$A:$A,0)),"-")&" ❓ "&IFERROR(INDEX(PMIS_Data!$I:$I,MATCH("SITE",PMIS_Data!$A:$A,0)),"-")&CHAR(10)&"↗ OPEN") -> SITE 50% █████░░░░░ ⚠ 0 ❓ 0 ↗ OPEN | I10: =HYPERLINK("#'SPEC_Assessment'!A1","SPEC"&CHAR(10)&TEXT(IFERROR(INDEX(PMIS_Data!$E:$E,MATCH("SPEC",PMIS_Data!$A:$A,0)),0),"0%")&" "&REPT("█",ROUND(IFERROR(INDEX(PMIS_Data!$E:$E,MATCH("SPEC",PMIS_Data!$A:$A,0)),0)*10,0))&REPT("░",10-ROUND(IFERROR(INDEX(PMIS_Data!$E:$E,MATCH("SPEC",PMIS_Data!$A:$A,0)),0)*10,0))&CHAR(10)&"⚠ "&IFERROR(INDEX(PMIS_Data!$H:$H,MATCH("SPEC",PMIS_Data!$A:$A,0)),"-")&" ❓ "&IFERROR(INDEX(PMIS_Data!$I:$I,MATCH("SPEC",PMIS_Data!$A:$A,0)),"-")&CHAR(10)&"↗ OPEN") -> SPEC 0% ░░░░░░░░░░ ⚠ - ❓ - ↗ OPEN

Sheet Executive Brief
A1: BEDFORD VA EHRM | E1: BEDFORD VA EHRM PROGRAM | Y1: =TODAY() -> 46220
E2: COMMAND CENTER – EXECUTIVE BRIEF | Y2: =TEXT(TODAY(),"dddd") -> Friday
E3: One Campus. One Plan. One Standard.
A5: CAMPUS READINESS | F5: BUILDINGS ASSESSED | K5: CONSTRUCTION READY | P5: OPEN QUESTIONS | U5: OPEN RISKS | AA5: SHUTDOWNS
B7: =Command_Center!B14 -> 0.50666667 | G7: =Command_Center!D14 -> 30 | L7: =MAX(0,Command_Center!D14-Command_Center!N14) -> 1 | Q7: =Command_Center!H14 -> 0 | V7: =Command_Center!F14 -> 0 | AB7: =Command_Center!L14 -> 0
B10: Overall Average | G10: Assessment Sheets | L10: =Command_Center!N14&" Not Ready" -> 29 Not Ready | Q10: Campus Total | V10: Campus Total | AB10: Active
A14: ACTIVE BUILDING | J14: ="TRADE READINESS – BUILDING "&TEXT(Command_Center!C17,"00") -> TRADE READINESS – BUILDING 61 | T14: ="MISSION INTELLIGENCE – BUILDING "&TEXT(Command_Center!C17,"00") -> MISSION INTELLIGENCE – BUILDING 61
A15: BUILDING PHOTO PLACEHOLDER | E15: ='COMMAND CENTERS'!C17 -> 61 | J15: TRADE | P15: STATUS | R15: TREND
T16: Open Questions | AA16: =Command_Center!H32 -> 0
J17: Fire Protection | O17: =IF(ISNUMBER(SEARCH("Pass",Command_Center!L18)),"✓ PASS",IF(ISNUMBER(SEARCH("Review",Command_Center!L18)),"⚠ REVIEW",Command_Center!L18)) -> FIRE Not Started | R17: ↗
T18: Open Risks | AA18: =Command_Center!D32 -> 0
J19: HVAC | O19: =IF(ISNUMBER(SEARCH("Pass",Command_Center!J21)),"✓ PASS",IF(ISNUMBER(SEARCH("Review",Command_Center!J21)),"⚠ REVIEW",Command_Center!J21)) -> HVAC Not Started | R19: ↗
T20: Open Photos | AA20: =Command_Center!L32 -> 0
E21: ="READINESS SCORE"&CHAR(10)&TEXT(Command_Center!F19,"0%") -> READINESS SCORE 55% | J21: Electrical | O21: =IF(ISNUMBER(SEARCH("Pass",Command_Center!L21)),"✓ PASS",IF(ISNUMBER(SEARCH("Review",Command_Center!L21)),"⚠ REVIEW",Command_Center!L21)) -> ELECTRICAL Not Started | R21: ↗
T22: Active Shutdowns | AA22: =Command_Center!N32 -> Selected Active
J23: Telecom / IT | O23: =IF(ISNUMBER(SEARCH("Pass",Command_Center!J24)),"✓ PASS",IF(ISNUMBER(SEARCH("Review",Command_Center!J24)),"⚠ REVIEW",Command_Center!J24)) -> TELECOM Not Started | R23: ↗
T24: Campus Questions | AA24: =Command_Center!H14 -> 0
J25: Security | O25: =IF(ISNUMBER(SEARCH("Pass",Command_Center!L24)),"✓ PASS",IF(ISNUMBER(SEARCH("Review",Command_Center!L24)),"⚠ REVIEW",Command_Center!L24)) -> SECURITY Not Started | R25: ↗
T26: Campus Risks | AA26: =Command_Center!F14 -> 0
A28: ="Assessment Sheet: "&Command_Center!C20 -> Assessment Sheet: B61_Assessment
A29: ="Selected Status: "&Command_Center!C22 -> Selected Status: PILOT PHASE
F32: PAYMENT CONFIDENCE | H32: PAYMENT DECISION | K32: OIT READINESS | L32: OIT STATUS | M32: OIT BLOCKERS | O32: MATERIAL COMPLIANCE | P32: PRODUCTIVITY | Q32: ACCEPTANCE READINESS | S32: OWNER DECISION
F33: ='COMMAND CENTERS'!C46 -> 0 | H33: ='COMMAND CENTERS'!D46 -> Withhold / Review | K33: ='COMMAND CENTERS'!E46 -> 0 | L33: ='COMMAND CENTERS'!F46 -> Blocked | M33: ='COMMAND CENTERS'!G46 -> No blocker documented | O33: ='COMMAND CENTERS'!H46 -> 0 | P33: ='COMMAND CENTERS'!I46 -> 0 | Q33: ='COMMAND CENTERS'!J46 -> 0 | S33: ='COMMAND CENTERS'!K46 -> Resolve OIT Blocker
B35: =Command_Center!J84 -> 0
